Workbook
Name Issue_Type: Table3[Issue Type]
Name Slicer_Impact: #N/A
Name Slicer_Impact1: #N/A
Name Slicer_Issue_owner1: #N/A
Name Slicer_Issue_Type: #N/A
Name Slicer_Name: #N/A
Name Slicer_Name1: #N/A
Name Slicer_Priority_by_Alfanar: #N/A
Name Slicer_Priority_by_SEC: #N/A
Name Slicer_Project: #N/A
Name Slicer_Project1: #N/A
Name Slicer_Region: #N/A
Name Slicer_Status: #N/A

Sheet Sheet3
A1: Supply chain-Purchasing
A2: Resource Department
A3: Treasury

Sheet All Issues
X2: A | Y2: Extremely High
X3: B | Y3: High
X4: C | Y4: Medium
Y5: Low
W8: AES-WESTERN | X8: Alfanar AES Meeting Updated Tracker Status 28th May 25.xlsx
B10: Project | C10: Project Name | D10: Project Manager | E10: Region | F10: SN | G10: Issue owner | H10: Name | I10: Issue Type | J10: Date Issued | K10: Main Issue | L10: Impact | M10: Action Taken | N10: Action Required | O10: Priority By SEC | P10: Priority by Alfanar | Q10: Action By | R10: Planned Target | S10: Forecast/Expected Target | T10: Status | U10: (Schedule/Cost)Impact | V10: Remarks | W10: Cost | X10: PO Status
B11: PE-243 | C11: (DRPC) at Tabuk 380KV BSP | D11: Shafqat Zia | E11: Western | F11: 1 | G11: Alfanar | H11: Supply chain-Purchasing | I11: Delivery | K11: Revised Purchase order for TSC panel to GE from SCD | L11: High | M11: PM following with SCD to issues the p.o, Budget supplement of TSC Panel is under Ex VP approval | N11: SCD need to be issued the P.O to GE, it will affect the FAC issuance | O11: A | P11: A | Q11: PM/SCD/RM | T11: Closed
B12: PE-243 | C12: (DRPC) at Tabuk 380KV BSP | D12: Shafqat Zia | E12: Western | F12: 1 | G12: Alfanar | H12: Supply chain-Purchasing | I12: VO/EOT | K12: SCD need to finalize Alfanar claim to GE (10.2 million SAR) | L12: High | M12: PM following with scd settle the claim, Diemention changes in the tranformer. | N12: SCD need to be settled alfanar claim at earliest | O12: A | P12: A | Q12: PM/SCD/RM | T12: Closed
B13: PE-270 | C13: 110/13.8KV HARAZAT SUB JEDDAH | D13: Muhammed Ilyas | E13: Western | F13: 1 | G13: Client | H13: SEC | I13: Client Issues | K13: Fiber & Data Route Establishment | L13: High | M13: Following with SEC | N13: SEC need to provide | O13: A | P13: A | Q13: PM | T13: Closed | V13: For Energization
B14: PE-270 | C14: 110/13.8KV HARAZAT SUB JEDDAH | D14: Muhammed Ilyas | E14: Western | F14: 1 | G14: Client | H14: SEC | I14: Client Issues | K14: 1. Final Settings of Line Protection Panels. (Testing will be done, once line readiness from client). 2. AMI integration with WRCC | L14: High | M14: Following up with SEC | N14: SEC need to expedite | O14: A | P14: A | Q14: PM | S14: Dependent on Line Readiness from Client | T14: Open | V14: For Energization
B15: PE-265 | C15: 110/33 KV ALMAHANI S/S IN TAIF | D15: Sohaib Afdal | E15: Western | F15: 1 | G15: Vendor | H15: HITACHI | I15: Delivery | K15: Complete Production (11 bays) status for the 110kv GIS and LCC panels, not yet confirmed by Hitachi | L15: High | M15: Email communication and followup with Hitachi team to expeditet the delivery | N15: Hitachi need to confirm the status of Complete produciton status and FAT Date. As per p.o terms delivery by 28th Jan 25. | O15: A | P15: A | Q15: Vendor | R15: 45784 | T15: Closed | X15: "P.O issued on ( Jan 24). (LOA signed on 20-Aug-23, GAFM date by 28th Jan 24) Delivery 13 months from LOA signed date and 10 month from GAFM , as per P.O delivery by . 28-Jan-25. Delivery to be expedited. GIS Material is partially delivered to site. waiting for CT&PT approval
B16: PE-265 | C16: 110/33 KV ALMAHANI S/S IN TAIF | D16: Sohaib Afdal | E16: Western | F16: 2 | G16: Client | H16: SEC | I16: Test & Comm. | K16: delay in final setting approval and Line Parameters for SWGR and Capacitor bank and line protection delaying open loop test | L16: High | M16: Submittal was provided to SEC requesting the approval to proceed Letter submitted to SE highlighting the key issues holding the testing progress | N16: Need to expedite final setting approval for SWGR and Capacitor bank and line protection to proceed immediately with Open Loop Tests | O16: A | P16: A | Q16: PM/SEC | R16: 46233 | S16: 46233 | T16: Open
B17: PE-265 | C17: 110/33 KV ALMAHANI S/S IN TAIF | D17: Sohaib Afdal | E17: Western | F17: 2 | G17: Alfanar | H17: AP / SE | I17: Installation | K17: Delayed installations of the (HV Terminations, CSE, MV Terminations) pending qualified subcontractor. | L17: High | M17: Prequalification Submitted to SE, Awaiting Approval to Close the PO | N17: support with SE to finalize the prequalification to close the PO | O17: A | P17: A | Q17: Vendor | R17: 46233 | S17: 46233 | T17: Open | X17: Material delivered (except for MV Terminations, expected by 1st week of Aug-26)
B18: PE-265 | C18: 110/33 KV ALMAHANI S/S IN TAIF | D18: Sohaib Afdal | E18: Western | F18: 2 | G18: Alfanar | H18: AP / SE | I18: Construction | K18: Costly design of the road works connection with the main road that will require additional 1.6m to the available Asphalt PO | L18: High | M18: Alternative offers were acquired with 0.9M SAR, however still no Budget to proceed with the current design | N18: Arrange with SE to agree on a proposal to link the road, SCD to provide Cheaper offers | O18: A | P18: A | Q18: Vendor | R18: 46233 | S18: 46264 | T18: Open
B19: PE-265 | C19: 110/33 KV ALMAHANI S/S IN TAIF | D19: Sohaib Afdal | E19: Western | F19: 2 | G19: Vendor | H19: HITACHI | I19: Delivery | K19: MV Capacitor Banks, During unpacking of the MV Capacitor Bank units, one unit out of four was found damaged with oil leakage, rendering it defective and unfit for installation. The unit requires full replacement. | L19: High | M19: HITACHI was formally notified of the damaged unit and requested to propose a replacement solution. HITACHI confirmed remanufacturing of a replacement unit, with delivery estimated by Aug-26. | N19: HITACHI to formally assess responsibility for transit damage and explore schedule acceleration options (priority manufacturing, parallel FAT, or air shipment where feasible). | O19: A | P19: A | Q19: Vendor | R19: 46203 | S19: 46264 | T19: Closed | U19: additional 3 months delay | X19: Material delivered
B20: PE-265 | C20: 110/33 KV ALMAHANI S/S IN TAIF | D20: Sohaib Afdal | E20: Western | F20: 3 | G20: Vendor | H20: SPTC | I20: Delivery | K20: Power Transformer 80/100 MVA Delivery | L20: High | M20: Mail shared to supplier,supplier informed FAT from 22nd May to 29th May. | N20: FAT date to be improved by end of Apr. Need delivery by 10th May 25 | O20: A | P20: A | Q20: Vendor/PM | R20: 45767 | S20: 45807 | T20: Closed | U20: Three month impact | X20: P.O issued on 4th Sep 24, Delivery period 16.5 Months from p.o issuancw. as per P.O delivery by 21th Jan 25, delivery to be expedited.Delivery is expected on 15-Jul-25 FAT Is completed.
B21: PE-265 | C21: 110/33 KV ALMAHANI S/S IN TAIF | D21: Sohaib Afdal | E21: Western | F21: 4 | G21: Vendor | H21: Prainsa | I21: Installation | K21: 110KV Building precast material delivery and instllation delayed, till date no materials delivered at site | L21: High | M21: Supplier send the plan for delivery by Mid of may and installation by mid of June, Alfanar not accepted. | N21: Supplier should supply all the materials immediately and installation need to complete by end of May-25 | O21: A | P21: A | Q21: Vendor/PM | R21: 45762 | S21: 45792 | T21: Closed | U21: One month impact | X21: All precast material is delivered
B22: PE-265 | C22: 110/33 KV ALMAHANI S/S IN TAIF | D22: Sohaib Afdal | E22: Western | F22: 5 | G22: Client | H22: SEC | I22: Delivery | K22: 110kv GIS ct-vt-Exceptional approval | L22: high | M22: Email communication and followup | N22: sec NEED TO APPROVE THE EXCEPTIONAL APPROVAL | O22: A | P22: A | Q22: Client/PM | T22: Closed | X22: Still SEC not replied.
B23: PE-265 | C23: 110/33 KV ALMAHANI S/S IN TAIF | D23: Sohaib Afdal | E23: Western | F23: 6 | G23: Vendor | H23: DAR | I23: Design Submission / Rectifications | K23: Delay in Submission and revision comments reply by DAR | L23: High | M23: E-mails and follow up is made with DAR Team to submit design pending works | N23: Dar need to Expedite the compliance SEC comments and submit revisions within 3-4 days | O23: A | P23: A | Q23: Vendor | T23: Closed | V23: Al Mahani Dar submittal tracking (22-Apr-25).xlsx | X23: Now DAR is replying for Comments from SEC
B24: PE-315 | C24: 110KV Salam Royal Palace | D24: Ahmed Faisal | E24: Western | F24: 1 | G24: Vendor | H24: M/S FAWAZ REFR & AIRCONDITIONING | I24: Delivery | K24: Ventilation Fans & Smoke Purging Fans-Delivery | L24: Extremely High | M24: Vendor has confirmed the shipment will start by 15th Aug 25 and expected delivery will be 30th Sep’2 which affect the TCC date. | N24: Expedite the vendor to start the shipment immediately. | O24: A | P24: A | Q24: Vendor/PM | S24: 45930 | T24: Closed | U24: One month impact
B25: PE-315 | C25: 110KV Salam Royal Palace | D25: Ahmed Faisal | E25: Western | F25: 2 | G25: Vendor | H25: AES | I25: Delivery | K25: Protection Panel-Consumer feeder is still pending and expected delivery 10th july'25.FAT for 5 panels completed on yesterday | L25: Medium | M25: Continous follow up and meeting to expedite the delivery. | N25: AES should deliver the consumer feeder by 10th July'25 as committed. | O25: C | P25: C | Q25: Vendor/PM | R25: 45777 | S25: 45848 | T25: Closed | U25: No impact
B26: PE-315 | C26: 110KV Salam Royal Palace | D26: Ahmed Faisal | E26: Western | F26: 3 | G26: Vendor | H26: AES | I26: Delivery | K26: ACDC Lighting Panel-FAT date yet to be confirmed. Base design approved on 8th May'25.We are pushing AES to the target FAT date of 15th July'25. | L26: High | M26: Continous follow up and meeting to expedite the delivery. | N26: Expedite the AES to the target FAT date of 15th July'25 | O26: B | P26: B | Q26: Vendor/PM | R26: 45777 | S26: 45853 | T26: Closed | U26: No impact
B27: PE-315 | C27: 110KV Salam Royal Palace | D27: Ahmed Faisal | E27: Western | F27: 4 | G27: Vendor | H27: AES | I27: Delivery | K27: Station Service Transformer-FAT will be on 30th Aug'25.Expected delivery by Sep'25 | L27: Extremely High | M27: Continous follow up and meeting to expedite the delivery. | N27: AES should improve the FAT date before 15th July'25. | O27: A | P27: A | Q27: Vendor/PM | R27: 45762 | S27: 45792 | T27: Closed | U27: 2 months impact
B28: PE-315 | C28: 110KV Salam Royal Palace | D28: Ahmed Faisal | E28: Western | F28: 5 | G28: Vendor | H28: LEEEC | I28: Delivery | K28: Power Transformer-RFS issued. However , shipment still not processed waiting conclusion of SEC visit to M/S LEEEC factory. | L28: Extremely High | M28: FAT completed on 10 Mar'25.Due to quality inspection,SEC visited the factory and review the comments give release for shipment. | N28: LEEEC should deliver the power transformer by 1st Aug'25. | O28: A | P28: A | Q28: Vendor/PM | R28: 45839 | S28: 45901 | T28: Closed | U28: 2 months impact
B29: PE-315 | C29: 110KV Salam Royal Palace | D29: Ahmed Faisal | E29: Western | F29: 6 | G29: Client | H29: SEC/Royal Palace Security team | I29: Delivery | K29: Security system & Access control scope yet to be finalized by SEC & Royal Palace security team. | L29: Extremely High | M29: PO finalized to Etech and awaiting for Technical Submittal. | N29: SEC should confirm the security system scope required or not for this project. | O29: A | P29: A | Q29: SEC/PM | S29: 45853 | T29: Closed
B30: PE-315 | C30: 110KV Salam Royal Palace | D30: Ahmed Faisal | E30: Western | F30: 7 | G30: Client | H30: SEC | I30: Delivery | K30: Cable route finalized 25th june'25 and given for manufacturing clearance.Submitted schematic diagram to SEC. | L30: Extremely High | M30: Submitted the schematic diagram to SEC.Once we get approval,we will start civil works. | N30: SEC should expedite the approval of cable route outside palace. | O30: A | P30: A | Q30: SEC/PM | S30: 45845 | T30: Closed | U30: 2 months impact
B31: PE-280 | C31: 110KV SS - KAEC-2 | D31: Hossam Mahrous | E31: Western | F31: 1 | G31: Client | H31: SEC | I31: Permits / Request from Client | K31: Armored cable requirement for LV cable | L31: Extremely High | M31: Matter has been highlighted to SEC & EMAAR as well | N31: Armored Cable requirement to be waived off from SEC & Issue highlighted to SEC & KAEC as well. PM to have close follow-up with SEC/KAEC to resolve the issue | O31: B | P31: B | Q31: Client/PM | R31: 45777 | S31: 45777 | T31: Closed | U31: One month impact (Cost Impact after vendor quote its price) | V31: Matter has been closed & SEC has approved LV cable design without armor rerquirement | W31: No Impact | X31: PO Placed
B32: PE-280 | C32: 110KV SS - KAEC-2 | D32: Hossam Mahrous | E32: Western | F32: 2 | G32: Client | H32: SEC | I32: Permits / Request from Client | K32: FAT Approval & Delivery for Power Transformer | L32: Extremely High | M32: Letter sent to SEC by VP for two times to expedite FAT & Rectification approval RFSC already given to supplier (Material is stuck with Supplier) | N32: SEC to provide FAT & Rectification approval | O32: B | P32: B | Q32: Client/Vendor/PM | R32: 45802 | S32: 45838 | T32: Closed | U32: One month impact | V32: Power Transformer to be dispatched within this week | W32: No Impact | X32: PO Placed
B33: PE-280 | C33: 110KV SS - KAEC-2 | D33: Hossam Mahrous | E33: Western | F33: 3 | G33: Alfanar | H33: T&C | I33: Resources | K33: Mobilization of T&C team | L33: High | M33: Portfolio Manager has communicated AT&C to finalization of PO | N33: Need support from management in mobilization of T&C team by 1st June 2025 | O33: B | P33: B | Q33: Vendor/PM | R33: 45809 | S33: 45838 | T33: Closed | U33: No Impact | V33: T&C Team starts working at site | W33: No Impact | X33: Under Negotiation
B34: PE-280 | C34: 110KV SS - KAEC-2 | D34: Hossam Mahrous | E34: Western | F34: 4 | G34: Vendor | H34: AES | I34: Delivery | K34: AES to get exceptional approval for (Duplex painting system-Double coat) Service station transformer from SEC. | L34: High | M34: AES has submitted exceptional letter to SEC | N34: AES to get the exceptional approval and delivery to be expedited before 30-Apr-25 | O34: B | P34: B | Q34: Client/Vendor/PM | R34: 45777 | T34: Closed | U34: One month impact | V34: Design approved | W34: No Impact | X34: PO Placed
B35: PE-280 | C35: 110KV SS - KAEC-2 | D35: Hossam Mahrous | E35: Western | F35: 5 | G35: Client | H35: SEC | I35: Permits / Request from Client | K35: Need exceptional approval of Faradol 810 used for capacitor bank | L35: High | M35: Letter sent to SEC by PM GAFM already given to supplier (Material under Manufacturing) | N35: Project team to have close follow-up with SEC to close the matter | O35: B | P35: B | Q35: Client/Vendor/PM | R35: 45855 | S35: 45855 | T35: Closed | U35: No Impact | V35: FAT scheduled on first week of August | W35: No Impact | X35: PO Placed
B36: PE-280 | C36: 110KV SS - KAEC-2 | D36: Hossam Mahrous | E36: Western | F36: 6 | G36: Client | H36: SEC | I36: Permits / Request from Client | K36: Need exceptional approval for battery type HOPPECKE | L36: High | M36: Letter sent to SEC on 23.01.2025 by PM GAFM already given to supplier (Material under Manufacturing) | N36: Project team to have close follow-up with SEC to close the matter | O36: B | P36: B | Q36: Client/Vendor/PM | R36: 45788 | S36: 45838 | T36: Closed | U36: One month impact | V36: FAT completed | W36: No Impact | X36: PO Placed
B37: PE-281 | C37: 110KV SS - KAEC-3 | D37: Hossam Mahrous | E37: Western | F37: 1 | G37: Client | H37: SEC | I37: Permits / Request from Client | K37: Armored cable requirement for LV cable | L37: Extremely High | M37: Matter has been highlighted to SEC & EMAAR as well | N37: Armored Cable requirement to be waived off from SEC & Issue highlighted to SEC & KAEC as well. PM to have close follow-up with SEC/KAEC to resolve the issue | O37: B | P37: B | Q37: Client/PM | R37: 45777 | S37: 45777 | T37: Closed | U37: One month impact (Cost Impact after vendor quote its price) | V37: Matter has been closed & SEC has approved LV cable design without armor rerquirement | W37: No Impact | X37: PO Placed
B38: PE-281 | C38: 110KV SS - KAEC-3 | D38: Hossam Mahrous | E38: Western | F38: 2 | G38: Client | H38: SEC | I38: Permits / Request from Client | K38: FAT Approval & Delivery for Power Transformer | L38: Extremely High | M38: Letter sent to SEC by VP for two times to expedite FAT & Rectification approval RFSC already given to supplier (Material is stuck with Supplier) | N38: SEC to provide FAT & Rectification approval | O38: B | P38: B | Q38: Client/Vendor/PM | R38: 45802 | S38: 45838 | T38: Closed | U38: One month impact | V38: Power Transformer to be dispatched within this week | W38: No Impact | X38: PO Placed
B39: PE-281 | C39: 110KV SS - KAEC-3 | D39: Hossam Mahrous | E39: Western | F39: 3 | G39: Alfanar | H39: T&C | I39: Resources | K39: Mobilization of T&C team | L39: High | M39: Portfolio Manager has communicated AT&C to finalization of PO | N39: Need support from management in mobilization of T&C team by 1st June 2025 | O39: B | P39: B | Q39: Vendor/PM | R39: 45809 | S39: 45838 | T39: Closed | U39: No Impact | V39: T&C Team starts working at site | W39: No Impact | X39: Under Negotiation
B40: PE-281 | C40: 110KV SS - KAEC-3 | D40: Hossam Mahrous | E40: Western | F40: 4 | G40: Vendor | H40: AES | I40: Delivery | K40: AES to get exceptional approval for (Duplex painting system-Double coat) Service station transformer from SEC. | L40: High | M40: AES has submitted exceptional letter to SEC | N40: AES to get the exceptional approval and delivery to be expedited before 30-Apr-25 | O40: B | P40: B | Q40: Client/Vendor/PM | R40: 45777 | T40: Closed | U40: One month impact | V40: Design approved | W40: No Impact | X40: PO Placed
B41: PE-281 | C41: 110KV SS - KAEC-3 | D41: Hossam Mahrous | E41: Western | F41: 5 | G41: Client | H41: SEC | I41: Permits / Request from Client | K41: Need exceptional approval of Faradol 810 used for capacitor bank | L41: High | M41: Letter sent to SEC & under approval | N41: Project team to have close follow-up with SEC to close the matter | O41: B | P41: B | Q41: Client/Vendor/PM | R41: 45855 | S41: 45855 | T41: Closed | U41: No Impact | V41: FAT scheduled on first week of August | W41: No Impact | X41: PO Placed
B42: PE-281 | C42: 110KV SS - KAEC-3 | D42: Hossam Mahrous | E42: Western | F42: 6 | G42: Client | H42: SEC | I42: Permits / Request from Client | K42: Need exceptional approval for battery type HOPPECKE | L42: High | M42: Letter sent to SEC & under approval for battery type | N42: Project team to have close follow-up with SEC to close the matter | O42: B | P42: B | Q42: Client/Vendor/PM | R42: 45788 | S42: 45838 | T42: Closed | U42: One month impact | V42: FAT completed | W42: No Impact | X42: PO Placed
B43: PE-330 | C43: Construction of OTOUD SS and interconnections | D43: Ahmed Hussein | E43: Southern | F43: 1 | G43: Client | H43: SEC | I43: Permits / Request from Client | K43: *Delay of issuing Municipalty permit for Substation due to missing title deed | L43: Medium | M43: Issue is discussed with SEC by Portfolio Manager and PM and Letter is submitted to SEC | N43: SEC to follow Up to get the title deed of the Land | O43: A | P43: A | Q43: SEC | T43: Closed
B44: PE-330 | C44: Construction of OTOUD SS and interconnections | D44: Ahmed Hussein | E44: Southern | F44: 2 | G44: Alfanar | H44: Project Team | I44: Delivery | K44: GIS Manufacturing Duration is very high relative to the 18 Months TCC which is expected to impact the TCC by 6 months delay | L44: High | M44: communicated with the supplier and the manufacturing duration is reduced to 11.5 months (Expected delivery date as stated by Hitachi is 6-Aug-2026 instead of 15-Sep-2026) | N44: Try to make the delivery date earlier to have enough time for Installation & T&C | O44: A | P44: A | Q44: PM | S44: 46301 | T44: Closed | U44: 2 months impact
B45: PE-330 | C45: Construction of OTOUD SS and interconnections | D45: Ahmed Hussein | E45: Southern | F45: 3 | G45: Alfanar | H45: Supply chain-Purchasing | I45: Delivery | K45: Transformers Manufacturing Duration is very high relative to the 18 Months TCC which is expected to impact the TCC by 7 months delay | L45: Extremely High | M45: Requested to swap to VoltAMP or LEEEC but rejected multiple times by local content department in SEC the GAFM letter is issued to SPTC in less than one month to expedite the delivery of TRFs | N45: Minimize the duration of manufacuring to 11 months or less | O45: A | P45: A | Q45: PM | S45: 46537 | T45: Open | U45: 7 months impact | X45: PO Placed
B46: PE-330 | C46: Construction of OTOUD SS and interconnections | D46: Ahmed Hussein | E46: Southern | F46: 4 | G46: Client | H46: SEC | I46: Design inputs | K46: Identification of Circuit Number to make Loop in/Loop Out (UGC Connection to Abha east-Khamis south-1 Line) | L46: High | M46: Requested from SEC the Identification | N46: Issue Letter to SEC and follow up to expedite | O46: B | P46: B | Q46: SEC | T46: Closed
B47: PE-330 | C47: Construction of OTOUD SS and interconnections | D47: Ahmed Hussein | E47: Southern | F47: 5 | G47: Alfanar | H47: Project Team | I47: PO Issuance Delay | K47: Delay of Isssuance of AC/DC System PO | L47: High | M47: Design in progress | N47: Expedite all the related calculations (HVAC, C.B Sizing,etc..) to issue GAFM for the AC/DC System | O47: B | P47: B | Q47: PE | R47: 46009 | S47: 46051 | T47: Closed | U47: Critical activity (if delivery delayed wrt target date, it will impact the schedule)
B48: PE-330 | C48: Construction of OTOUD SS and interconnections | D48: Ahmed Hussein | E48: Southern | F48: 6 | G48: Alfanar | H48: Project Team | I48: PO Issuance Delay | K48: Delay of Isssuance Precast and accordingly delay of design of precast which delays the Civil Design | L48: High | M48: Collecting offers | N48: Expedite PO Issuance to finalize precast design then Civil Design | O48: B | P48: B | Q48: Civil PE | R48: 45988 | S48: 46053 | T48: Closed | U48: Delay in Civil works(if Municipality permit issued)
B49: PE-330 | C49: Construction of OTOUD SS and interconnections | D49: Ahmed Hussein | E49: Southern | F49: 7 | G49: Alfanar | H49: Project Team | I49: Treasury | K49: Delay of Issuance of Insurance Bond which delays collection of Advance payment | L49: High | N49: Expedite issuance of insurance Bond to collect the advance payment | O49: B | P49: B | Q49: PM | R49: 45988 | S49: 46051 | T49: Closed | U49: Delay in Civil works(if Municipality permit issued)
B50: PE-330 | C50: Construction of OTOUD SS and interconnections | D50: Ahmed Hussein | E50: Southern | F50: 8 | G50: Alfanar | H50: Project Team | I50: Construction | K50: Relocation of the store is required to completed excavation for the SS Building | L50: High | M50: PM find new store and Relocation of Mobilization location ongoing | N50: Expedite store relocation and civil works to ensure building readiness | O50: B | P50: B | Q50: PM | T50: Closed | U50: Delay in Civil works
B51: PE-330 | C51: Construction of OTOUD SS and interconnections | D51: Ahmed Hussein | E51: Southern | F51: 9 | G51: Alfanar | H51: Project Team | I51: Construction | K51: Single UGC Permits rejection by Municipality | L51: Extremely High | M51: PM sent letters to stakeholders to resolve the issue and is closely following up on permits with the municipality EOT submitted to SE on 17-Aug-2026, requesting a 12-month extension, Currently under SE review. | N51: Urgent Support Required from SE to Facilitate Municipality Permit Issuance | O51: A | P51: A | Q51: PM | S51: 46264 | T51: Open | U51: 1-Impacting start of Underground cable scope. 2- impact energization and potentially result in TCC delay.
B52: PE-330 | C52: Construction of OTOUD SS and interconnections | D52: Ahmed Hussein | E52: Southern | F52: 10 | G52: Alfanar | H52: Project Team | I52: Construction | K52: HDD Alignment Impacted by existing deep water-pipeline | L52: High | M52: PM sent letters to stakeholders to resolve the issue | N52: Freeze design and finalize routes to avoid further delays and rework (HDD / UGC) | O52: B | P52: B | Q52: design team/PM | S52: 46295 | T52: Open | U52: 1-Delay in single circuit UGC works. 2- Risk of potential design changes and associated technical calculations due to
B53: PE-330 | C53: Construction of OTOUD SS and interconnections | D53: Ahmed Hussein | E53: Southern | F53: 11 | G53: Alfanar | H53: Project Team | I53: Construction | K53: Civil Readiness delay | L53: Medium | M53: 1-Expedite the Site Activities by flow internal Construction Plan , 2-High coordination with All supply to deliver the Equipment in proper time | N53: Expedite the Precast Activities and closed the Change order matters ASAP | O53: C | P53: C | Q53: Construction team/PM | S53: 46295 | T53: Open | U53: 1-Delay in in installation scope 2-1-Equipments will arrive before building readiness, thus will increase storage-related risks and additional storage/handling costs
B54: PE-330 | C54: Construction of OTOUD SS and interconnections | D54: Ahmed Hussein | E54: Southern | F54: 12 | G54: Alfanar | H54: Project Team | I54: Equipment/ Engineering | K54: The issuance of GAFM for the Double-Circuit HV Cable has been delayed due to design finalization delay. | L54: Medium | M54: 1-A joint site visit was conducted to locate the existing link boxes. 2-Induced Voltage and Circulating Current Calculations were submitted. 3-M55The resubmission approach was agreed upon. | N54: 1- Expedite the Submittal cycle Approval to avoid any additional delays 2- High coordination with the AES to reduce manufacturing Duration | O54: C | P54: C | Q54: PM | S54: 20/8/2026 | T54: Open | U54: The delay in issuing the GAFM for the Double-Circuit HV Cable impacting the UGC scope , SS energization, and completion dates | V54: Delivery terms as per PO are 4 months from GAFM issuance, the forecast Completion for Double Circuit is 14-Feb-2027
B55: PE-330 | C55: Construction of OTOUD SS and interconnections | D55: Ahmed Hussein | E55: Southern | F55: 13 | G55: Alfanar | H55: Project Team | I55: Equipment/ Engineering | K55: Protection Panels Detail Design are not Approved​ yet Subject to IRF ZIV Relays are received rejection from PED | L55: Medium | M55: Close coordination was conducted with AES to resolve the issue or arrange a replacement for IRF ZIV, followed by resubmission at the earliest. | N55: 1- Expedite the Submittal cycle Approval to avoid any additional delays 2- High coordination with the AES to To determine the FAT date | O55: C | P55: C | Q55: PM | S55: 46254 | T55: Closed | U55: The delay in approving the Protection Panels Detailed Design has impacted both the SWGR and SAS systems, consequently affecting the contractual TCC date. | V55: The resubmission is currently in progress, while the 132kV Transformer Protection Panel Detailed Design has already been approved. on 22-Jul-2026
B56: PE-330 | C56: Construction of OTOUD SS and interconnections | D56: Ahmed Hussein | E56: Southern | F56: 14 | G56: Alfanar | H56: Project Team | I56: Equipment/ Engineering | K56: MV SWGR Detail Design are not Approved​ yet Subject to Protection Panels Detail Design and IRF ZIV Relays are received rejection from PED, while the FAT date has not yet been confirmed | L56: Medium | M56: Close coordination is ongoing with AES to resolve and close the Protection Panel issue. | N56: 1- Expedite the Submittal cycle Approval to avoid any additional delays 2- High coordination with the AES to To determine the FAT date | O56: C | P56: C | Q56: PM | S56: 46386 | T56: Open | U56: The delay in approving the Protection Panels Detailed Design has impacted the SWGR FAT schedule and is expected to delay the SWGR delivery by approximately two months
B57: PE-330 | C57: Construction of OTOUD SS and interconnections | D57: Ahmed Hussein | E57: Southern | F57: 15 | G57: Alfanar | H57: Project Team | I57: equipment/ Engineering | K57: Delay in issuing the GAFM for the SAS system due to the Protection Panels Detailed Design not yet being approved. | L57: Medium | M57: Close coordination is ongoing with AES to resolve the Protection Panel issue | N57: 1-Expedite the submittal approval cycle to avoid any further delays. 2-Request AES to reduce the manufacturing duration. | O57: C | P57: C | Q57: PM | S57: 46572 | T57: Open | U57: directe impacting the Contractual TCC date around 6 months
B58: PE-330 | C58: Construction of OTOUD SS and interconnections | D58: Ahmed Hussein | E58: Southern | F58: 16 | G58: Alfanar | H58: Project Team | I58: Equipment/ Engineering | K58: Delay in issuing the GAFM for the Batteries and Battery Chargers due to the pending Base Design approval and PO cancellation with AES, due to they request a Variation Order. | L58: Medium | M58: new PO was issued on 12 July 2026, and the Base Design is currently under review for approval. | N58: 1-Expedite the submittal approval cycle to avoid any further delays. | O58: C | P58: C | Q58: PM | S58: 46492 | T58: Closed | U58: directe impacting the Contractual TCC date around 6 months | V58: GAFM for Battery done today 12/8/2026
B59: PE-331 | C59: 110kV Taif OHTL | D59: Engr Sudhakar | E59: Western | F59: 2 | G59: Alfanar | H59: Supply chain-Purchasing | I59: PO Issuance Delay | J59: 45734 | K59: Delay in Hardware PO issuance due to Revising the technical submittal of Insulator and Line H/W | L59: High | M59: Hence insulator Supplier has been swapped ZAPEL to LAPP. Accordingly revised Technical submittal submitted to SEC for approval | N59: Awaiting the Final Offer from Vendor, to finalise the PO. | O59: A | P59: A | Q59: SCD | T59: Closed
B60: PE-331 | C60: 110kV Taif OHTL | D60: Engr Sudhakar | E60: Western | F60: 6 | G60: Alfanar | H60: Supply chain-Purchasing | I60: VO/EOT | K60: Hydrology Study and report submission | L60: High | M60: SEC asked to submit the change order and parallely to conduct hydrology study for OHTL. | N60: Offers collected from third party for carry the study.PO issued on 6th May25.work to start ASAP.VO to be submitted. | O60: A | P60: A | Q60: Tender team | T60: Closed
B61: PE-331 | C61: 110kV Taif OHTL | D61: Engr Sudhakar | E61: Western | F61: 7 | G61: Vendor | H61: Moneer Al Boqami | I61: Construction | K61: Concrete supplier price escalllation | L61: High | M61: RFQ rasied to alternative suppliers | N61: SCD to secure alternative supplier for concrete ASAP | O61: B | P61: A | Q61: SCD | R61: 45810 | S61: 45830 | T61: Closed
B62: PE-331 | C62: 110kV Taif OHTL | D62: Engr Sudhakar | E62: Western | F62: 8 | G62: Vendor | H62: LAPP | I62: Delivery | K62: Extending the delays in delivery against the PO agreed delivery dates | L62: Medium | M62: GFAM issued on 26 April 2025, followed by remainder mails sent to supplier for knowing the date of factory test. | N62: Supply chain to interfere to push the vendor to take agreed delivered dates mentioned PO. | O62: B | P62: A | Q62: SCD | R62: 45807 | T62: Closed
B63: PE-331 | C63: 110kV Taif OHTL | D63: Engr Sudhakar | E63: Western | F63: 9 | G63: Alfanar | H63: Tender | I63: Tender | K63: Require Budgeted supplement for Unit price of Structural pads in hilly area locations. | L63: High | M63: Visited the Site progress, observed the condition at site | N63: Need to be revised budgeted unit prices as per the site special condition | O63: B | P63: A | Q63: Management | T63: Closed | V63: Deployed sub contractors as per the tender rates.
B64: PE-331 | C64: 110kV Taif OHTL | D64: Engr Sudhakar | E64: Western | F64: 10 | G64: Alfanar | H64: Supply chain-Purchasing | I64: PO Issuance Delay | K64: Under Crossing Gantry and transposition towers PO finalization | L64: Medium | M64: Official email was sent to place the order with approved supplier. | N64: SCD has to finalise the order with already supplier in PE-329 to avoid the further delay. | O64: A | P64: A | Q64: SCD | S64: 45838 | T64: Open
B65: PE-331 | C65: 110kV Taif OHTL | D65: Engr Sudhakar | E65: Western | F65: 11 | G65: Vendor | H65: Dalkevod | I65: Delivery | K65: Forecasted delay in the delivery of Line Hardware materials at Site. | L65: High | M65: Following up with SCD to Coordinate to Supplier for early delivery of material | N65: SCD should negotiate with Supplier for earlier material delivery as per PO Conditions. | O65: A | P65: A | Q65: SCD | T65: Open | X65: GAFM Issued on 15-April -2025. As per PO Delivery will be 28-30 Weeks from GAFM. (As per the Baseline MF Finish Sept 2025)
B66: PE-331 | C66: 110kV Taif OHTL | D66: Engr Sudhakar | E66: Western | F66: 12 | G66: Alfanar | H66: Supply chain-Purchasing | I66: Delivery | K66: Foundation subcontractors PO Issuance delay | L66: High | M66: Following up with SCD for PO issuance | N66: SCD should expedite the PO issuance to avoid the mobilisation delay of the sub contractor. | O66: A | P66: A | Q66: SCD | S66: 45833 | T66: Open | X66: PR Created on May 08 2025
B67: PE-331 | C67: 110kV Taif OHTL | D67: Engr Sudhakar | E67: Western | F67: 13 | G67: Alfanar | H67: Supply chain-Purchasing | I67: PO Issuance Delay | K67: Delay in Tower foundation work PO | L67: High | M67: Following up with mail by mentioning the impact in the construction delay. | N67: SCD to expedite the finalisation of PO, as Foundation design status are under approval with SEC. | O67: A | P67: A | Q67: SCD | T67: Open
B68: PE-331 | C68: 110kV Taif OHTL | D68: Engr Sudhakar | E68: Western | F68: 14 | G68: Vendor | H68: DAR | I68: Design Submission / Rectifications | K68: Delay in the approval of foundation design submission & approval | L68: High | M68: Borehole layout submission complaince and Soil investigation report submissions are done. | N68: Project team need to expedite with client for approval, is there any complaince with DAR to be done on priority to avoid the delay in the construction works. | O68: A | P68: A | Q68: PM/SEC | T68: Open
B69: PE-331 | C69: 110kV Taif OHTL | D69: Engr Sudhakar | E69: Western | F69: 4 | G69: Vendor | H69: DAR | I69: Design Submission / Rectifications | J69: 45738 | K69: Structure Pad Works Delay due to change in Plan and Profile Portion | L69: High | M69: Remainder Mails were sent to DAR for Compliance and Timely approval from Client. | N69: Plan and Profile Portion received and submitted , Structure Pads Works resumed. | O69: A | P69: A | Q69: PM | T69: Closed
B70: PE-331 | C70: 110kVTaif OHTL | D70: Engr Sudhakar | E70: Western | F70: 1 | G70: Alfanar | H70: Supply chain-Purchasing | I70: Delivery | J70: 45712 | K70: Forecasted Delay in insulators delivery | L70: Medium | M70: Approved PLR Insulator supplier Proposed us the long delivery time due to production issues. Alternative supplier proposed to SEC and already approved and PO issued | N70: PO for alternative supplier already obtained,MFC for LOT-1 is released | O70: A | P70: A | Q70: PM | T70: Closed
B71: PE-331 | C71: 110kVTaif OHTL | D71: Engr Sudhakar | E71: Western | F71: 3 | G71: Vendor | H71: DAR | I71: Design Submission / Rectifications | J71: 45756 | K71: Delay in resubmission in Plan and profile affecting civil submission ( Bohre Hole Layout & Access Road) | L71: Extremely High | M71: Project team highlighted delays and urgencies via a lot reminders to DAR Team . | N71: Design team to immediate finalization of P& P revisions and approval which highly impacted the construction activities and project completion. Milestones. | O71: A | P71: A | Q71: PM | T71: Closed | V71: PE-331 110kV OHTL Design Submittal Delay List 20-04-2025..xlsx
B72: PE-307 | C72: 132/13.8KV Sub Industrial City Tabuk | D72: Shafqat Zia | E72: Western | F72: 1 | G72: Vendor | H72: AES | I72: Delivery | K72: AES pending Deliverable | L72: High | M72: Continuous follow up, meetings and letters shared to AES to expedite the deliverys | N72: PM need to have close followup with AES to delivery the pending deliverables. Current status : delivered and closed | O72: C | P72: C | Q72: Vendor | R72: 45746 | T72: Closed | U72: No impact
B73: PE-307 | C73: 132/13.8KV Sub Industrial City Tabuk | D73: Shafqat Zia | E73: Western | F73: 4 | G73: Vendor | H73: AES | I73: Delivery | K73: FAT for Cyber Security | L73: High | M73: FAT dates confirmed by AES after follow-up and FAT Completed on 25-Mar-25 | N73: FAT Completed, report approved. Release of shipment issued from AES. | O73: C | P73: C | Q73: Vendor | T73: Closed | U73: No impact
B74: PE-307 | C74: 132/13.8KV Sub Industrial City Tabuk | D74: Shafqat Zia | E74: Western | F74: 7 | G74: Vendor | H74: SPTC | I74: Delivery | K74: Power Transformer delivery as per baseline is 05-Feb-26, which is critical activity. Need to ensure delivery on time. | L74: Extremely High | M74: Highlighted to MODON, as they went to SPTC office to followup earlier delivery plan from SPTC. | N74: FAT ongoing (04-14th Jan-26); Expected delivery 1st week of Jan'26. Current status : delivered and closed | O74: C | P74: C | Q74: Vendor/MODON | S74: 46058 | T74: Closed | U74: Critical activity (if delivery delayed wrt target date, it will impact both schedule & cost) | X74: P.O issued on 20th May 24, Delivery period 22 Months from 13-May-24. as per P.O delivery by 4th Mar 26, requested delivery by 30-Nov-25 for the delivery
B75: PE-307 | C75: 132/13.8KV Sub Industrial City Tabuk | D75: Shafqat Zia | E75: Western | G75: Vendor | H75: Ramz Alataa | I75: Design Submission / Rectifications | K75: HVAC Materials - Delivery of PACU Units, HVAC Fans, DDC Control Panels | L75: High | M75: All DTS revised submittal closed and approved; Delivery plan to be expedited from Supplier | N75: 1) PACU Units - FAT planned on 14-Jan-26 2) HVAC Fans Delivery expected 25-Jan-26; 3) HVAC DDC Control Panels dispatched, this week 15-Jan-2026 Current status : delivered and closed | O75: C | P75: C | Q75: Vendor | S75: 45848 | T75: Closed | U75: Schedule impact | X75: PO issued on 24-Nov-24, PACU units, Fans, DDC Panels 12-16 weeks from GAFM;
B76: PE-307 | C76: 132/13.8KV Sub Industrial City Tabuk | D76: Shafqat Zia | E76: Western | F76: 8 | G76: Vendor | H76: HITACHI | I76: Delivery | K76: 13.8KV 7MVAR CAPACITOR BANK Delivery FAT date confirmation required from Supplier | L76: Low | M76: Email communication and followup with Hitachi team to expeditet the delivery | N76: LOT 1 (mechanical parts) FAT Completed; LOT 2 (Main materials) yet to deliver at Dammam (FAT completed on 17-Aug-25) | O76: C | P76: C | Q76: Vendor | S76: 45853 | T76: Closed | U76: No impact | X76: "P.O issued on (05th Jun 24). (GAFM on 28-oct-24 ) Delivery 45 Weeks from GAFM date, as per P.O delivery by 8th Sep 25. Delivery to be expedited by Jul-25.
B77: PE-307 | C77: 132/13.8KV Sub Industrial City Tabuk | D77: Shafqat Zia | E77: Western | F77: 9 | G77: Client | H77: SEC/MODON | I77: Design Submission / Rectifications | K77: Civil Structural drawing submitted & awaiting for approval | L77: Low | M77: Continuous follow up with Precast vendor (PRIANSA) and closed the comments, obtained Approved from SEC. | N77: Civil Structural drwg submitted on 30-Oct-24 & approval awaiting from SEC. Since SEC is inter linking with Approval of super structure Precast drawings (M/s Prainsa) which (Rev. R2 submitted to SEC on 26-Feb-25) & Approved on 16-Mar-25. - Structural drwg approved on 01-Jun-25 | O77: C | P77: C | Q77: SEC | S77: 45809 | T77: Closed
B78: PE-340 | C78: 132kV OHTL JIZAN | D78: Amir Abo Mansour | E78: Southern | F78: 1 | G78: Vendor | H78: GE | I78: Delivery | J78: 45763 | K78: Long lead duration for GIS delivery of 20 month exceeding project duration of 18 Month | L78: Extremely High | M78: SWAP letter to alternate supplier sent offically to SEC | N78: Approval from SEC recived on 5th May | O78: A | P78: A | Q78: Client/PM | T78: closed | V78: delayed agreement by Supply Chain Department with the alternate supplier the manufacturing & delivey duration is 13.5 months starting from 12-Jun-2025 (expected delivery by 1st of Aug-2026 this will impact negatively on the TCC milestone of the project
B79: PE-340 | C79: 132kV OHTL JIZAN | D79: Amir Abo Mansour | E79: Southern | F79: 2 | G79: Alfanar | H79: Tender | I79: Tender | J79: 45753 | K79: Costing file not shared to release tender budget | L79: High | M79: Reminder email sent to Tender team. Files recived on 16 April 26 | N79: Budget released on 5th May | O79: B | P79: A | Q79: Tender/PM | T79: closed
B80: PE-340 | C80: 132kV OHTL JIZAN | D80: Amir Abo Mansour | E80: Southern | F80: 3 | G80: Alfanar | H80: Supply chain-Purchasing | I80: Construction | K80: Delay Start in Route Survey works | L80: High | M80: Survey Works at site to be Start as early as possible, either with in house survey teams or outsourcing whichever is reliable and efficient. | N80: PO with S/c to be finalized at the erliest to start survey and to complet with one week | O80: B | P80: A | Q80: SCD | T80: closed
B81: PE-340 | C81: 132kV OHTL JIZAN | D81: Amir Abo Mansour | E81: Southern | F81: 4 | G81: Client | H81: SEC | I81: Client Issues | K81: As per PTS & KMZ File Provided, there is Mis matching of Co ordinates from PI Start to PI End by SEC | L81: High | M81: Email has been sent to concern Engr; SEC replied that required coordinates will be shared shortly | N81: SEC to resolve the issue on priority to avoid further delays in design submission | O81: A | P81: A | Q81: SEC | T81: closed
B82: PE-340 | C82: 132kV OHTL JIZAN | D82: Amir Abo Mansour | E82: Southern | F82: 5 | G82: Alfanar | H82: Supply chain-Purchasing | I82: PO Issuance Delay | K82: Delay in Design office finalization | L82: High | M82: Following up with email to the supply chain department to finalise the PO | N82: SCD need to Issue the PO on urgent basis. | O82: A | P82: A | Q82: SCD | T82: Closed | V82: Closed on 27-May-2025 Comments completed on 10-Jul-2025
B83: PE-340 | C83: 132kV OHTL JIZAN | D83: Amir Abo Mansour | E83: Southern | F83: 6 | G83: Alfanar | H83: Supply chain-Purchasing | I83: PO Issuance Delay | K83: Delay in the issuance of PO for Long lead items or other items | L83: High | M83: Offical Email and New Target dates has been given for Quick finalisation of the POs | N83: SCD to expedite the collecting of Offers and negotiation with Vendors as earliest posible to avoid further delay. | O83: A | P83: A | Q83: SCD | T83: Closed | V83: closed 22-Jul-2025 process took 15 weeks to be completed
B84: PE-340 | C84: 132kV OHTL JIZAN | D84: Amir Abo Mansour | E84: Southern | F84: 7 | G84: Alfanar | H84: Supply chain-Purchasing | I84: PO Issuance Delay | K84: GIS Supplier Swapping from Hyundai to GE | L84: High | M84: By reconciling the cost of GE, comparing with Hyundai, Project team planning to SWAP Again Hyundai to GE. | N84: Even GE Cost is low, But SCD to Negotiate the Delivery terms with Vendor before proceeding. | O84: B | P84: A | Q84: SCD | T84: Closed
B85: PE-340 | C85: 132kV OHTL JIZAN | D85: Amir Abo Mansour | E85: Southern | F85: 8 | G85: Client | H85: SE | I85: Client Issues | K85: Delay in the submission & approval of plan and profile | L85: Extremely High | M85: *Portion 1,2&3 are approved *Portion 4, New proposal for PIs affected by availability of rock crusher company is submitted to SEC for approval to submit plan & profile accordingly | N85: *Follow up with SEC to get approval on new proposal for portion 4 | O85: A | P85: A | Q85: SCD/PM | T85: Open | U85: 7 Months
B86: PE-340 | C86: 132kV OHTL JIZAN | D86: Amir Abo Mansour | E86: Southern | F86: 9 | G86: Client | H86: SE | I86: Construction | K86: Delay in submission & approval of foundation design which is affecting the start of foundation works | L86: Extremely High | M86: Only 15 locations approved out of 99 submitted | N86: Follow up with SE to obtain approval on submitted portion to start work on site | O86: A | P86: A | Q86: SC/PM | T86: Open | U86: 4 Months
B87: PE-327 | C87: 132kVNajran OHTL | D87: Engr Ayman Al Attar | E87: Southern | F87: 1 | G87: Client | H87: SEC | I87: Permits | J87: 45713 | K87: ROW ISSUES ( 9 Private Lands) affecting 9-10 Towers | L87: Medium | M87: Emails and offical Letter and sent to SEC to clear the area and proceed with soil investigation | N87: Follow up with Client to clear the ROW Obstacles | O87: A | P87: A | Q87: PM | T87: Closed
B88: PE-327 | C88: 132kVNajran OHTL | D88: Engr Ayman Al Attar | E88: Southern | F88: 2 | G88: Alfanar | H88: Supply chain-Purchasing | I88: Delivery | J88: 45736 | K88: Delay in PO issuance for some main items (Piling, Foundation Works, Access Roads,Surege arrestor) | L88: Medium | M88: Reminder Mails have been sent to SCD | N88: PO's has been Issued as per the Request | O88: A | P88: A | Q88: SCD | T88: Closed
B89: PE-327 | C89: 132kVNajran OHTL | D89: Engr Ayamn Al Attar | E89: Southern | F89: 3 | G89: Vendor | H89: DAR | I89: Design Submission / Rectifications | J89: 45736 | K89: Delay in the process of Engineering for the submission and the comment rectifications | L89: High | M89: 2 warning letters have been submitted to DAR for these issue as it's the main bottleneck of the Project A recovery action plan for Submission of Design Submittals is given by Design Engineering team on 15-April-2025. | N89: Project team has to Co ordinate with DAR to Ensure the Commitments dates followed. | O89: A | P89: A | Q89: PM | T89: Closed | V89: https://alfanargroup-my.sharepoint.com/:x:/g/personal/mohamed_sanan_alfanar_com/Ec86f57lNyRKvQRWJWbuVfEBlKYrNtnqm64PQlUVHRHKqg?e=TjfBCu
B90: PE-327 | C90: 132kVNajran OHTL | D90: Engr Ayamn Al Attar | E90: Southern | F90: 1 | G90: Client | H90: SEC | I90: Design Submission / Rectifications | J90: 45719 | K90: Approval of proposal Cable entry to BSP & GIS basement | L90: High | M90: Three proposals are already sent to M/s SEC for 132KV UG Cable Routing Entry insideNajran BSP, till date we are awaiting SEC approval. | N90: Following up with Client, as this approval is required for proceeding the Work of under cable scope. | O90: A | P90: A | Q90: PM | S90: 46028 | T90: Closed
B91: PE-327 | C91: 132kVNajran OHTL | D91: Engr Ayman Al Attar | E91: Southern | F91: 5 | G91: Client | H91: SEC | I91: Delivery | J91: 45755 | K91: Approval from SEC to Swap Gantry Supplier (MS Energiya) from Alternative to Main Supplier | L91: Medium | M91: Official letter was sent to SEC for Swapping the alternative Contractor(M/s Energiya) to maine contractor (M/s Babatain Steel) as exisiting main contractor is decling to provide the offer due to small Quantity | N91: Approval received by SEC on 17-April-2025 with reference to approval mail Manufacturing release for LOT-1 released. | O91: A | P91: A | Q91: Client | T91: Closed
B92: PE-327 | C92: 132kVNajran OHTL | D92: Engr Ayamn Al Attar | E92: Southern | F92: 6 | G92: Vendor | H92: DAR | I92: Design Submission / Rectifications | J92: 45757 | K92: Delay in the re submission of key plan of 132kv UG Cable | L92: High | M92: Remainder mails was sent to DAR , later we recieved the date of action plan for Submission. After 15 days from Rev 01 DAR wen sec replied on 10-April-25 again resubmitted REV 02 on 27-April-2025. | N92: Required Approvals are impacting the Manufacturing release of the Major UG Materals, Following up with SEC to Expedite the Further actions | O92: A | P92: A | Q92: Client | T92: Closed
B93: PE-327 | C93: 132kVNajran OHTL | D93: Engr Ayamn Al Attar | E93: Southern | F93: 7 | G93: Alfanar | H93: Supply chain-Purchasing | I93: Construction | J93: 45722 | K93: Delay in the start of Soil investigation work by M/s GSL | L93: High | M93: As the Call for Start of the Work done on 06-March-2025, Even with Contionus Follow up vendor is delaying the start , Remainder mails were sent to Concern party. | N93: Supply chain department should intervene in this matter, proper action plan to be obtained to recover the delay in the performance. | O93: A | P93: A | Q93: SCD | T93: Closed | V93: Official mail sent to SCD for PO Cancellation
B94: PE-327 | C94: 132kVNajran OHTL | D94: Engr Ayamn Al Attar | E94: Southern | F94: 8 | G94: Vendor | H94: Saden | I94: Construction | J94: 45766 | K94: Slow rate of Soil Investigation works by M/s saden 2 Tower per day with only two rig machine, in view this rate, Soil investigation go for 8.5 Months for Completion. | L94: High | M94: In view with Productivity of the soil investigation Works, Site Management is asked to mobilise the borehole machine by M/s Saden to catch up the progress. | N94: A meeting with Sub con and project team is required for resolving the equipment mobilisation plan by assuring work front. | O94: A | P94: A | Q94: Project Team | T94: Closed
B95: PE-327 | C95: 132kVNajran OHTL | D95: Engr Ayamn Al Attar | E95: Southern | F95: 2 | G95: Alfanar | H95: Construction | I95: Construction | J95: 45766 | K95: Slow rate of Structure pad works and access road works due sand dunes. | L95: High | M95: Sub Contractor evaluation meeting was Conducted at site along with Project Manager and Site Management. Total no Sub contractor was 03 , recently added 1 that is sum upto 04 Nos contractors at site. | N95: As the Site is accompained Majorly by High Dunes, its is required to Improve the no of Sub contractors other wise the Mobilisation of equipments from the existing sub contractors to acheive the progress as planned. | O95: A | P95: A | Q95: Project Team | T95: Closed
B96: PE-327 | C96: 132kVNajran OHTL | D96: Engr Ayamn Al Attar | E96: Southern | F96: 3 | G96: Vendor | H96: Pfisterer Switzerland AG | I96: Delivery | K96: Long Duration of the Delivery for Line Hardware materials | L96: High | M96: Communication with vendor has been done for reducing the delivery date of the hardware materials by mentioning our TCC date Mar 2026. | N96: A Meeting with Supplier along with SCD to be conducted to reduce the delivery dates of the materials | O96: A | P96: A | Q96: PM/SCD | R96: 45930 | S96: 46044 | T96: Closed | U96: 1 Month
B97: PE-327 | C97: 132kVNajran OHTL | D97: Engr Ayamn Al Attar | E97: Southern | F97: 4 | G97: Alfanar | H97: Supply chain-Purchasing | I97: PO Issuance Delay | K97: Delay in the Tower foundation work PO issuance | L97: High | M97: Following up with mail by mentioning the impact in the construction delay. | N97: SCD to expedite the finalisation of PO, as Foundation design status are under approval with SEC. | O97: A | P97: A | Q97: SCD | T97: Closed
B98: PE-327 | C98: 132kVNajran OHTL | D98: Engr Ayamn Al Attar | E98: Southern | F98: 5 | G98: Vendor | H98: DAR | I98: Design Submission / Rectifications | K98: Delay in the complaince of foundation design resubmission | L98: High | M98: Following up with mail by mentioning the impact in the construction delay. | N98: Following with client & design engineering team for approval and submission as per the action commitment date. | O98: A | P98: A | Q98: PM/SEC | T98: Closed
B99: PE-327 | C99: 132kVNajran OHTL | D99: Engr Ayamn Al Attar | E99: Southern | F99: 6 | G99: Alfanar | H99: Supply chain-Purchasing | I99: PO Issuance Delay | K99: Delay in the PO of OHTL Stringing Works | L99: High | M99: Following up with mail by mentioning the impact in the construction delay. | N99: SCD to expedite the finalisation of PO, as time prolongs may impact the vendor rate of work | O99: B | P99: A | Q99: SCD | T99: Closed
B100: PE-327 | C100: 132kVNajran OHTL | D100: Engr Ayamn Al Attar | E100: Southern | F100: 7 | G100: Alfanar | H100: Supply chain-Purchasing | I100: PO Issuance Delay | K100: Delay in the PO of Concrete ready mix | L100: High | M100: Following up with mail by mentioning the impact in the construction delay. | N100: As Foundation works planned to start in the coming week, SCD should expedite the finalisation of PO which was agreed by PM on urgent basis to avoid unforeseen delays in the construction | O100: A | P100: A | Q100: SCD | T100: Closed
B101: PE-327 | C101: 132kVNajran OHTL | D101: Engr Ayamn Al Attar | E101: Southern | F101: 8 | G101: Client | H101: SEC | I101: Delivery | K101: Delay in the delivery of 132KV Lattice Steel towers | L101: Extremely High | M101: Delay notice has been submitted to SEC From Project team and higher management level to SEC management representatives. | N101: 85% of Material has been received, Still 15% Materials needs to expedite for completion to avoid the halt in the work front for sub contractor. | O101: A | P101: A | Q101: SEC | S101: 46249 | T101: Open | U101: 5 Months schedule impacted | V101: LOT-05 Tower Materials and , lot-3 & Lot-4 Missing materials is pending for delivery for major works | X101: By Saudi Energy.
B102: PE-327 | C102: 132kVNajran OHTL | D102: Engr Ayamn Al Attar | E102: Southern | F102: 9 | G102: Client | H102: SEC | I102: Delivery | K102: Delay in the Angle tower Essential bolts and other accessories | L102: Extremely High | M102: Notification has been sent to SEC / Energya supplier, as this missing accessories impacted the planned stringing works. | N102: Efforts are ongoing to get the material purchase from other sites as there is no availability of materials in the local market | O102: A | P102: A | Q102: SEC | T102: Closed | U102: 2 Months schedule impacted
B103: PE-327 | C103: 132kVNajran OHTL | D103: Engr Ayamn Al Attar | E103: Southern | F103: 10 | G103: Client/EOT/VO | H103: SEC | I103: VO/EOT | K103: Revised Change order submission and approvals impacting the PO issuance of Transposition and UC Gantry tower. | L103: Extremely High | M103: R0 Change order has been submitted to SEC , Received with comments, new revised change order has been under complaince with tender team | N103: Complaince of revised change order, will be prepared and submitted by this week, follow up is required for approval to proceed with PO issuance. | O103: A | P103: A | Q103: SEC/ALFANAR | S103: 46072 | T103: CLosed
B104: PE-327 | C104: 132kVNajran OHTL | D104: Engr Ayamn Al Attar | E104: Southern | F104: 11 | G104: Alfanar | H104: Supply chain-Purchasing | I104: PO Issuance Delay | K104: Delay in the finalisation of PO for Transposition tower | L104: Extremely High | M104: DPO has been finalised and sent to SCD on 02-May-2026, follow up remainder has been sent. | N104: PO has been issued to Energya. | O104: A | P104: A | Q104: SCD | S104: 46160 | T104: CLosed | U104: Towers being new scope , change order along with time extention has been submitted, technical approval for towers has been received. | X104: PO Finalised without type testing.
...

Sheet Statistics
A3: Total No. of issues | B3: =COUNTA(Table1[Project]) -> 508
I4: Issues Log Statistics
A12: Client | B12: =COUNTIFS(Table1[Issue owner],A12,Table1[Status],"open") -> 83
A13: Client/EOT/VO | B13: =COUNTIFS(Table1[Issue owner],A13,Table1[Status],"open") -> 1
A14: Vendor | B14: =COUNTIFS(Table1[Issue owner],A14,Table1[Status],"open") -> 87
A15: Alfanar | B15: =COUNTIFS(Table1[Issue owner],A15,Table1[Status],"open") -> 50
B16: =SUM(B12:B15) -> 221
A17: Vendor | B17: No
A18: SPTC | B18: =COUNTIFS(Table1[Name],Statistics!A18,Table1[Status],"open") -> 2
A19: RITZ | B19: =COUNTIFS(Table1[Name],Statistics!A19,Table1[Status],"open") -> 0
A20: SIEMENS | B20: =COUNTIFS(Table1[Name],Statistics!A20,Table1[Status],"open") -> 2
A21: AES | B21: =COUNTIFS(Table1[Name],Statistics!A21,Table1[Status],"open") -> 17
A22: HITACHI | B22: =COUNTIFS(Table1[Name],Statistics!A22,Table1[Status],"open") -> 21
A23: BCG | B23: =COUNTIFS(Table1[Name],Statistics!A23,Table1[Status],"open") -> 1
A24: LAPP | B24: =COUNTIFS(Table1[Name],Statistics!A24,Table1[Status],"open") -> 1 | J24: Status | K24: Issues No. | L24: % | N24: Criticality | O24: No. | P24: % | R24: Issue Owner | S24: No. | T24: %
A25: Ranco & Zamil | B25: =COUNTIFS(Table1[Name],Statistics!A25,Table1[Status],"open") -> 2 | J25: Open | K25: =B87 -> 222 | L25: =K25/$K$27 -> 0.43960396 | N25: Extremely High | O25: =COUNTIFS(Table1[Impact],Statistics!N25,Table1[Status],"open") -> 97 | P25: =O25/$O$29 -> 0.43693694 | R25: Client | S25: =B12+B13 -> 84 | T25: =S25/$S$28 -> 0.3800905
A26: Arteche | B26: =COUNTIFS(Table1[Name],Statistics!A26,Table1[Status],"open") -> 1 | J26: Closed | K26: =B88 -> 283 | L26: =K26/$K$27 -> 0.56039604 | N26: High | O26: =COUNTIFS(Table1[Impact],Statistics!N26,Table1[Status],"open") -> 102 | P26: =O26/$O$29 -> 0.45945946 | R26: Alfanar | S26: =B15 -> 50 | T26: =S26/$S$28 -> 0.22624434
A27: EPC | B27: =COUNTIFS(Table1[Name],Statistics!A27,Table1[Status],"open") -> 0 | J27: Total No. of issues | K27: =SUM(K25:K26) -> 505 | L27: =K27/$K$27 -> 1 | N27: Medium | O27: =COUNTIFS(Table1[Impact],Statistics!N27,Table1[Status],"open") -> 23 | P27: =O27/$O$29 -> 0.1036036 | R27: Vendor | S27: =B14 -> 87 | T27: =S27/$S$28 -> 0.39366516
A28: DAR | B28: =COUNTIFS(Table1[Name],Statistics!A28,Table1[Status],"open") -> 2 | N28: Low | O28: =COUNTIFS(Table1[Impact],Statistics!N28,Table1[Status],"open") -> 0 | P28: =O28/$O$29 -> 0 | R28: Total No. of issues | S28: =SUM(S25:S27) -> 221 | T28: =S28/$S$28 -> 1
A29: Pfisterer Switzerland AG | B29: =COUNTIFS(Table1[Name],Statistics!A29,Table1[Status],"open") -> 1 | N29: Total No. of issues | O29: =SUM(O25:O28) -> 222 | P29: =O29/$O$29 -> 1
A30: MEFC | B30: =COUNTIFS(Table1[Name],Statistics!A30,Table1[Status],"open") -> 1
A31: NCC | B31: =COUNTIFS(Table1[Name],Statistics!A31,Table1[Status],"open") -> 1
A32: AL WABEL | B32: =COUNTIFS(Table1[Name],Statistics!A32,Table1[Status],"open") -> 1
A33: E-Techs | B33: =COUNTIFS(Table1[Name],Statistics!A33,Table1[Status],"open") -> 0
A34: Tridelta | B34: =COUNTIFS(Table1[Name],Statistics!A34,Table1[Status],"open") -> 0
A35: MSCL | B35: =COUNTIFS(Table1[Name],Statistics!A35,Table1[Status],"open") -> 0
A36: Al Majal | B36: =COUNTIFS(Table1[Name],Statistics!A36,Table1[Status],"open") -> 0
A37: Hyosung | B37: =COUNTIFS(Table1[Name],Statistics!A37,Table1[Status],"open") -> 1
A38: Hyundai | B38: =COUNTIFS(Table1[Name],Statistics!A38,Table1[Status],"open") -> 1
A39: ABB | B39: =COUNTIFS(Table1[Name],Statistics!A39,Table1[Status],"open") -> 1
A40: M/S FAWAZ REFR & AIRCONDITIONING | B40: =COUNTIFS(Table1[Name],Statistics!A40,Table1[Status],"open") -> 0
A41: Prainsa | B41: =COUNTIFS(Table1[Name],Statistics!A41,Table1[Status],"open") -> 0
... A60: Applus | B60: =COUNTIFS(Table1[Name],Statistics!A60,Table1[Status],"open") -> 0
B65: =SUM(B18:B64) -> 80
A74: Alfanar Dep. | B74: Issues No.
A75: Supply chain-Purchasing | B75: =COUNTIFS(Table1[Name],Statistics!A75,Table1[Status],"open") -> 6
A76: Resource Department | B76: =COUNTIFS(Table1[Name],Statistics!A76,Table1[Status],"open") -> 1
A77: PMO | B77: =COUNTIFS(Table1[Name],Statistics!A77,Table1[Status],"open") -> 0
A78: BUSINESS OPERATIONS SUPPORT | B78: =COUNTIFS(Table1[Name],Statistics!A78,Table1[Status],"open") -> 0
A79: Treasury | B79: =COUNTIFS(Table1[Name],Statistics!A79,Table1[Status],"open") -> 0
A80: Construction | B80: =COUNTIFS(Table1[Name],Statistics!A80,Table1[Status],"open") -> 16
A81: T&C | B81: =COUNTIFS(Table1[Name],Statistics!A81,Table1[Status],"open") -> 0
A82: Supplement | B82: =COUNTIFS(Table1[Name],Statistics!A82,Table1[Status],"open") -> 0
A83: Project Team | B83: =COUNTIFS(Table1[Name],Statistics!A83,Table1[Status],"open") -> 7
A84: Tender | B84: =COUNTIFS(Table1[Name],Statistics!A84,Table1[Status],"open") -> 0
B85: =SUM(B75:B84) -> 30
A87: Open | B87: =COUNTIF(Table1[Status],Statistics!A87) -> 222
A88: Closed | B88: =COUNTIF(Table1[Status],Statistics!A88) -> 283
B89: =SUM(B87:B88) -> 505
A91: Priority by SEC | B91: Issues No.
A92: A | B92: =COUNTIFS(Table1[Priority By SEC],Statistics!A92,Table1[Status],"open") -> 148
A93: B | B93: =COUNTIFS(Table1[Priority By SEC],Statistics!A93,Table1[Status],"open") -> 40
A94: C | B94: =COUNTIFS(Table1[Priority By SEC],Statistics!A94,Table1[Status],"open") -> 10
B95: =SUM(B92:B94) -> 198

Sheet Sheet1
B2: SPTC
B3: RITZ
B4: SIEMENS
B5: AES
B6: HITACHI
B7: BCG
B8: LAPP
B9: Hitachi
B10: Arteche
B11: EPC
B12: DAR
B13: Pfisterer Switzerland AG
... B28: Moneer Al Boqami

Sheet May 25 - Achievement
A1: Achievement

Sheet Urgent Support List

Sheet Lists
A1: Status | D1: Issue Type | E1: No. Issues | G1: Issue Owner
A2: Open | D2: Design inputs | E2: =COUNTIFS(Table1[Issue Type],Table3[[#This Row],[Issue Type]],Table1[Status],"open") -> 11 | G2: Client
A3: Closed | D3: Delivery | E3: =COUNTIFS(Table1[Issue Type],Table3[[#This Row],[Issue Type]],Table1[Status],"open") -> 58 | G3: Client/EOT/VO | Q3: HITACHI
D4: Installation | E4: =COUNTIFS(Table1[Issue Type],Table3[[#This Row],[Issue Type]],Table1[Status],"open") -> 11 | G4: Vendor | Q4: SPTC
D5: Test & Comm. | E5: =COUNTIFS(Table1[Issue Type],Table3[[#This Row],[Issue Type]],Table1[Status],"open") -> 6 | G5: Client | Q5: SIEMENS
D6: Design Submission / Rectifications | E6: =COUNTIFS(Table1[Issue Type],Table3[[#This Row],[Issue Type]],Table1[Status],"open") -> 27 | G6: Alfanar | K6: Vendors | L6: Design inputs | Q6: RITZ
D7: Resources | E7: =COUNTIFS(Table1[Issue Type],Table3[[#This Row],[Issue Type]],Table1[Status],"open") -> 2 | K7: Vendors | L7: Delivery | Q7: TRENCH
D8: PO Issuance Delay | E8: =COUNTIFS(Table1[Issue Type],Table3[[#This Row],[Issue Type]],Table1[Status],"open") -> 8 | K8: Vendors | L8: Installation | Q8: AES
D9: Revised PO | E9: =COUNTIFS(Table1[Issue Type],Table3[[#This Row],[Issue Type]],Table1[Status],"open") -> 0 | K9: Vendors | L9: Test & Comm. | Q9: BCG
D10: Local Content | E10: =COUNTIFS(Table1[Issue Type],Table3[[#This Row],[Issue Type]],Table1[Status],"open") -> 0 | K10: Vendors | L10: Design Submission / Rectifications | Q10: LAPP
D11: IQAMA Issues | E11: =COUNTIFS(Table1[Issue Type],Table3[[#This Row],[Issue Type]],Table1[Status],"open") -> 0 | K11: Resources | L11: Resources | Q11: Hitachi
D12: Construction | E12: =COUNTIFS(Table1[Issue Type],Table3[[#This Row],[Issue Type]],Table1[Status],"open") -> 24 | K12: Procurement | L12: PO Issuance Delay | Q12: Arteche
D13: Treasury | E13: =COUNTIFS(Table1[Issue Type],Table3[[#This Row],[Issue Type]],Table1[Status],"open") -> 0 | K13: Procurement | L13: Revised PO | Q13: EPC
D14: Permits / Request from Client | E14: =COUNTIFS(Table1[Issue Type],Table3[[#This Row],[Issue Type]],Table1[Status],"open") -> 15 | L14: Local Content | Q14: DAR
D15: Shutdown | E15: =COUNTIFS(Table1[Issue Type],Table3[[#This Row],[Issue Type]],Table1[Status],"open") -> 9 | L15: IQAMA Issues | Q15: NCC
D16: VO/EOT | E16: =COUNTIFS(Table1[Issue Type],Table3[[#This Row],[Issue Type]],Table1[Status],"open") -> 5 | L16: Construction | Q16: LEEEC
D17: Client Issues | E17: =COUNTIFS(Table1[Issue Type],Table3[[#This Row],[Issue Type]],Table1[Status],"open") -> 18 | Q17: AL WABEL
D18: Tender | E18: =COUNTIFS(Table1[Issue Type],Table3[[#This Row],[Issue Type]],Table1[Status],"open") -> 0 | Q18: E-Techs
D19: Close Out | E19: =COUNTIFS(Table1[Issue Type],Table3[[#This Row],[Issue Type]],Table1[Status],"open") -> 2 | Q19: Tri Delta
D20: Funding | E20: =COUNTIFS(Table1[Issue Type],Table3[[#This Row],[Issue Type]],Table1[Status],"open") -> 2 | Q20: MSCL
D21: FAT Test | E21: =COUNTIFS(Table1[Issue Type],Table3[[#This Row],[Issue Type]],Table1[Status],"open") -> 0 | Q21: Al Majal
Q22: Hyosung
Q23: Hyundai
Q24: ABB
Q25: Maricon_UAE
Q26: M/S FAWAZ REFR & AIRCONDITIONING
Q27: Prainsa
Q28: Al Babtain
Q29: Moneer Al Boqami
Q30: GE
Q31: Rezayat trading Company

Sheet Vendor Issues
A9: Project | B9: SN | C9: Issue owner | D9: Name | E9: date Issued | F9: Main Issue | G9: Impact | H9: Action Taken | I9: Action Required | J9: Action By | K9: Planned Target | L9: Forecast/Expected Target | M9: Status | N9: (Schedule/Cost)Impact | O9: Remarks
A10: PE-234 | B10: 3 | C10: Vendor | D10: Hitachi/SEC | E10: 45581 | F10: HV test not yet started which scheduled on 16 Feb 2025. | G10: High | H10: Email sent to the client on 16 Oct 2024 to coordinate with client and supplier to start HV test. On 09 Feb 25 replied by cancelation of HV test and rescheduled by Apr’25 | I10: Client and supplier must expedite in start HV test. | J10: Hitachi/SEC | K10: 45704 | L10: 45762 | M10: Open | N10: Schedule 2 Months
A11: PE-283 | B11: 1 | C11: Vendor | D11: SPTC | E11: 45580 | F11: Delay in manufacturing of Power Transformer by SPTC as the expected FAT is (Aug-25) | G11: High | H11: EOT submitted to recover the delay in Transformer delivery, and it is under approval with SEC | I11: Full support is required from vendor to expedite the material delivery, We should follow up with SEC for the approval of EOT | J11: PM Vendor | K11: 45655 | L11: 45901 | M11: Open | N11: 8 Months Delay | O11: Issue still affecting our project's progress
A12: PE-283 | B12: 2 | C12: Vendor | D12: SIEMENS | E12: 45580 | F12: Delay in manufacturing of SWGR due to design change (Jul-25) | G12: High | H12: Regular meetings and factory visits with SIEMENS are being conducted to expedite the delivery timeline. | I12: Full support is required from vendor to expedite the material delivery. There is a possibility of delivering it by April 2025 if Alfanar covers the transportation cost via air freight (SAR 600K) from Germany to the Jeddah factory. However, this would require senior management approval. | J12: MNGT/PM /Vendor | K12: 45636 | L12: 45839 | M12: Open | N12: 3 Months Delay | O12: Issue still affecting our project's progress
A13: PE-283 | B13: 3 | C13: Vendor | D13: HITACHI | E13: 45580 | F13: Delay in manufacturing of GIS by HITACHI due to manufacturing demand & design change for 2 times | G13: High | H13: Frequent meeting & Factory visit with HITACHI to enhanced LCC Panels delivery to mid of Mar 25, GIS FAT Date , Apr 25 . | I13: Full support is required from vendor to expedite the material delivery. | J13: PM Vendor | K13: 45651 | L13: 45778 | M13: Open | N13: 4 Months Delay | O13: Issue still affecting our project's progress
A14: PE-283 | B14: 4 | C14: Vendor | D14: RITZ | F14: Ther's a delay from the Vendor in supplying (SIS) | G14: High | H14: We make several meetings with them, and also inform Purchase department GAFM has been issued in Aug-24 | I14: Management should take action with them, Letter should be issued to claim their delay from Purchase department | J14: PD/Mng | K14: 45731 | L14: 45838 | M14: Open | N14: 4 Months Delay
A15: PE-283 | B15: 5 | C15: Vendor | D15: TRENCH | E15: 45597 | F15: Delay in manufacturing of out doors CT by TRENCH due to force majeure (Flood) stopped production line at the supplier Factory. | G15: Medium | H15: Frequent meeting with TRENCH to enhance deliver to Apr 25 to mitigate the delay. | I15: Full support is required from vendor to expedite the material delivery. | J15: PM Vendor | K15: 45597 | L15: 45823 | M15: Open | N15: 3 Months Delay
A16: PE-284 | B16: 1 | C16: Vendor | D16: SPTC | E16: 45543 | F16: Delay in manufacturing of Power Transformer by SPTC as the FAT is Aug-25 | G16: High | H16: Frequent meeting & Factory visit with SPTC to enhance deliver before Apr 25 to mitigate the delay as our TCC Contractual is 12-Jul-25​ | I16: Full support is required from vendor to expedite the material delivery, We should follow up with SEC for the approval of EOT | J16: PM/Vendor/Client | K16: 45736 | L16: 45884 | M16: Open | N16: 6 months. | O16: Major delay of project
A17: PE-284 | B17: 3 | C17: Vendor | D17: Hitachi | E17: 45653 | F17: Delay in manufacturing of GIS by HITACHI due to manufacturing demand & design change for 2 times the final date should be confirmed by them | G17: High | H17: Frequent meeting & Factory visit with HITACHI to enhance deliver before Apr25 to mitigate the delay​ | I17: Higher management should take this matter with Hitachi | J17: PM/Vendor/Client | K17: 45725 | L17: 45777 | M17: Open | N17: 2 months
A18: PE-284 | B18: 4 | C18: Vendor | D18: RITZ | E18: 45641 | F18: Ther's a delay from the Vendor in supplying (SIS) | G18: High | H18: We make several meetings with them, and also inform Purchase department GAFM has been issued in Aug-24 | I18: Management should take action with them, Letter should be issued to claim their delay from Purchase department | J18: PD/Mng | K18: 45731 | L18: 45838 | M18: Open | N18: 4 Months Delay
A19: PE-284 | B19: 5 | C19: Vendor | D19: Siemens | E19: 45571 | F19: Delay in manufacturing of SWGR due to design change as the delivery is expected by End of May 25 | G19: Medium | H19: Frequent meeting & Factory visit with SIEMENS to enhance deliver before End of Apr 25 to mitigate the delay​ | I19: Full support is required from vendor to expedite the material delivery. There is a possibility of delivering it by April 2025 if Alfanar covers the transportation cost via air freight (SAR 600K) from Germany to the Jeddah factory. However, this would require senior management approval. | J19: PM/Vendor/Client | K19: 45735 | L19: 45839 | M19: Open | N19: 3 months
A20: PE-284 | B20: 6 | C20: Vendor | D20: Trench | E20: 45623 | F20: Delay in manufacturing of CT by TRENCH due to recent Flood as the expected delivery is May-25 | G20: Medium | H20: Frequent meeting with TRENCH to enhance deliver before MAR25 to mitigate the delay​ | I20: Higher management had made meeting and decided already with TRENCH to deliver in May. ​ | J20: PM/Vendor/Client | K20: 45687 | L20: 45823 | M20: Open | N20: 4 months
A21: PE-298 | B21: 4 | C21: Vendor | D21: AES | E21: 45659 | F21: Delayed GAFM in Protection , Metering and SAS due to delayed Detail Design approval | G21: High | H21: 1. Partial GAFM released for Protection panels 2. Meetings and foolow ups getting conducted for expediting design approvals 3. Close follow up with Factory to get the submittals and compliances | I21: 1.After GAFM required commitment from Alfanar factory for FAT date in line with Project schedule. | J21: PM/Procurement/ vendor | K21: 45667 | L21: 45757 | M21: Open | N21: 70 Days delays | O21: Except SAS panels, GAFM to be released
A22: PE-298 | B22: 5 | C22: Vendor | D22: AES | F22: No Confirmed date from AES for the FAT and Delivery date for Equipment (SWGR, SAS, Protection, Telecom, Panels, Cyper Security) | G22: High | H22: Several Meetings arranged with AES to expedite design phases and Provide GAFM and now waiting for target dates for these Equipment | I22: High management follow up to get the delivery in line with the time schedule | J22: PM | K22: 45867 | L22: 45867 | M22: Open
A23: PE-298 | B23: 6 | C23: Vendor | D23: Hitachi | F23: CBK fuel liquid changed by supplier with anthor liquid oil and it is required to get approval from Sec for the new liquid oil | G23: Medium | H23: Follow up with supplier to confrim that new oil get approval | I23: High supervision with the supplier | J23: PM | K23: 45839 | L23: 45899 | M23: Open
A24: PE-311 | B24: 1 | C24: Vendor | D24: AES | E24: 45656 | F24: Delay from Alfanar factory in providing the designs and delivery date. Such as (Grounding conductor, protection, SAS & telecom, SWGR, Cyper security, Panels).​ | G24: High | H24: Arranged several meetings with AES and a warning letter has been issued. Telecom and Grounding situation has been enhanced. | I24: Close follow up on the remaining Points below: 1. Protection detail design and delivery 2. SAS sysetm Design and Delivery 3. Fault Locator Detail Design and Delivery 4. AES : to share AC Panels base design R02 5. AES : to share DC Panels base design R01 | J24: PM/Vendor/Client | K24: 45921 | L24: 45960 | M24: Open | N24: Schedule. 1 month
A25: PE-311 | B25: 7 | C25: Vendor | D25: LAPP | E25: 45615 | F25: Insulators FAT schedule need to be enhanced from Dec’25 to Oct’2025.​ | G25: Medium | H25: 1. We have issued a letter to SEPDC with force major case due to the fire occurred at Lapp factory 2. Several meeting have been arranged with LAPP to reduce the delivery 3. Lapp confirmed the FAT by October 2025. | I25: Follow up and try to enhnace the delivery more if possible Delivery to be confirmed after GAFM after Plan & Profile approval. | J25: PM/Vendor | K25: 46014 | L25: 46014 | M25: Open | N25: Schedule. 3 month
A26: PE-313 | B26: 2 | C26: Vendor | D26: Hitachi | F26: Delay in receiving the final date of Delivery from Hitachi for 132 KV GIS | G26: High | H26: Several Meetings and mails have been sent from Project team to accelerate the feedback from Vendor | I26: Follow up with the vendor to have final feedback | J26: PM | K26: 45801 | L26: 45823 | M26: Open
A27: PE-313 | B27: 3 | C27: Vendor | D27: SPTC | E27: 45421 | F27: Delay in delivery of 132KV Power Transformer according to vendor’s plan ( SPTC). Delivery in Feb’26.​ | G27: High | H27: Letter has been sent to the client on 09 May' 2024 for swapping the supplier from SPTC to LEEEC to meet the delivery schedule as per planned delivery date on May' 2025. Another letter sent to the client regarding the delay in response to swap the manufacturer on 08 Aug 2024. | I27: Close follow up with manufacturer to enhance delivery date. | J27: PM/Vendor | K27: 25/12/2025 as per supplier | L27: 46079 | M27: Open | N27: Schedule. 9 Months | O27: our schedule date in May, but the PO date in December, delivery now after our TCC
A28: PE-313 | B28: 4 | C28: Vendor | D28: Arteche | E28: 45704 | F28: The vendor of Free-Standing CT sent an email to delay the delivery to be on Mar’26 which scheduled to be on Jul’25 | G28: High | H28: The issue has been escalated to supply chain and supply chain sent official letter to the supplier. | I28: The supplier must follow the contractual delivery schedule. | J28: PM/Vendor | K28: 45851 | L28: 46098 | M28: Open | N28: Schedule. 8 Months | O28: After our TCC
A29: PE-313 | B29: 5 | C29: Vendor | D29: AES | E29: 45667 | F29: Delay in the confirmation date for FAT and delivery for the main Material and Equipment (SWGR, Station service TR, Panels, Protection, SAS, Communication) | G29: High | H29: Several mails has been sent to them requiring the FAT date Max by 1st of June | I29: Follow up with Vendoe to confirm the final date of delivery of every item | J29: PM | K29: 45762 | L29: 45823 | M29: Open
A30: PE-313 | B30: 5 | C30: Vendor | D30: EPC | E30: 45722 | F30: Delay in delivery of precast which scheduled to be delivered on Feb’25. | G30: Medium | H30: Warning email has been sent to the vendor on 10 Mar 2025 regarding the delay of manufacturing progress. | I30: Pushing the supplier to expedite in delivery of precast. | J30: PM/Vendor | K30: 45708 | L30: 45777 | M30: Open | N30: Schedule. 3 Months
A31: PE-325 | B31: 6 | C31: Vendor | D31: AES | E31: 45656 | F31: Delay from Alfanar factory in providing the designs and delivery date. Such as ( protection, SAS & telecom).​ | G31: High | H31: Arranged several meetings with AES and a warning letter has been issued. Telecom and Grounding situation has been enhanced. | I31: Close follow up on the remaining Points below: 1. Protection detail design and delivery 2. SAS sysetm Design and Delivery 3. Fault Locator Detail Design and Delivery | J31: PM/Vendor/Client | K31: 45672 | L31: 45729 | M31: Open | N31: 30 days delay
A32: PE-325 | B32: 9 | C32: Vendor | D32: AES | F32: No Confirmed date from AES for the FAT and Delivery date for Equipment (SWGR, SAS,MV Cables Protection, Telecom, Panels, Cyper Security) | G32: High | H32: Several Meetings arranged with AES to expedite design phases and Provide GAFM and now waiting for target dates for these Equipment | I32: High management follow up to get the delivery in line with the time schedule as they confirmed date by End of Aug while the planned is 15-Jul | J32: PM | K32: 45853 | L32: 45900 | M32: Open
A33: PE-325 | B33: 10 | C33: Vendor | D33: LAPP | E33: 45615 | F33: Insulators FAT schedule need to be enhanced from Dec’25 to Oct’2025.​ | G33: Medium | H33: 1. We have issued a letter to SEPDC with force major case due to the fire occurred at Lapp factory 2. Several meeting have been arranged with LAPP to reduce the delivery 3. Lapp confirmed the FAT by October 2025. | I33: Follow up and try to enhnace the delivery more if possible Delivery to be confirmed after GAFM after Plan & Profile approval. | J33: PM/Vendor | K33: 46021 | L33: 45735 | M33: Open | N33: schedule impact
