Workbook

Sheet Marketing-Related Sheet
A1: S.N. | B1: Project Code | C1: Project Name | D1: Project Managers Name | E1: Region | F1: Marketing Required (Yes/No) | G1: Requirement Provided (Yes/No) | H1: PO Creation (Yes/No) | I1: Marketing Completion (Yes/No) | J1: Required for Closing Projects (Yes/No/N/A) | K1: Start Date | L1: Planned % | M1: Actual % | N1: Var. | O1: Client | P1: City | Q1: EOT STATUS (Submitted/Approved/Under Approval/ N/A) | R1: TCC | U1: FAC | X1: Remarks
K2: Start Date | R2: Contract Date | S2: Revised Date | T2: Forecast Date | U2: Contract Date | V2: Revised Date | W2: Forecast Date | X2: Remarks
C3: CENTRAL REGION UNIT (BASIL ALHAKAMI)
A4: 1 | B4: PE-215 | C4: =VLOOKUP(B4,'Detailed Update'!B:C,2,FALSE) -> SMP - O&M 3 Yrs | D4: =VLOOKUP(B4,'Updated Progress % + TCC'!B:D,3,FALSE) -> Mohamed Sabri | E4: =VLOOKUP(B4,'Updated Progress % + TCC'!B:J,9,FALSE) -> Central | F4: =IF(M4>70.01%,"No","Yes") -> No | G4: No | H4: No | I4: No | K4: =VLOOKUP(B4,'Detailed Update'!B:D,3,FALSE) -> 44652 | L4: =VLOOKUP(B4,'Detailed Update'!B:I,4,FALSE) -> 1 | M4: =VLOOKUP(B4,'Detailed Update'!B:I,5,FALSE) -> 1 | N4: =M4-L4 -> 0 | O4: =VLOOKUP(B4,'Detailed Update'!B:I,6,FALSE) -> SEC | P4: =VLOOKUP(B4,'Detailed Update'!B:I,8,FALSE) -> Riyadh | Q4: Approved | R4: =VLOOKUP(B4,'Detailed Update'!B:T,11,FALSE) -> 45442 | S4: =VLOOKUP(B4,'Detailed Update'!B:T,12,FALSE) -> 45812 | T4: =VLOOKUP(B4,'Detailed Update'!B:T,13,FALSE) -> 45812 | U4: =VLOOKUP(B4,'Detailed Update'!B:T,17,FALSE) -> 45442 | V4: =VLOOKUP(B4,'Detailed Update'!B:S,18,FALSE) -> 45812 | W4: =VLOOKUP(B4,'Detailed Update'!B:T,19,FALSE) -> 45812 | X4: =VLOOKUP(B4,'Detailed Update'!B:U,20,FALSE) -> All certification Received
A5: 2 | B5: PE-226 | C5: =VLOOKUP(B5,'Detailed Update'!B:C,2,FALSE) -> KHASM-AL-AAN BSP | D5: =VLOOKUP(B5,'Updated Progress % + TCC'!B:D,3,FALSE) -> Amin El Sayed | E5: =VLOOKUP(B5,'Updated Progress % + TCC'!B:J,9,FALSE) -> Central | F5: =IF(M5>70.01%,"No","Yes") -> No | G5: No | H5: No | I5: No | K5: =VLOOKUP(B5,'Detailed Update'!B:D,3,FALSE) -> 44350 | L5: =VLOOKUP(B5,'Detailed Update'!B:I,4,FALSE) -> 1 | M5: =VLOOKUP(B5,'Detailed Update'!B:I,5,FALSE) -> 0.863 | N5: =M5-L5 -> -0.137 | O5: =VLOOKUP(B5,'Detailed Update'!B:I,6,FALSE) -> SEC | P5: =VLOOKUP(B5,'Detailed Update'!B:I,8,FALSE) -> Riyadh | Q5: Approved | R5: =VLOOKUP(B5,'Detailed Update'!B:T,11,FALSE) -> 44960 | S5: =VLOOKUP(B5,'Detailed Update'!B:T,12,FALSE) -> 45657 | T5: =VLOOKUP(B5,'Detailed Update'!B:T,13,FALSE) -> 46411 | U5: =VLOOKUP(B5,'Detailed Update'!B:T,17,FALSE) -> 45141 | V5: =VLOOKUP(B5,'Detailed Update'!B:S,18,FALSE) -> 45808 | W5: =VLOOKUP(B5,'Detailed Update'!B:T,19,FALSE) -> 46563 | X5: =VLOOKUP(B5,'Detailed Update'!B:U,20,FALSE) -> Partial TCC Received | Project on Hold
A6: 3 | B6: PM-223 | C6: =VLOOKUP(B6,'Detailed Update'!B:C,2,FALSE) -> GASCO - 2 | D6: =VLOOKUP(B6,'Updated Progress % + TCC'!B:D,3,FALSE) -> Fathi Mohamed | E6: =VLOOKUP(B6,'Updated Progress % + TCC'!B:J,9,FALSE) -> Central | F6: =IF(M6>70.01%,"No","Yes") -> No | G6: No | H6: No | I6: No | K6: =VLOOKUP(B6,'Detailed Update'!B:D,3,FALSE) -> 44368 | L6: =VLOOKUP(B6,'Detailed Update'!B:I,4,FALSE) -> 1 | M6: =VLOOKUP(B6,'Detailed Update'!B:I,5,FALSE) -> 0.9991 | N6: =M6-L6 -> -0.0009 | O6: =VLOOKUP(B6,'Detailed Update'!B:I,6,FALSE) -> GASCO | P6: =VLOOKUP(B6,'Detailed Update'!B:I,8,FALSE) -> Riyadh | Q6: Approved | R6: =VLOOKUP(B6,'Detailed Update'!B:T,11,FALSE) -> 45136 | S6: =VLOOKUP(B6,'Detailed Update'!B:T,12,FALSE) -> 45747 | T6: =VLOOKUP(B6,'Detailed Update'!B:T,13,FALSE) -> 45961 | U6: =VLOOKUP(B6,'Detailed Update'!B:T,17,FALSE) -> 45136 | V6: =VLOOKUP(B6,'Detailed Update'!B:S,18,FALSE) -> 45747 | W6: =VLOOKUP(B6,'Detailed Update'!B:T,19,FALSE) -> 45961 | X6: =VLOOKUP(B6,'Detailed Update'!B:U,20,FALSE) -> Initial Handing over received
A7: 4 | B7: PE-228 | C7: =VLOOKUP(B7,'Detailed Update'!B:C,2,FALSE) -> SVC QASSIM -2 | D7: =VLOOKUP(B7,'Updated Progress % + TCC'!B:D,3,FALSE) -> Hany Kamal | E7: =VLOOKUP(B7,'Updated Progress % + TCC'!B:J,9,FALSE) -> Central | F7: =IF(M7>70.01%,"No","Yes") -> No | G7: No | H7: No | I7: No | K7: =VLOOKUP(B7,'Detailed Update'!B:D,3,FALSE) -> 44444 | L7: =VLOOKUP(B7,'Detailed Update'!B:I,4,FALSE) -> 1 | M7: =VLOOKUP(B7,'Detailed Update'!B:I,5,FALSE) -> 0.9928 | N7: =M7-L7 -> -0.0072 | O7: =VLOOKUP(B7,'Detailed Update'!B:I,6,FALSE) -> SEC | P7: =VLOOKUP(B7,'Detailed Update'!B:I,8,FALSE) -> Riyadh | Q7: Approved | R7: =VLOOKUP(B7,'Detailed Update'!B:T,11,FALSE) -> 45235 | S7: =VLOOKUP(B7,'Detailed Update'!B:T,12,FALSE) -> 45733 | T7: =VLOOKUP(B7,'Detailed Update'!B:T,13,FALSE) -> 45733 | U7: =VLOOKUP(B7,'Detailed Update'!B:T,17,FALSE) -> 45356 | V7: =VLOOKUP(B7,'Detailed Update'!B:S,18,FALSE) -> 45855 | W7: =VLOOKUP(B7,'Detailed Update'!B:T,19,FALSE) -> 46264 | X7: =VLOOKUP(B7,'Detailed Update'!B:U,20,FALSE) -> TCC Received.
A8: 5 | B8: PE-233 | C8: =VLOOKUP(B8,'Detailed Update'!B:C,2,FALSE) -> Tabarjal 380KV BSP Expn. | D8: =VLOOKUP(B8,'Updated Progress % + TCC'!B:D,3,FALSE) -> Malik Qarioutyee | E8: =VLOOKUP(B8,'Updated Progress % + TCC'!B:J,9,FALSE) -> Central | F8: =IF(M8>70.01%,"No","Yes") -> No | G8: No | H8: No | I8: No | K8: =VLOOKUP(B8,'Detailed Update'!B:D,3,FALSE) -> 44542 | L8: =VLOOKUP(B8,'Detailed Update'!B:I,4,FALSE) -> 1 | M8: =VLOOKUP(B8,'Detailed Update'!B:I,5,FALSE) -> 0.99 | N8: =M8-L8 -> -0.01 | O8: =VLOOKUP(B8,'Detailed Update'!B:I,6,FALSE) -> SEC | P8: =VLOOKUP(B8,'Detailed Update'!B:I,8,FALSE) -> Riyadh | Q8: Approved | R8: =VLOOKUP(B8,'Detailed Update'!B:T,11,FALSE) -> 45272 | S8: =VLOOKUP(B8,'Detailed Update'!B:T,12,FALSE) -> 46021 | T8: =VLOOKUP(B8,'Detailed Update'!B:T,13,FALSE) -> 46233 | U8: =VLOOKUP(B8,'Detailed Update'!B:T,17,FALSE) -> 45424 | V8: =VLOOKUP(B8,'Detailed Update'!B:S,18,FALSE) -> 46172 | W8: =VLOOKUP(B8,'Detailed Update'!B:T,19,FALSE) -> 46386 | X8: =VLOOKUP(B8,'Detailed Update'!B:U,20,FALSE) -> Partial TCC received on 16-Jan-24
A9: 6 | B9: PE-245 | C9: =VLOOKUP(B9,'Detailed Update'!B:C,2,FALSE) -> Hail OHTL | D9: =VLOOKUP(B9,'Updated Progress % + TCC'!B:D,3,FALSE) -> Rafa Awad Al Hassan | E9: =VLOOKUP(B9,'Updated Progress % + TCC'!B:J,9,FALSE) -> Central | F9: =IF(M9>70.01%,"No","Yes") -> No | G9: No | H9: No | I9: No | K9: =VLOOKUP(B9,'Detailed Update'!B:D,3,FALSE) -> 44788 | L9: =VLOOKUP(B9,'Detailed Update'!B:I,4,FALSE) -> 1 | M9: =VLOOKUP(B9,'Detailed Update'!B:I,5,FALSE) -> 0.9612 | N9: =M9-L9 -> -0.0388 | O9: =VLOOKUP(B9,'Detailed Update'!B:I,6,FALSE) -> SEC | P9: =VLOOKUP(B9,'Detailed Update'!B:I,8,FALSE) -> Riyadh | Q9: Approved | R9: =VLOOKUP(B9,'Detailed Update'!B:T,11,FALSE) -> 45427 | S9: =VLOOKUP(B9,'Detailed Update'!B:T,12,FALSE) -> 45656 | T9: =VLOOKUP(B9,'Detailed Update'!B:T,13,FALSE) -> 46193 | U9: =VLOOKUP(B9,'Detailed Update'!B:T,17,FALSE) -> 45580 | V9: =VLOOKUP(B9,'Detailed Update'!B:S,18,FALSE) -> 45804 | W9: =VLOOKUP(B9,'Detailed Update'!B:T,19,FALSE) -> 46341 | X9: =VLOOKUP(B9,'Detailed Update'!B:U,20,FALSE) -> One line Energizaed. Another line by 20-Jun-26. Change Order approval is critical
A10: 7 | B10: PE-247 | C10: =VLOOKUP(B10,'Detailed Update'!B:C,2,FALSE) -> RIYADH SEDRA-2 | D10: =VLOOKUP(B10,'Updated Progress % + TCC'!B:D,3,FALSE) -> Anas Derzy | E10: =VLOOKUP(B10,'Updated Progress % + TCC'!B:J,9,FALSE) -> Central | F10: =IF(M10>70.01%,"No","Yes") -> No | G10: No | H10: No | I10: No | K10: =VLOOKUP(B10,'Detailed Update'!B:D,3,FALSE) -> 44833 | L10: =VLOOKUP(B10,'Detailed Update'!B:I,4,FALSE) -> 1 | M10: =VLOOKUP(B10,'Detailed Update'!B:I,5,FALSE) -> 0.991 | N10: =M10-L10 -> -0.009 | O10: =VLOOKUP(B10,'Detailed Update'!B:I,6,FALSE) -> Roshn | P10: =VLOOKUP(B10,'Detailed Update'!B:I,8,FALSE) -> Riyadh | Q10: Under Approval | R10: =VLOOKUP(B10,'Detailed Update'!B:T,11,FALSE) -> 45538 | S10: =VLOOKUP(B10,'Detailed Update'!B:T,12,FALSE) -> 45538 | T10: =VLOOKUP(B10,'Detailed Update'!B:T,13,FALSE) -> 45920 | U10: =VLOOKUP(B10,'Detailed Update'!B:T,17,FALSE) -> 45599 | V10: =VLOOKUP(B10,'Detailed Update'!B:S,18,FALSE) -> 45599 | W10: =VLOOKUP(B10,'Detailed Update'!B:T,19,FALSE) -> 46264 | X10: =VLOOKUP(B10,'Detailed Update'!B:U,20,FALSE) -> Partial TCC received & 90% invoice approved
A11: 8 | B11: PE-248 | C11: =VLOOKUP(B11,'Detailed Update'!B:C,2,FALSE) -> PP10 Conv. | D11: =VLOOKUP(B11,'Updated Progress % + TCC'!B:D,3,FALSE) -> Rabei Mohamed Mohamed Attia Daoud | E11: =VLOOKUP(B11,'Updated Progress % + TCC'!B:J,9,FALSE) -> Central | F11: =IF(M11>70.01%,"No","Yes") -> No | G11: No | H11: No | I11: No | K11: =VLOOKUP(B11,'Detailed Update'!B:D,3,FALSE) -> 44847 | L11: =VLOOKUP(B11,'Detailed Update'!B:I,4,FALSE) -> 1 | M11: =VLOOKUP(B11,'Detailed Update'!B:I,5,FALSE) -> 0.9576 | N11: =M11-L11 -> -0.0424 | O11: =VLOOKUP(B11,'Detailed Update'!B:I,6,FALSE) -> SEC | P11: =VLOOKUP(B11,'Detailed Update'!B:I,8,FALSE) -> Riyadh | Q11: Approved | R11: =VLOOKUP(B11,'Detailed Update'!B:T,11,FALSE) -> 45517 | S11: =VLOOKUP(B11,'Detailed Update'!B:T,12,FALSE) -> 46018 | T11: =VLOOKUP(B11,'Detailed Update'!B:T,13,FALSE) -> 46263 | U11: =VLOOKUP(B11,'Detailed Update'!B:T,17,FALSE) -> 45974 | V11: =VLOOKUP(B11,'Detailed Update'!B:S,18,FALSE) -> 46477 | W11: =VLOOKUP(B11,'Detailed Update'!B:T,19,FALSE) -> 46720 | X11: =VLOOKUP(B11,'Detailed Update'!B:U,20,FALSE) -> TCC milestone achieved. Certification not receied. Punchlist Clearance is critical
A12: 9 | B12: PE-255 | C12: =VLOOKUP(B12,'Detailed Update'!B:C,2,FALSE) -> 380kv D/C OHTL LILO SAAD OHTL | D12: =VLOOKUP(B12,'Updated Progress % + TCC'!B:D,3,FALSE) -> Malik Al Qaryotee | E12: =VLOOKUP(B12,'Updated Progress % + TCC'!B:J,9,FALSE) -> Central | F12: =IF(M12>70.01%,"No","Yes") -> No | G12: Yes | K12: =VLOOKUP(B12,'Detailed Update'!B:D,3,FALSE) -> 44857 | L12: =VLOOKUP(B12,'Detailed Update'!B:I,4,FALSE) -> 0.8998 | M12: =VLOOKUP(B12,'Detailed Update'!B:I,5,FALSE) -> 0.7518 | N12: =M12-L12 -> -0.148 | O12: =VLOOKUP(B12,'Detailed Update'!B:I,6,FALSE) -> SEC | P12: =VLOOKUP(B12,'Detailed Update'!B:I,8,FALSE) -> Riyadh | Q12: Approved | R12: =VLOOKUP(B12,'Detailed Update'!B:T,11,FALSE) -> 45283 | S12: =VLOOKUP(B12,'Detailed Update'!B:T,12,FALSE) -> 45813 | T12: =VLOOKUP(B12,'Detailed Update'!B:T,13,FALSE) -> 46386 | U12: =VLOOKUP(B12,'Detailed Update'!B:T,17,FALSE) -> 45466 | V12: =VLOOKUP(B12,'Detailed Update'!B:S,18,FALSE) -> 45996 | W12: =VLOOKUP(B12,'Detailed Update'!B:T,19,FALSE) -> 46569 | X12: =VLOOKUP(B12,'Detailed Update'!B:U,20,FALSE) -> 1. Amendment for New circuit Arrangement at Tapping Point . 2. Outage requirements 3. Hardware fittings material for re-route portion
A13: 10 | B13: PE-256 | C13: =VLOOKUP(B13,'Detailed Update'!B:C,2,FALSE) -> Sudair PV 380KV BSP | D13: =VLOOKUP(B13,'Updated Progress % + TCC'!B:D,3,FALSE) -> Tariq Mahmoud Ali Alsheyab | E13: =VLOOKUP(B13,'Updated Progress % + TCC'!B:J,9,FALSE) -> Central | F13: =IF(M13>70.01%,"No","Yes") -> No | G13: No | H13: No | I13: No | K13: =VLOOKUP(B13,'Detailed Update'!B:D,3,FALSE) -> 44867 | L13: =VLOOKUP(B13,'Detailed Update'!B:I,4,FALSE) -> 1 | M13: =VLOOKUP(B13,'Detailed Update'!B:I,5,FALSE) -> 0.7877 | N13: =M13-L13 -> -0.2123 | O13: =VLOOKUP(B13,'Detailed Update'!B:I,6,FALSE) -> SEC | P13: =VLOOKUP(B13,'Detailed Update'!B:I,8,FALSE) -> Riyadh | Q13: Under Approval | R13: =VLOOKUP(B13,'Detailed Update'!B:T,11,FALSE) -> 45537 | S13: =VLOOKUP(B13,'Detailed Update'!B:T,12,FALSE) -> 45537 | T13: =VLOOKUP(B13,'Detailed Update'!B:T,13,FALSE) -> 46325 | U13: =VLOOKUP(B13,'Detailed Update'!B:T,17,FALSE) -> 45690 | V13: =VLOOKUP(B13,'Detailed Update'!B:S,18,FALSE) -> 45690 | W13: =VLOOKUP(B13,'Detailed Update'!B:T,19,FALSE) -> 46478 | X13: =VLOOKUP(B13,'Detailed Update'!B:U,20,FALSE) -> SS portion energized. Delay in Receiving Permit UGC works and inside PP9 works (MTO,LOA& ARAMCO Permits)
A14: 11 | B14: PE-259 | C14: =VLOOKUP(B14,'Detailed Update'!B:C,2,FALSE) -> WAAD AL SHAMAAL 380KV BSP | D14: =VLOOKUP(B14,'Updated Progress % + TCC'!B:D,3,FALSE) -> Muhannad Ibrahim Al Heh | E14: =VLOOKUP(B14,'Updated Progress % + TCC'!B:J,9,FALSE) -> Central | F14: =IF(M14>70.01%,"No","Yes") -> No | G14: No | H14: No | I14: No | K14: =VLOOKUP(B14,'Detailed Update'!B:D,3,FALSE) -> 44871 | L14: =VLOOKUP(B14,'Detailed Update'!B:I,4,FALSE) -> 1 | M14: =VLOOKUP(B14,'Detailed Update'!B:I,5,FALSE) -> 0.9693 | N14: =M14-L14 -> -0.0307 | O14: =VLOOKUP(B14,'Detailed Update'!B:I,6,FALSE) -> SEC | P14: =VLOOKUP(B14,'Detailed Update'!B:I,8,FALSE) -> Riyadh | Q14: Approved | R14: =VLOOKUP(B14,'Detailed Update'!B:T,11,FALSE) -> 45611 | S14: =VLOOKUP(B14,'Detailed Update'!B:T,12,FALSE) -> 45807 | T14: =VLOOKUP(B14,'Detailed Update'!B:T,13,FALSE) -> 46356 | U14: =VLOOKUP(B14,'Detailed Update'!B:T,17,FALSE) -> 45762 | V14: =VLOOKUP(B14,'Detailed Update'!B:S,18,FALSE) -> 45960 | W14: =VLOOKUP(B14,'Detailed Update'!B:T,19,FALSE) -> 46509 | X14: =VLOOKUP(B14,'Detailed Update'!B:U,20,FALSE) -> Paritally Energized on 09-Feb-26 | Delay in receiving outage to enrgize CKT 2 Wind to Waad Alshamaal & Wind to TABARJAL energization (expected by Oct 26)
A15: 12 | B15: PE-264 | C15: =VLOOKUP(B15,'Detailed Update'!B:C,2,FALSE) -> TABARJAL-B 13213.8 KV S/S IN JOUF | D15: =VLOOKUP(B15,'Updated Progress % + TCC'!B:D,3,FALSE) -> Khalid Mohamed Aql | E15: =VLOOKUP(B15,'Updated Progress % + TCC'!B:J,9,FALSE) -> Central | F15: =IF(M15>70.01%,"No","Yes") -> No | G15: No | H15: No | I15: No | K15: =VLOOKUP(B15,'Detailed Update'!B:D,3,FALSE) -> 45063 | L15: =VLOOKUP(B15,'Detailed Update'!B:I,4,FALSE) -> 1 | M15: =VLOOKUP(B15,'Detailed Update'!B:I,5,FALSE) -> 0.9918 | N15: =M15-L15 -> -0.0082 | O15: =VLOOKUP(B15,'Detailed Update'!B:I,6,FALSE) -> SEC | P15: =VLOOKUP(B15,'Detailed Update'!B:I,8,FALSE) -> Riyadh | Q15: Approved | R15: =VLOOKUP(B15,'Detailed Update'!B:T,11,FALSE) -> 45732 | S15: =VLOOKUP(B15,'Detailed Update'!B:T,12,FALSE) -> 45838 | T15: =VLOOKUP(B15,'Detailed Update'!B:T,13,FALSE) -> 46202 | U15: =VLOOKUP(B15,'Detailed Update'!B:T,17,FALSE) -> 45885 | V15: =VLOOKUP(B15,'Detailed Update'!B:S,18,FALSE) -> 45991 | W15: =VLOOKUP(B15,'Detailed Update'!B:T,19,FALSE) -> 46355 | X15: =VLOOKUP(B15,'Detailed Update'!B:U,20,FALSE) -> 1.Total of four circuits are planned; two are scheduled for energization by June 2026. 2.SE confirmation is still pending for the remaining two circuits.
A16: 13 | B16: PE-271 | C16: =VLOOKUP(B16,'Detailed Update'!B:C,2,FALSE) -> AL-DAR AL-BAIDHA 132/13.8KV SUB | D16: =VLOOKUP(B16,'Updated Progress % + TCC'!B:D,3,FALSE) -> Hassan Ayloti | E16: =VLOOKUP(B16,'Updated Progress % + TCC'!B:J,9,FALSE) -> Central | F16: =IF(M16>70.01%,"No","Yes") -> No | G16: No | H16: No | I16: No | K16: =VLOOKUP(B16,'Detailed Update'!B:D,3,FALSE) -> 45120 | L16: =VLOOKUP(B16,'Detailed Update'!B:I,4,FALSE) -> 1 | M16: =VLOOKUP(B16,'Detailed Update'!B:I,5,FALSE) -> 0.985 | N16: =M16-L16 -> -0.015 | O16: =VLOOKUP(B16,'Detailed Update'!B:I,6,FALSE) -> SEC | P16: =VLOOKUP(B16,'Detailed Update'!B:I,8,FALSE) -> Riyadh | Q16: Approved | R16: =VLOOKUP(B16,'Detailed Update'!B:T,11,FALSE) -> 45608 | S16: =VLOOKUP(B16,'Detailed Update'!B:T,12,FALSE) -> 46081 | T16: =VLOOKUP(B16,'Detailed Update'!B:T,13,FALSE) -> 46098 | U16: =VLOOKUP(B16,'Detailed Update'!B:T,17,FALSE) -> 45759 | V16: =VLOOKUP(B16,'Detailed Update'!B:S,18,FALSE) -> 46231 | W16: =VLOOKUP(B16,'Detailed Update'!B:T,19,FALSE) -> 46416 | X16: =VLOOKUP(B16,'Detailed Update'!B:U,20,FALSE) -> Energized on 17-Mar-26 | Other Circuit depends on Outage | Expected - 31-Oct-26
A17: 14 | B17: PE-272 | C17: =VLOOKUP(B17,'Detailed Update'!B:C,2,FALSE) -> AL-MUNSIYAH 132/13.8KV SUB # 8273 | D17: =VLOOKUP(B17,'Updated Progress % + TCC'!B:D,3,FALSE) -> Mohamed El hag | E17: =VLOOKUP(B17,'Updated Progress % + TCC'!B:J,9,FALSE) -> Central | F17: =IF(M17>70.01%,"No","Yes") -> No | G17: No | H17: No | I17: No | K17: =VLOOKUP(B17,'Detailed Update'!B:D,3,FALSE) -> 45120 | L17: =VLOOKUP(B17,'Detailed Update'!B:I,4,FALSE) -> 1 | M17: =VLOOKUP(B17,'Detailed Update'!B:I,5,FALSE) -> 0.9613 | N17: =M17-L17 -> -0.0387 | O17: =VLOOKUP(B17,'Detailed Update'!B:I,6,FALSE) -> SEC | P17: =VLOOKUP(B17,'Detailed Update'!B:I,8,FALSE) -> Riyadh | Q17: Under Approval | R17: =VLOOKUP(B17,'Detailed Update'!B:T,11,FALSE) -> 45609 | S17: =VLOOKUP(B17,'Detailed Update'!B:T,12,FALSE) -> 45609 | T17: =VLOOKUP(B17,'Detailed Update'!B:T,13,FALSE) -> 46272 | U17: =VLOOKUP(B17,'Detailed Update'!B:T,17,FALSE) -> 45760 | V17: =VLOOKUP(B17,'Detailed Update'!B:S,18,FALSE) -> 45760 | W17: =VLOOKUP(B17,'Detailed Update'!B:T,19,FALSE) -> 46423 | X17: =VLOOKUP(B17,'Detailed Update'!B:U,20,FALSE) -> One Circuit Energized. Other Circuit depends on Outage | Expected - 31-Oct-26
A18: 15 | B18: PE-273 | C18: =VLOOKUP(B18,'Detailed Update'!B:C,2,FALSE) -> ALMANFOHA 132/13.8KV SUB # 8138 | D18: =VLOOKUP(B18,'Updated Progress % + TCC'!B:D,3,FALSE) -> Mohamed El hag | E18: =VLOOKUP(B18,'Updated Progress % + TCC'!B:J,9,FALSE) -> Central | F18: =IF(M18>70.01%,"No","Yes") -> No | G18: No | H18: No | I18: No | K18: =VLOOKUP(B18,'Detailed Update'!B:D,3,FALSE) -> 45119 | L18: =VLOOKUP(B18,'Detailed Update'!B:I,4,FALSE) -> 1 | M18: =VLOOKUP(B18,'Detailed Update'!B:I,5,FALSE) -> 0.986 | N18: =M18-L18 -> -0.014 | O18: =VLOOKUP(B18,'Detailed Update'!B:I,6,FALSE) -> SEC | P18: =VLOOKUP(B18,'Detailed Update'!B:I,8,FALSE) -> Riyadh | Q18: Under Approval | R18: =VLOOKUP(B18,'Detailed Update'!B:T,11,FALSE) -> 45608 | S18: =VLOOKUP(B18,'Detailed Update'!B:T,12,FALSE) -> 45991 | T18: =VLOOKUP(B18,'Detailed Update'!B:T,13,FALSE) -> 45991 | U18: =VLOOKUP(B18,'Detailed Update'!B:T,17,FALSE) -> 45759 | V18: =VLOOKUP(B18,'Detailed Update'!B:S,18,FALSE) -> 46142 | W18: =VLOOKUP(B18,'Detailed Update'!B:T,19,FALSE) -> 46415 | X18: =VLOOKUP(B18,'Detailed Update'!B:U,20,FALSE) -> One Circuit Energized on 21-Dec-25
A19: 16 | B19: PE-274 | C19: =VLOOKUP(B19,'Detailed Update'!B:C,2,FALSE) -> NASIRIYAH 132/13.8KV SUB # 8154 | D19: =VLOOKUP(B19,'Updated Progress % + TCC'!B:D,3,FALSE) -> Omar Samman | E19: =VLOOKUP(B19,'Updated Progress % + TCC'!B:J,9,FALSE) -> Central | F19: =IF(M19>70.01%,"No","Yes") -> No | G19: No | H19: No | I19: No | K19: =VLOOKUP(B19,'Detailed Update'!B:D,3,FALSE) -> 45119 | L19: =VLOOKUP(B19,'Detailed Update'!B:I,4,FALSE) -> 1 | M19: =VLOOKUP(B19,'Detailed Update'!B:I,5,FALSE) -> 0.927 | N19: =M19-L19 -> -0.073 | O19: =VLOOKUP(B19,'Detailed Update'!B:I,6,FALSE) -> SEC | P19: =VLOOKUP(B19,'Detailed Update'!B:I,8,FALSE) -> Riyadh | Q19: Approved | R19: =VLOOKUP(B19,'Detailed Update'!B:T,11,FALSE) -> 45608 | S19: =VLOOKUP(B19,'Detailed Update'!B:T,12,FALSE) -> 46034 | T19: =VLOOKUP(B19,'Detailed Update'!B:T,13,FALSE) -> 46022 | U19: =VLOOKUP(B19,'Detailed Update'!B:T,17,FALSE) -> 45759 | V19: =VLOOKUP(B19,'Detailed Update'!B:S,18,FALSE) -> 46185 | W19: =VLOOKUP(B19,'Detailed Update'!B:T,19,FALSE) -> 46295 | X19: =VLOOKUP(B19,'Detailed Update'!B:U,20,FALSE) -> One Energized on 11-Feb-26. TCC received with dated 31-Dec-2025
A20: 17 | B20: PE-275 | C20: =VLOOKUP(B20,'Detailed Update'!B:C,2,FALSE) -> 380kV Diriyah Gate-2 BSP # 9080 | D20: =VLOOKUP(B20,'Updated Progress % + TCC'!B:D,3,FALSE) -> Amin El Sayed | E20: =VLOOKUP(B20,'Updated Progress % + TCC'!B:J,9,FALSE) -> Central | F20: =IF(M20>70.01%,"No","Yes") -> Yes | I20: yes | K20: =VLOOKUP(B20,'Detailed Update'!B:D,3,FALSE) -> 45246 | L20: =VLOOKUP(B20,'Detailed Update'!B:I,4,FALSE) -> 0.5084 | M20: =VLOOKUP(B20,'Detailed Update'!B:I,5,FALSE) -> 0.4512 | N20: =M20-L20 -> -0.0572 | O20: =VLOOKUP(B20,'Detailed Update'!B:I,6,FALSE) -> SEC | P20: =VLOOKUP(B20,'Detailed Update'!B:I,8,FALSE) -> Riyadh | Q20: Under Approval | R20: =VLOOKUP(B20,'Detailed Update'!B:T,11,FALSE) -> 45977 | S20: =VLOOKUP(B20,'Detailed Update'!B:T,12,FALSE) -> 46490 | T20: =VLOOKUP(B20,'Detailed Update'!B:T,13,FALSE) -> 46547 | U20: =VLOOKUP(B20,'Detailed Update'!B:T,17,FALSE) -> 46128 | V20: =VLOOKUP(B20,'Detailed Update'!B:S,18,FALSE) -> 46641 | W20: =VLOOKUP(B20,'Detailed Update'!B:T,19,FALSE) -> 46698 | X20: =VLOOKUP(B20,'Detailed Update'!B:U,20,FALSE) -> Progress based on Internal Baseline. 1-Delay in approval of water proofing VO & removal of loose material, which affects the construction works. 2- Negative Cash flow. 3-Claim Approval 201 Mn for prolongation & inflation costs. 4- Delivery for disconnector switch expected to be delayed.
A21: 18 | B21: PE-276 | C21: =VLOOKUP(B21,'Detailed Update'!B:C,2,FALSE) -> SHARAFIYAH 380 KV SS | D21: =VLOOKUP(B21,'Updated Progress % + TCC'!B:D,3,FALSE) -> Mohamed Sabri | E21: =VLOOKUP(B21,'Updated Progress % + TCC'!B:J,9,FALSE) -> Central | F21: =IF(M21>70.01%,"No","Yes") -> No | G21: No | H21: No | I21: No | K21: =VLOOKUP(B21,'Detailed Update'!B:D,3,FALSE) -> 45139 | L21: =VLOOKUP(B21,'Detailed Update'!B:I,4,FALSE) -> 1 | M21: =VLOOKUP(B21,'Detailed Update'!B:I,5,FALSE) -> 0.9378 | N21: =M21-L21 -> -0.0622 | O21: =VLOOKUP(B21,'Detailed Update'!B:I,6,FALSE) -> SEC | P21: =VLOOKUP(B21,'Detailed Update'!B:I,8,FALSE) -> Riyadh | Q21: Under Approval | R21: =VLOOKUP(B21,'Detailed Update'!B:T,11,FALSE) -> 45689 | S21: =VLOOKUP(B21,'Detailed Update'!B:T,12,FALSE) -> 45689 | T21: =VLOOKUP(B21,'Detailed Update'!B:T,13,FALSE) -> 46183 | U21: =VLOOKUP(B21,'Detailed Update'!B:T,17,FALSE) -> 45839 | V21: =VLOOKUP(B21,'Detailed Update'!B:S,18,FALSE) -> 45839 | W21: =VLOOKUP(B21,'Detailed Update'!B:T,19,FALSE) -> 46333 | X21: =VLOOKUP(B21,'Detailed Update'!B:U,20,FALSE) -> Partially Energized. 1.Taihan - Oil Joints 2.Design Approval - 6 Remote end ( 132 kV) 3.Gantry Foundation for Existing Substation 4.Unclear Shutdown schedule for Power and Communication link with all remote ends 5. Delay in Micro Trenching of FOC 25km
A22: 19 | B22: PE-279 | C22: =VLOOKUP(B22,'Detailed Update'!B:C,2,FALSE) -> AL-NAZEEM 132/13.8KV SS # 8271 | D22: =VLOOKUP(B22,'Updated Progress % + TCC'!B:D,3,FALSE) -> Nedal Alkhatib | E22: =VLOOKUP(B22,'Updated Progress % + TCC'!B:J,9,FALSE) -> Central | F22: =IF(M22>70.01%,"No","Yes") -> No | G22: No | H22: No | I22: No | K22: =VLOOKUP(B22,'Detailed Update'!B:D,3,FALSE) -> 45131 | L22: =VLOOKUP(B22,'Detailed Update'!B:I,4,FALSE) -> 1 | M22: =VLOOKUP(B22,'Detailed Update'!B:I,5,FALSE) -> 0.9085 | N22: =M22-L22 -> -0.0915 | O22: =VLOOKUP(B22,'Detailed Update'!B:I,6,FALSE) -> SEC | P22: =VLOOKUP(B22,'Detailed Update'!B:I,8,FALSE) -> Riyadh | Q22: Approved | R22: =VLOOKUP(B22,'Detailed Update'!B:T,11,FALSE) -> 45619 | S22: =VLOOKUP(B22,'Detailed Update'!B:T,12,FALSE) -> 45831 | T22: =VLOOKUP(B22,'Detailed Update'!B:T,13,FALSE) -> 46387 | U22: =VLOOKUP(B22,'Detailed Update'!B:T,17,FALSE) -> 45770 | V22: =VLOOKUP(B22,'Detailed Update'!B:S,18,FALSE) -> 45984 | W22: =VLOOKUP(B22,'Detailed Update'!B:T,19,FALSE) -> 46540 | X22: =VLOOKUP(B22,'Detailed Update'!B:U,20,FALSE) -> Commissioing on Hold due to non-readiness of UG Contractor
A23: 20 | B23: PE-299 | C23: =VLOOKUP(B23,'Detailed Update'!B:C,2,FALSE) -> Reinf of 132KV Network of Baqaa | D23: =VLOOKUP(B23,'Updated Progress % + TCC'!B:D,3,FALSE) -> Yousef AlMohtaseb | E23: =VLOOKUP(B23,'Updated Progress % + TCC'!B:J,9,FALSE) -> Central | F23: =IF(M23>70.01%,"No","Yes") -> No | G23: No | H23: No | I23: No | K23: =VLOOKUP(B23,'Detailed Update'!B:D,3,FALSE) -> 45238 | L23: =VLOOKUP(B23,'Detailed Update'!B:I,4,FALSE) -> 0.9992 | M23: =VLOOKUP(B23,'Detailed Update'!B:I,5,FALSE) -> 0.9358 | N23: =M23-L23 -> -0.0634 | O23: =VLOOKUP(B23,'Detailed Update'!B:I,6,FALSE) -> SEC | P23: =VLOOKUP(B23,'Detailed Update'!B:I,8,FALSE) -> Riyadh | Q23: Approved | R23: =VLOOKUP(B23,'Detailed Update'!B:T,11,FALSE) -> 45784 | S23: =VLOOKUP(B23,'Detailed Update'!B:T,12,FALSE) -> 45981 | T23: =VLOOKUP(B23,'Detailed Update'!B:T,13,FALSE) -> 46326 | U23: =VLOOKUP(B23,'Detailed Update'!B:T,17,FALSE) -> 45937 | V23: =VLOOKUP(B23,'Detailed Update'!B:S,18,FALSE) -> 46132 | W23: =VLOOKUP(B23,'Detailed Update'!B:T,19,FALSE) -> 46477 | X23: =VLOOKUP(B23,'Detailed Update'!B:U,20,FALSE) -> 1.OHTL S/C & D/C crossing - Delay in HOT permits 2.Cutting point outage at TEE OFF location. 3.ERS System & TEE- OFF Tower Installation 4.Design Approval of Flood Protection
A24: 21 | B24: PE-300 | C24: =VLOOKUP(B24,'Detailed Update'!B:C,2,FALSE) -> 300 MVAR STATCOM | D24: =VLOOKUP(B24,'Updated Progress % + TCC'!B:D,3,FALSE) -> Ibrahim Jaradat | E24: =VLOOKUP(B24,'Updated Progress % + TCC'!B:J,9,FALSE) -> Central | F24: =IF(M24>70.01%,"No","Yes") -> Yes | G24: no | K24: =VLOOKUP(B24,'Detailed Update'!B:D,3,FALSE) -> 45357 | L24: =VLOOKUP(B24,'Detailed Update'!B:I,4,FALSE) -> 0.7928 | M24: =VLOOKUP(B24,'Detailed Update'!B:I,5,FALSE) -> 0.6916 | N24: =M24-L24 -> -0.1012 | O24: =VLOOKUP(B24,'Detailed Update'!B:I,6,FALSE) -> SEC | P24: =VLOOKUP(B24,'Detailed Update'!B:I,8,FALSE) -> Riyadh | Q24: Under Approval | R24: =VLOOKUP(B24,'Detailed Update'!B:T,11,FALSE) -> 46087 | S24: =VLOOKUP(B24,'Detailed Update'!B:T,12,FALSE) -> 46271 | T24: =VLOOKUP(B24,'Detailed Update'!B:T,13,FALSE) -> 46315 | U24: =VLOOKUP(B24,'Detailed Update'!B:T,17,FALSE) -> 46240 | V24: =VLOOKUP(B24,'Detailed Update'!B:S,18,FALSE) -> 46059 | W24: =VLOOKUP(B24,'Detailed Update'!B:T,19,FALSE) -> 46103 | X24: =VLOOKUP(B24,'Detailed Update'!B:U,20,FALSE) -> 1.Delay in delivery of AES scope material. (delay in these materials ,impact the project completion ) 2.Delay in 380 kv insulator (Lapp) 3.New fire pump-Delivery (change order), 4.Delay in delivery of MV grounding transformer
A25: 22 | B25: PE-306 | C25: =VLOOKUP(B25,'Detailed Update'!B:C,2,FALSE) -> NEW AL-ARED 380/132KV BSP | D25: =VLOOKUP(B25,'Updated Progress % + TCC'!B:D,3,FALSE) -> Munther Elkhatib | E25: =VLOOKUP(B25,'Updated Progress % + TCC'!B:J,9,FALSE) -> Central | F25: =IF(M25>70.01%,"No","Yes") -> No | G25: No | H25: No | I25: No | K25: =VLOOKUP(B25,'Detailed Update'!B:D,3,FALSE) -> 45218 | L25: =VLOOKUP(B25,'Detailed Update'!B:I,4,FALSE) -> 1 | M25: =VLOOKUP(B25,'Detailed Update'!B:I,5,FALSE) -> 0.9468 | N25: =M25-L25 -> -0.0532 | O25: =VLOOKUP(B25,'Detailed Update'!B:I,6,FALSE) -> SEC | P25: =VLOOKUP(B25,'Detailed Update'!B:I,8,FALSE) -> Riyadh | Q25: Under Approval | R25: =VLOOKUP(B25,'Detailed Update'!B:T,11,FALSE) -> 45766 | S25: =VLOOKUP(B25,'Detailed Update'!B:T,12,FALSE) -> 45888 | T25: =VLOOKUP(B25,'Detailed Update'!B:T,13,FALSE) -> 46203 | U25: =VLOOKUP(B25,'Detailed Update'!B:T,17,FALSE) -> 45919 | V25: =VLOOKUP(B25,'Detailed Update'!B:S,18,FALSE) -> 46041 | W25: =VLOOKUP(B25,'Detailed Update'!B:T,19,FALSE) -> 46356 | X25: =VLOOKUP(B25,'Detailed Update'!B:U,20,FALSE) -> 1.Slow Punch list - Transformers ,GIS, AES 2.Delay in SEC UG Cable Vendor - New Line( Circuits 3 )
A26: 23 | B26: PE-309 | C26: =VLOOKUP(B26,'Detailed Update'!B:C,2,FALSE) -> Reliablity Enh.for SS of 9011 in Sudair | D26: =VLOOKUP(B26,'Updated Progress % + TCC'!B:D,3,FALSE) -> Mohsin Arshad | E26: =VLOOKUP(B26,'Updated Progress % + TCC'!B:J,9,FALSE) -> Central | F26: =IF(M26>70.01%,"No","Yes") -> Yes | G26: =IF(N26>70.01%,"No","Yes") -> Yes | K26: =VLOOKUP(B26,'Detailed Update'!B:D,3,FALSE) -> 46015 | L26: =VLOOKUP(B26,'Detailed Update'!B:I,4,FALSE) -> 0.4504 | M26: =VLOOKUP(B26,'Detailed Update'!B:I,5,FALSE) -> 0.2189 | N26: =M26-L26 -> -0.2315 | O26: =VLOOKUP(B26,'Detailed Update'!B:I,6,FALSE) -> SEC | P26: =VLOOKUP(B26,'Detailed Update'!B:I,8,FALSE) -> Riyadh | Q26: N/A | R26: =VLOOKUP(B26,'Detailed Update'!B:T,11,FALSE) -> 46349 | S26: =VLOOKUP(B26,'Detailed Update'!B:T,12,FALSE) -> 46349 | T26: =VLOOKUP(B26,'Detailed Update'!B:T,13,FALSE) -> 46498 | U26: =VLOOKUP(B26,'Detailed Update'!B:T,17,FALSE) -> 46500 | V26: =VLOOKUP(B26,'Detailed Update'!B:S,18,FALSE) -> 46500 | W26: =VLOOKUP(B26,'Detailed Update'!B:T,19,FALSE) -> 46649 | X26: =VLOOKUP(B26,'Detailed Update'!B:U,20,FALSE) -> Current issues 1.Delay in Plan & Profile - OHTL 2.Delay in Plan & Profile - UG Cable ( T- off Tower Location) 3.Delay in SE supply GIS Bays 4.Delay in Material :- Tower, Hardware, Insulator 5. Delay in providing existing Design : Remote End, U/G 8500 to 8521, Basement & Sleeves Details, Telecom Room, Control Room Layouts 6.Delay in Mobilization of Project Team OHTL Site Engr & Project Engr, QA & QC Civil & Electrical 7. Unclear Shutdown for Project
A27: 24 | B27: PE-310 | C27: =VLOOKUP(B27,'Detailed Update'!B:C,2,FALSE) -> Al Shifa Housing 132/13.8KV SS | D27: =VLOOKUP(B27,'Updated Progress % + TCC'!B:D,3,FALSE) -> Meshari Alqarni | E27: =VLOOKUP(B27,'Updated Progress % + TCC'!B:J,9,FALSE) -> Central | F27: =IF(M27>70.01%,"No","Yes") -> No | G27: No | H27: No | I27: No | K27: =VLOOKUP(B27,'Detailed Update'!B:D,3,FALSE) -> 45313 | L27: =VLOOKUP(B27,'Detailed Update'!B:I,4,FALSE) -> 0.946 | M27: =VLOOKUP(B27,'Detailed Update'!B:I,5,FALSE) -> 0.8692 | N27: =M27-L27 -> -0.0768 | O27: =VLOOKUP(B27,'Detailed Update'!B:I,6,FALSE) -> SEC | P27: =VLOOKUP(B27,'Detailed Update'!B:I,8,FALSE) -> Riyadh | Q27: Under Approval | R27: =VLOOKUP(B27,'Detailed Update'!B:T,11,FALSE) -> 45983 | S27: =VLOOKUP(B27,'Detailed Update'!B:T,12,FALSE) -> 46194 | T27: =VLOOKUP(B27,'Detailed Update'!B:T,13,FALSE) -> 46251 | U27: =VLOOKUP(B27,'Detailed Update'!B:T,17,FALSE) -> 46133 | V27: =VLOOKUP(B27,'Detailed Update'!B:S,18,FALSE) -> 46347 | W27: =VLOOKUP(B27,'Detailed Update'!B:T,19,FALSE) -> 46404 | X27: =VLOOKUP(B27,'Detailed Update'!B:U,20,FALSE) -> 1.Incomplete HV underground cable works under another contractor’s scope are impacting the substation energization activities. 2.STATCOM PQS approval remains pending with SEC/vendor, affecting material delivery and subsequent installation. 3.Delay in remote end (8131) works due to pending C1 work permit
A28: 25 | B28: PE-326 | C28: =VLOOKUP(B28,'Detailed Update'!B:C,2,FALSE) -> Shaqra Wind 380/132kV SS | D28: =VLOOKUP(B28,'Updated Progress % + TCC'!B:D,3,FALSE) -> Ahmed Mosaad Abdel Nabi Hussein | E28: =VLOOKUP(B28,'Updated Progress % + TCC'!B:J,9,FALSE) -> Central | F28: =IF(M28>70.01%,"No","Yes") -> Yes | G28: no | K28: =VLOOKUP(B28,'Detailed Update'!B:D,3,FALSE) -> 45589 | L28: =VLOOKUP(B28,'Detailed Update'!B:I,4,FALSE) -> 0.9675 | M28: =VLOOKUP(B28,'Detailed Update'!B:I,5,FALSE) -> 0.6877 | N28: =M28-L28 -> -0.2798 | O28: =VLOOKUP(B28,'Detailed Update'!B:I,6,FALSE) -> SEC | P28: =VLOOKUP(B28,'Detailed Update'!B:I,8,FALSE) -> Riyadh | Q28: N/A | R28: =VLOOKUP(B28,'Detailed Update'!B:T,11,FALSE) -> 46165 | S28: =VLOOKUP(B28,'Detailed Update'!B:T,12,FALSE) -> 46165 | T28: =VLOOKUP(B28,'Detailed Update'!B:T,13,FALSE) -> 46387 | U28: =VLOOKUP(B28,'Detailed Update'!B:T,17,FALSE) -> 46318 | V28: =VLOOKUP(B28,'Detailed Update'!B:S,18,FALSE) -> 46318 | W28: =VLOOKUP(B28,'Detailed Update'!B:T,19,FALSE) -> 46540 | X28: =VLOOKUP(B28,'Detailed Update'!B:U,20,FALSE) -> 1-Delay in the delivery of 132kV and 380kV GIB and Hybrid GIS (SEC Direct purchase) beyond the scheduled dates, where the original plan was December 2025; however, only the 132kV GIB was delivered in end of May 2026, while the 380kV GIB and Hybrid GIS are still pending. 2-Delay in the supply of AC and DC panels from AES up to date. 3- Delay in obtaining ITP approvals for DSM and TFR systems AES prequalification to perform the FAT in AES factory. 4-Change order confirmation for the additional scope , which holding following activities (Civil work for Search facilities - Guard house - security building and along with all septic tank and water connections , HCIS stage 3 finalization and approval , Procurement of all electrical , mechanical , security material related to this pending . 5-Delay in the approval of firefighting system designs due to changing multiple changes in the review process from SEC and adding new comments with each revision. 6- After approval of lightening panels design (MS Hawaa ) SEC insist to change the manufactural to new alternate as (MS hawaa )is currently suspended in the system 7- Confirmation of EOT which submitted 9-Apr-26.
A29: 26 | B29: PE-335 | C29: =VLOOKUP(B29,'Detailed Update'!B:C,2,FALSE) -> Battery Energy (BESS) - Qaisumah | D29: =VLOOKUP(B29,'Updated Progress % + TCC'!B:D,3,FALSE) -> Tariq Mahmoud Ali Alsheyab | E29: =VLOOKUP(B29,'Updated Progress % + TCC'!B:J,9,FALSE) -> Central | F29: =IF(M29>70.01%,"No","Yes") -> No | G29: No | H29: No | I29: No | K29: =VLOOKUP(B29,'Detailed Update'!B:D,3,FALSE) -> 45642 | L29: =VLOOKUP(B29,'Detailed Update'!B:I,4,FALSE) -> 1 | M29: =VLOOKUP(B29,'Detailed Update'!B:I,5,FALSE) -> 0.9563 | N29: =M29-L29 -> -0.0437 | O29: =VLOOKUP(B29,'Detailed Update'!B:I,6,FALSE) -> SEC | P29: =VLOOKUP(B29,'Detailed Update'!B:I,8,FALSE) -> Riyadh | Q29: N/A | R29: =VLOOKUP(B29,'Detailed Update'!B:T,11,FALSE) -> 46158 | S29: =VLOOKUP(B29,'Detailed Update'!B:T,12,FALSE) -> 46158 | T29: =VLOOKUP(B29,'Detailed Update'!B:T,13,FALSE) -> 46153 | U29: =VLOOKUP(B29,'Detailed Update'!B:T,17,FALSE) -> 46311 | V29: =VLOOKUP(B29,'Detailed Update'!B:S,18,FALSE) -> 46311 | W29: =VLOOKUP(B29,'Detailed Update'!B:T,19,FALSE) -> 46306 | X29: =VLOOKUP(B29,'Detailed Update'!B:U,20,FALSE) -> Energized.
A30: 27 | B30: PE-336 | C30: =VLOOKUP(B30,'Detailed Update'!B:C,2,FALSE) -> Battery Energy (BESS) - Dawadmi | D30: =VLOOKUP(B30,'Updated Progress % + TCC'!B:D,3,FALSE) -> Mohamed Ahmed Abdellatif Abdelkader | E30: =VLOOKUP(B30,'Updated Progress % + TCC'!B:J,9,FALSE) -> Central | F30: =IF(M30>70.01%,"No","Yes") -> No | G30: No | H30: No | I30: No | K30: =VLOOKUP(B30,'Detailed Update'!B:D,3,FALSE) -> 45642 | L30: =VLOOKUP(B30,'Detailed Update'!B:I,4,FALSE) -> 1 | M30: =VLOOKUP(B30,'Detailed Update'!B:I,5,FALSE) -> 0.9766 | N30: =M30-L30 -> -0.0234 | O30: =VLOOKUP(B30,'Detailed Update'!B:I,6,FALSE) -> SEC | P30: =VLOOKUP(B30,'Detailed Update'!B:I,8,FALSE) -> Riyadh | Q30: N/A | R30: =VLOOKUP(B30,'Detailed Update'!B:T,11,FALSE) -> 46158 | S30: =VLOOKUP(B30,'Detailed Update'!B:T,12,FALSE) -> 46158 | T30: =VLOOKUP(B30,'Detailed Update'!B:T,13,FALSE) -> 46152 | U30: =VLOOKUP(B30,'Detailed Update'!B:T,17,FALSE) -> 46311 | V30: =VLOOKUP(B30,'Detailed Update'!B:S,18,FALSE) -> 46311 | W30: =VLOOKUP(B30,'Detailed Update'!B:T,19,FALSE) -> 46305 | X30: =VLOOKUP(B30,'Detailed Update'!B:U,20,FALSE) -> Energized.
A31: 28 | B31: PE-337 | C31: =VLOOKUP(B31,'Detailed Update'!B:C,2,FALSE) -> Battery Energy (BESS) - Airport | D31: =VLOOKUP(B31,'Updated Progress % + TCC'!B:D,3,FALSE) -> Tarig Mohammed | E31: =VLOOKUP(B31,'Updated Progress % + TCC'!B:J,9,FALSE) -> Central | F31: =IF(M31>70.01%,"No","Yes") -> No | G31: No | H31: No | I31: No | K31: =VLOOKUP(B31,'Detailed Update'!B:D,3,FALSE) -> 45642 | L31: =VLOOKUP(B31,'Detailed Update'!B:I,4,FALSE) -> 1 | M31: =VLOOKUP(B31,'Detailed Update'!B:I,5,FALSE) -> 0.9883 | N31: =M31-L31 -> -0.0117 | O31: =VLOOKUP(B31,'Detailed Update'!B:I,6,FALSE) -> SEC | P31: =VLOOKUP(B31,'Detailed Update'!B:I,8,FALSE) -> Riyadh | Q31: N/A | R31: =VLOOKUP(B31,'Detailed Update'!B:T,11,FALSE) -> 46158 | S31: =VLOOKUP(B31,'Detailed Update'!B:T,12,FALSE) -> 46158 | T31: =VLOOKUP(B31,'Detailed Update'!B:T,13,FALSE) -> 46148 | U31: =VLOOKUP(B31,'Detailed Update'!B:T,17,FALSE) -> 46311 | V31: =VLOOKUP(B31,'Detailed Update'!B:S,18,FALSE) -> 46311 | W31: =VLOOKUP(B31,'Detailed Update'!B:T,19,FALSE) -> 46301 | X31: =VLOOKUP(B31,'Detailed Update'!B:U,20,FALSE) -> Energized.
A32: 29 | B32: PE-339 | C32: =VLOOKUP(B32,'Detailed Update'!B:C,2,FALSE) -> Battery Energy (BESS) - Jouf | D32: =VLOOKUP(B32,'Updated Progress % + TCC'!B:D,3,FALSE) -> Khalid Mohamed Aql | E32: =VLOOKUP(B32,'Updated Progress % + TCC'!B:J,9,FALSE) -> Central | F32: =IF(M32>70.01%,"No","Yes") -> No | G32: No | H32: No | I32: No | K32: =VLOOKUP(B32,'Detailed Update'!B:D,3,FALSE) -> 45642 | L32: =VLOOKUP(B32,'Detailed Update'!B:I,4,FALSE) -> 1 | M32: =VLOOKUP(B32,'Detailed Update'!B:I,5,FALSE) -> 0.9862 | N32: =M32-L32 -> -0.0138 | O32: =VLOOKUP(B32,'Detailed Update'!B:I,6,FALSE) -> SEC | P32: =VLOOKUP(B32,'Detailed Update'!B:I,8,FALSE) -> Jouf | Q32: N/A | R32: =VLOOKUP(B32,'Detailed Update'!B:T,11,FALSE) -> 46158 | S32: =VLOOKUP(B32,'Detailed Update'!B:T,12,FALSE) -> 46158 | T32: =VLOOKUP(B32,'Detailed Update'!B:T,13,FALSE) -> 46158 | U32: =VLOOKUP(B32,'Detailed Update'!B:T,17,FALSE) -> 46311 | V32: =VLOOKUP(B32,'Detailed Update'!B:S,18,FALSE) -> 46311 | W32: =VLOOKUP(B32,'Detailed Update'!B:T,19,FALSE) -> 46311 | X32: =VLOOKUP(B32,'Detailed Update'!B:U,20,FALSE) -> Energized.
A33: 30 | B33: PE-348 | C33: =VLOOKUP(B33,'Detailed Update'!B:C,2,FALSE) -> Construction of Hail-2 Substation for BESS | D33: =VLOOKUP(B33,'Updated Progress % + TCC'!B:D,3,FALSE) -> Muhannad Ibrahim Al Heh | E33: =VLOOKUP(B33,'Updated Progress % + TCC'!B:J,9,FALSE) -> Central | F33: =IF(M33>70.01%,"No","Yes") -> Yes | G33: No | K33: =VLOOKUP(B33,'Detailed Update'!B:D,3,FALSE) -> 45841 | L33: =VLOOKUP(B33,'Detailed Update'!B:I,4,FALSE) -> 0.8873 | M33: =VLOOKUP(B33,'Detailed Update'!B:I,5,FALSE) -> 0.4661 | N33: =M33-L33 -> -0.4212 | O33: =VLOOKUP(B33,'Detailed Update'!B:I,6,FALSE) -> SEC | P33: =VLOOKUP(B33,'Detailed Update'!B:I,8,FALSE) -> Hail | Q33: N/A | R33: =VLOOKUP(B33,'Detailed Update'!B:T,11,FALSE) -> 46176 | S33: =VLOOKUP(B33,'Detailed Update'!B:T,12,FALSE) -> 46176 | T33: =VLOOKUP(B33,'Detailed Update'!B:T,13,FALSE) -> 46280 | U33: =VLOOKUP(B33,'Detailed Update'!B:T,17,FALSE) -> 46329 | V33: =VLOOKUP(B33,'Detailed Update'!B:S,18,FALSE) -> 46329 | W33: =VLOOKUP(B33,'Detailed Update'!B:T,19,FALSE) -> 46433 | X33: =VLOOKUP(B33,'Detailed Update'!B:U,20,FALSE) -> 1-Delay in approving critical designs such as FF designs, & Remote end AMI , with some submittals open for more than 3 months 2- Delay in design inputs has delayed grid studies submission & approval cycles 3- Delay in Alfanar equipment delivery: - Auxiliary transformer - AC & DC Panels - TFR & DSM - Remote End AMI & Metering 4- Delay in BESS Supplier fire fighting protion delivery (BESS gas pipes) 5- Delay in Firefighting pumps delivery 6- Delay in surge arrestors, and post insulators delivery 7- Delay in 33Kv SWGR termination kits delivery 8- Delay in HGIS Delivery: 1 out of 2 Bays delivered 9- Delay in UPS delivery
A34: 31 | B34: PE-353 | C34: =VLOOKUP(B34,'Detailed Update'!B:C,2,FALSE) -> Conv of Riyadh CC PP10 - Phase 2 | D34: =VLOOKUP(B34,'Updated Progress % + TCC'!B:D,3,FALSE) -> Muhannad Badawi | E34: =VLOOKUP(B34,'Updated Progress % + TCC'!B:J,9,FALSE) -> Central | F34: =IF(M34>70.01%,"No","Yes") -> Yes | G34: =IF(N34>70.01%,"No","Yes") -> Yes | K34: =VLOOKUP(B34,'Detailed Update'!B:D,3,FALSE) -> 45785 | L34: =VLOOKUP(B34,'Detailed Update'!B:I,4,FALSE) -> 0.4019 | M34: =VLOOKUP(B34,'Detailed Update'!B:I,5,FALSE) -> 0.1642 | N34: =M34-L34 -> -0.2377 | O34: =VLOOKUP(B34,'Detailed Update'!B:I,6,FALSE) -> SEC | P34: =VLOOKUP(B34,'Detailed Update'!B:I,8,FALSE) -> Riyadh | Q34: N/A | R34: =VLOOKUP(B34,'Detailed Update'!B:T,11,FALSE) -> 46515 | S34: =VLOOKUP(B34,'Detailed Update'!B:T,12,FALSE) -> 46515 | T34: =VLOOKUP(B34,'Detailed Update'!B:T,13,FALSE) -> 46765 | U34: =VLOOKUP(B34,'Detailed Update'!B:T,17,FALSE) -> 46912 | V34: =VLOOKUP(B34,'Detailed Update'!B:S,18,FALSE) -> 46912 | W34: =VLOOKUP(B34,'Detailed Update'!B:T,19,FALSE) -> 47162 | X34: =VLOOKUP(B34,'Detailed Update'!B:U,20,FALSE) -> 1.Base Design Approval : Disagreement with SE on interpretation of the Contract. 2.Engineering Review Cycle Delays : Agreed timelines for review are not being adhered. 3.Delivery durations for critical (LLIs) exceed the Contractual timeline, creating a significant risk to meeting the contractual milestones. 4.Accelerated Dec 2026 completion requested by SE for GT 1st Fire. 5.Site Access Gate Permits & Work Permit issues.
A35: 32 | B35: PE-356 | C35: =VLOOKUP(B35,'Detailed Update'!B:C,2,FALSE) -> 380KV OHTL | MAWQAQ BSP CONNECTION | D35: =VLOOKUP(B35,'Updated Progress % + TCC'!B:D,3,FALSE) -> Omar Samman | E35: =VLOOKUP(B35,'Updated Progress % + TCC'!B:J,9,FALSE) -> Central | F35: =IF(M35>70.01%,"No","Yes") -> Yes | G35: no | K35: =VLOOKUP(B35,'Detailed Update'!B:D,3,FALSE) -> 45897 | L35: =VLOOKUP(B35,'Detailed Update'!B:I,4,FALSE) -> 0.5331 | M35: =VLOOKUP(B35,'Detailed Update'!B:I,5,FALSE) -> 0.1606 | N35: =M35-L35 -> -0.3725 | O35: =VLOOKUP(B35,'Detailed Update'!B:I,6,FALSE) -> SEC | P35: =VLOOKUP(B35,'Detailed Update'!B:I,8,FALSE) -> Riyadh | Q35: N/A | R35: =VLOOKUP(B35,'Detailed Update'!B:T,11,FALSE) -> 46446 | S35: =VLOOKUP(B35,'Detailed Update'!B:T,12,FALSE) -> 46446 | T35: =VLOOKUP(B35,'Detailed Update'!B:T,13,FALSE) -> 46723 | U35: =VLOOKUP(B35,'Detailed Update'!B:T,17,FALSE) -> 46595 | V35: =VLOOKUP(B35,'Detailed Update'!B:S,18,FALSE) -> 46595 | W35: =VLOOKUP(B35,'Detailed Update'!B:T,19,FALSE) -> 46873 | X35: =VLOOKUP(B35,'Detailed Update'!B:U,20,FALSE) -> 1) Revised Route with additional change order.Revised Route under approval 2) Finalization of the route is pending for the portion that falls under KSRR. 3) Cost and time impact resulting from the increased transmission line route length and associated scope changes. 4) Delay in approval of plan and profile
A36: 33 | B36: PE-360 | C36: =VLOOKUP(B36,'Detailed Update'!B:C,2,FALSE) -> SMP|OPERATION & PROF. SERVICES (HES&HHU) | D36: =VLOOKUP(B36,'Updated Progress % + TCC'!B:D,3,FALSE) -> Hazem Mahmoud | E36: =VLOOKUP(B36,'Updated Progress % + TCC'!B:J,9,FALSE) -> Central | F36: =IF(M36>70.01%,"No","Yes") -> No | K36: =VLOOKUP(B36,'Detailed Update'!B:D,3,FALSE) -> 45853 | L36: =VLOOKUP(B36,'Detailed Update'!B:I,4,FALSE) -> 0.8333 | M36: =VLOOKUP(B36,'Detailed Update'!B:I,5,FALSE) -> 0.8333 | N36: =M36-L36 -> 0 | O36: =VLOOKUP(B36,'Detailed Update'!B:I,6,FALSE) -> SEC | P36: =VLOOKUP(B36,'Detailed Update'!B:I,8,FALSE) -> Riyadh | Q36: N/A | R36: =VLOOKUP(B36,'Detailed Update'!B:T,11,FALSE) -> 46217 | S36: =VLOOKUP(B36,'Detailed Update'!B:T,12,FALSE) -> 46309 | T36: =VLOOKUP(B36,'Detailed Update'!B:T,13,FALSE) -> 46309 | U36: =VLOOKUP(B36,'Detailed Update'!B:T,17,FALSE) -> 46217 | V36: =VLOOKUP(B36,'Detailed Update'!B:S,18,FALSE) -> 46309 | W36: =VLOOKUP(B36,'Detailed Update'!B:T,19,FALSE) -> 46309 | X36: =VLOOKUP(B36,'Detailed Update'!B:U,20,FALSE) -> Extension of 1 quarter received
A37: 34 | B37: PE-362 | C37: =VLOOKUP(B37,'Detailed Update'!B:C,2,FALSE) -> 132KV SS |CONST. SPORTS BOULEVARD-RIYADH | D37: =VLOOKUP(B37,'Updated Progress % + TCC'!B:D,3,FALSE) -> Mirza Ikramullah | E37: =VLOOKUP(B37,'Updated Progress % + TCC'!B:J,9,FALSE) -> Central | F37: =IF(M37>70.01%,"No","Yes") -> Yes | G37: No | K37: =VLOOKUP(B37,'Detailed Update'!B:D,3,FALSE) -> 45882 | L37: =VLOOKUP(B37,'Detailed Update'!B:I,4,FALSE) -> 0.3324 | M37: =VLOOKUP(B37,'Detailed Update'!B:I,5,FALSE) -> 0.2194 | N37: =M37-L37 -> -0.113 | O37: =VLOOKUP(B37,'Detailed Update'!B:I,6,FALSE) -> SEC | P37: =VLOOKUP(B37,'Detailed Update'!B:I,8,FALSE) -> Riyadh | Q37: N/A | R37: =VLOOKUP(B37,'Detailed Update'!B:T,11,FALSE) -> 46429 | S37: =VLOOKUP(B37,'Detailed Update'!B:T,12,FALSE) -> 46429 | T37: =VLOOKUP(B37,'Detailed Update'!B:T,13,FALSE) -> 46660 | U37: =VLOOKUP(B37,'Detailed Update'!B:T,17,FALSE) -> 46579 | V37: =VLOOKUP(B37,'Detailed Update'!B:S,18,FALSE) -> 46579 | W37: =VLOOKUP(B37,'Detailed Update'!B:T,19,FALSE) -> 46810 | X37: =VLOOKUP(B37,'Detailed Update'!B:U,20,FALSE) -> Delay in Site Handing Over. Not handed over yet
A38: 35 | B38: PE-316 | C38: =VLOOKUP(B38,'Detailed Update'!B:C,2,FALSE) -> HVDC-1 | COA-WOA | RUH-9022 | D38: =VLOOKUP(B38,'Updated Progress % + TCC'!B:D,3,FALSE) -> Mohamed Sabri | E38: =VLOOKUP(B38,'Updated Progress % + TCC'!B:J,9,FALSE) -> Central | F38: =IF(M38>70.01%,"No","Yes") -> Yes | H38: =IF(O38>70.01%,"No","Yes") -> No | I38: =IF(P38>70.01%,"No","Yes") -> No | K38: =VLOOKUP(B38,'Detailed Update'!B:D,3,FALSE) -> 45470 | L38: =VLOOKUP(B38,'Detailed Update'!B:I,4,FALSE) -> 0.7932 | M38: =VLOOKUP(B38,'Detailed Update'!B:I,5,FALSE) -> 0.6971 | N38: =M38-L38 -> -0.0961 | O38: =VLOOKUP(B38,'Detailed Update'!B:I,6,FALSE) -> SEC | P38: =VLOOKUP(B38,'Detailed Update'!B:I,8,FALSE) -> Riyadh | Q38: N/A | R38: =VLOOKUP(B38,'Detailed Update'!B:T,11,FALSE) -> 46387 | S38: =VLOOKUP(B38,'Detailed Update'!B:T,12,FALSE) -> 46387 | T38: =VLOOKUP(B38,'Detailed Update'!B:T,13,FALSE) -> 46418 | U38: =VLOOKUP(B38,'Detailed Update'!B:T,17,FALSE) -> 46538 | V38: =VLOOKUP(B38,'Detailed Update'!B:S,18,FALSE) -> 46538 | W38: =VLOOKUP(B38,'Detailed Update'!B:T,19,FALSE) -> 46569 | X38: =VLOOKUP(B38,'Detailed Update'!B:U,20,FALSE) -> -
A39: 36 | B39: PE-317 | C39: =VLOOKUP(B39,'Detailed Update'!B:C,2,FALSE) -> HVDC-2 | COA-SOA | RUH-9041 | D39: =VLOOKUP(B39,'Updated Progress % + TCC'!B:D,3,FALSE) -> Mohamed Sabri | E39: =VLOOKUP(B39,'Updated Progress % + TCC'!B:J,9,FALSE) -> Central | F39: =IF(M39>70.01%,"No","Yes") -> No | I39: yes | K39: =VLOOKUP(B39,'Detailed Update'!B:D,3,FALSE) -> 45470 | L39: =VLOOKUP(B39,'Detailed Update'!B:I,4,FALSE) -> 0.8948 | M39: =VLOOKUP(B39,'Detailed Update'!B:I,5,FALSE) -> 0.7873 | N39: =M39-L39 -> -0.1075 | O39: =VLOOKUP(B39,'Detailed Update'!B:I,6,FALSE) -> SEC | P39: =VLOOKUP(B39,'Detailed Update'!B:I,8,FALSE) -> Riyadh | Q39: N/A | R39: =VLOOKUP(B39,'Detailed Update'!B:T,11,FALSE) -> 46387 | S39: =VLOOKUP(B39,'Detailed Update'!B:T,12,FALSE) -> 46387 | T39: =VLOOKUP(B39,'Detailed Update'!B:T,13,FALSE) -> 46446 | U39: =VLOOKUP(B39,'Detailed Update'!B:T,17,FALSE) -> 46538 | V39: =VLOOKUP(B39,'Detailed Update'!B:S,18,FALSE) -> 46538 | W39: =VLOOKUP(B39,'Detailed Update'!B:T,19,FALSE) -> 46597 | X39: =VLOOKUP(B39,'Detailed Update'!B:U,20,FALSE) -> -
A40: 37 | B40: PE-363 | C40: =VLOOKUP(B40,'Detailed Update'!B:C,2,FALSE) -> SULYBIAH SS 8823 132/33KV | D40: =VLOOKUP(B40,'Updated Progress % + TCC'!B:D,3,FALSE) -> Youssef Al Mohtaesab | E40: =VLOOKUP(B40,'Updated Progress % + TCC'!B:J,9,FALSE) -> Central | F40: =IF(M40>70.01%,"No","Yes") -> Yes | K40: =VLOOKUP(B40,'Detailed Update'!B:D,3,FALSE) -> 46047 | L40: =VLOOKUP(B40,'Detailed Update'!B:I,4,FALSE) -> 0.0505 | M40: =VLOOKUP(B40,'Detailed Update'!B:I,5,FALSE) -> 0.0342 | N40: =M40-L40 -> -0.0163 | O40: =VLOOKUP(B40,'Detailed Update'!B:I,6,FALSE) -> SEC | P40: =VLOOKUP(B40,'Detailed Update'!B:I,8,FALSE) -> Qassim | Q40: N/A | R40: =VLOOKUP(B40,'Detailed Update'!B:T,11,FALSE) -> 46593 | S40: =VLOOKUP(B40,'Detailed Update'!B:T,12,FALSE) -> 46593 | T40: =VLOOKUP(B40,'Detailed Update'!B:T,13,FALSE) -> 46673 | U40: =VLOOKUP(B40,'Detailed Update'!B:T,17,FALSE) -> 46746 | V40: =VLOOKUP(B40,'Detailed Update'!B:S,18,FALSE) -> 46746 | W40: =VLOOKUP(B40,'Detailed Update'!B:T,19,FALSE) -> 46826 | X40: =VLOOKUP(B40,'Detailed Update'!B:U,20,FALSE) -> 1. Delay in Receiving Design for GIS Package Supplied by SEC Vendor 2. Delay in soil investigation activities due to one corner of the substation located on farmland 3. Terminal compound 1 location changed 4. Repetition of soil investigation activities due to the client's rejection of the proposed vendor
A41: 38 | B41: PE-372 | C41: =VLOOKUP(B41,'Detailed Update'!B:C,2,FALSE) -> AL-DWADMI SS 8618 132/33KV | D41: =VLOOKUP(B41,'Updated Progress % + TCC'!B:D,3,FALSE) -> Mohamed Azhar | E41: =VLOOKUP(B41,'Updated Progress % + TCC'!B:J,9,FALSE) -> Central | F41: =IF(M41>70.01%,"No","Yes") -> Yes | K41: =VLOOKUP(B41,'Detailed Update'!B:D,3,FALSE) -> 46036 | L41: =VLOOKUP(B41,'Detailed Update'!B:I,4,FALSE) -> 0.0858 | M41: =VLOOKUP(B41,'Detailed Update'!B:I,5,FALSE) -> 0.0579 | N41: =M41-L41 -> -0.0279 | O41: =VLOOKUP(B41,'Detailed Update'!B:I,6,FALSE) -> SEC | P41: =VLOOKUP(B41,'Detailed Update'!B:I,8,FALSE) -> Riyadh | Q41: N/A | R41: =VLOOKUP(B41,'Detailed Update'!B:T,11,FALSE) -> 46580 | S41: =VLOOKUP(B41,'Detailed Update'!B:T,12,FALSE) -> 46580 | T41: =VLOOKUP(B41,'Detailed Update'!B:T,13,FALSE) -> 46660 | U41: =VLOOKUP(B41,'Detailed Update'!B:T,17,FALSE) -> 46733 | V41: =VLOOKUP(B41,'Detailed Update'!B:S,18,FALSE) -> 46733 | W41: =VLOOKUP(B41,'Detailed Update'!B:T,19,FALSE) -> 46813 | X41: =VLOOKUP(B41,'Detailed Update'!B:U,20,FALSE) -> 1. Delay in approval of GEL 2. Delay of Receiving Design for GIS Package Supplied by SEC (GIS Delivery delayed ) 3. Delay in municipality approval 4. Delay in Issuance Of P.O Transformer
A42: 39 | B42: PE-394 | C42: =VLOOKUP(B42,'Detailed Update'!B:C,2,FALSE) -> NEW AL-GHADIR SS#8237 132/33K | D42: =VLOOKUP(B42,'Updated Progress % + TCC'!B:D,3,FALSE) -> Rafa Awad Al Hassan | E42: =VLOOKUP(B42,'Updated Progress % + TCC'!B:J,9,FALSE) -> Central | F42: =IF(M42>70.01%,"No","Yes") -> Yes | K42: =VLOOKUP(B42,'Detailed Update'!B:D,3,FALSE) -> 46043 | L42: =VLOOKUP(B42,'Detailed Update'!B:I,4,FALSE) -> 0.0739 | M42: =VLOOKUP(B42,'Detailed Update'!B:I,5,FALSE) -> 0.0563 | N42: =M42-L42 -> -0.0176 | O42: =VLOOKUP(B42,'Detailed Update'!B:I,6,FALSE) -> SEC | P42: =VLOOKUP(B42,'Detailed Update'!B:I,8,FALSE) -> Riyadh | Q42: N/A | R42: =VLOOKUP(B42,'Detailed Update'!B:T,11,FALSE) -> 46651 | S42: =VLOOKUP(B42,'Detailed Update'!B:T,12,FALSE) -> 46651 | T42: =VLOOKUP(B42,'Detailed Update'!B:T,13,FALSE) -> 46681 | U42: =VLOOKUP(B42,'Detailed Update'!B:T,17,FALSE) -> 46804 | V42: =VLOOKUP(B42,'Detailed Update'!B:S,18,FALSE) -> 46804 | W42: =VLOOKUP(B42,'Detailed Update'!B:T,19,FALSE) -> 46834 | X42: =VLOOKUP(B42,'Detailed Update'!B:U,20,FALSE) -> -
A43: 40 | B43: PE-395 | C43: =VLOOKUP(B43,'Detailed Update'!B:C,2,FALSE) -> New Al- Wadi 132/13.8Kv substation #8224 and its Connection in Riyadh City | D43: =VLOOKUP(B43,'Updated Progress % + TCC'!B:D,3,FALSE) -> Osama Mahood | E43: =VLOOKUP(B43,'Updated Progress % + TCC'!B:J,9,FALSE) -> Central | F43: =IF(M43>70.01%,"No","Yes") -> Yes | K43: =VLOOKUP(B43,'Detailed Update'!B:D,3,FALSE) -> 46064 | L43: =VLOOKUP(B43,'Detailed Update'!B:I,4,FALSE) -> 0.0236 | M43: =VLOOKUP(B43,'Detailed Update'!B:I,5,FALSE) -> 0.039 | N43: =M43-L43 -> 0.0154 | O43: =VLOOKUP(B43,'Detailed Update'!B:I,6,FALSE) -> SEC-COA | P43: =VLOOKUP(B43,'Detailed Update'!B:I,8,FALSE) -> Riyadh | Q43: N/A | R43: =VLOOKUP(B43,'Detailed Update'!B:T,11,FALSE) -> 46671 | S43: =VLOOKUP(B43,'Detailed Update'!B:T,12,FALSE) -> 46671 | T43: =VLOOKUP(B43,'Detailed Update'!B:T,13,FALSE) -> 46695 | U43: =VLOOKUP(B43,'Detailed Update'!B:T,17,FALSE) -> 46823 | V43: =VLOOKUP(B43,'Detailed Update'!B:S,18,FALSE) -> 46823 | W43: =VLOOKUP(B43,'Detailed Update'!B:T,19,FALSE) -> 46847 | X43: =VLOOKUP(B43,'Detailed Update'!B:U,20,FALSE) -> 1- Civil construction and related engineering/design activities suspended due to site cavities discovered after Soil investigation report. 2- Under Ground cables radar scanning & cable route layout submission.
C44: EASTERN REGION UNIT (BASIL ALHAKAMI)
A45: Completed Projects | B45: PE111 | C45: CONST. QURAYYAH IPP 380/230KV - Samsung | D45: =VLOOKUP(B45,'Updated Progress % + TCC'!B:D,3,FALSE) -> #N/A | E45: Eastern | F45: =IF(M45>70.01%,"No","Yes") -> No | G45: No | H45: No | L45: 1 | M45: 1 | N45: =M45-L45 -> 0 | O45: SEC | P45: Dammam
B46: PE127 | C46: KDF Substation | D46: =VLOOKUP(B46,'Updated Progress % + TCC'!B:D,3,FALSE) -> #N/A | E46: Eastern | F46: =IF(M46>70.01%,"No","Yes") -> No | G46: No | H46: No | K46: 41462 | L46: 1 | M46: 1 | N46: =M46-L46 -> 0 | O46: SEC | P46: Dammam | Q46: Approved
B47: PE-128 | C47: WEST of 2nd DIE 115/13.8 KV S/S | D47: =VLOOKUP(B47,'Updated Progress % + TCC'!B:D,3,FALSE) -> #N/A | E47: Eastern | F47: =IF(M47>70.01%,"No","Yes") -> No | G47: No | H47: No | K47: 41462 | L47: 1 | M47: 1 | N47: =M47-L47 -> 0 | O47: SEC | P47: Dammam | Q47: Approved
B48: PE-129 | C48: DHAHIYAH 115/13.8 KV S/S | D48: =VLOOKUP(B48,'Updated Progress % + TCC'!B:D,3,FALSE) -> #N/A | E48: Eastern | F48: =IF(M48>70.01%,"No","Yes") -> No | G48: No | H48: No | K48: 41462 | L48: 1 | M48: 1 | N48: =M48-L48 -> 0 | O48: SEC | P48: Dammam | Q48: Approved
B49: PE130 | C49: As-Shayyit Substation | D49: =VLOOKUP(B49,'Updated Progress % + TCC'!B:D,3,FALSE) -> #N/A | E49: Eastern | F49: =IF(M49>70.01%,"No","Yes") -> No | G49: No | H49: No | K49: 41462 | L49: 1 | M49: 1 | N49: =M49-L49 -> 0 | O49: SEC | P49: Dammam | Q49: Approved
B50: PE-140 | C50: CONSTRUCTION OF AL-UQAIR 380/115KV BSP AND EXPANSION OF JAWATHA 230/115KV S/S AND ABQAIQ CENTRAL 230KV S/S | D50: =VLOOKUP(B50,'Updated Progress % + TCC'!B:D,3,FALSE) -> #N/A | E50: Eastern | F50: =IF(M50>70.01%,"No","Yes") -> No | G50: No | H50: No | K50: 41759 | L50: 1 | M50: 1 | N50: =M50-L50 -> 0 | O50: SEC | P50: Dammam | Q50: Approved
B51: PE-141 | C51: Construction of Al-Khafji 380/115/13.8 KV BSP | D51: =VLOOKUP(B51,'Updated Progress % + TCC'!B:D,3,FALSE) -> #N/A | E51: Eastern | F51: =IF(M51>70.01%,"No","Yes") -> No | G51: No | H51: No | K51: 41759 | L51: 1 | M51: 1 | N51: =M51-L51 -> 0 | O51: SEC | P51: Khafji | Q51: Approved
B52: PE159 | C52: CONSTRUCTION OF AL-MAZROEYAH 115/13.8KV SUBSTAION IN AL-HASSA | D52: =VLOOKUP(B52,'Updated Progress % + TCC'!B:D,3,FALSE) -> #N/A | E52: Eastern | F52: =IF(M52>70.01%,"No","Yes") -> No | G52: No | H52: No | K52: 42156 | L52: 1 | M52: 1 | N52: =M52-L52 -> 0 | O52: SEC | P52: Al Hassa | Q52: Approved
B53: PE160 | C53: CONSTRUCTION OF POWER FACTOR CORRECTION (PHASE II) FOR 115/13.8KV S/S IN AL-HASSA | D53: =VLOOKUP(B53,'Updated Progress % + TCC'!B:D,3,FALSE) -> #N/A | E53: Eastern | F53: =IF(M53>70.01%,"No","Yes") -> No | G53: No | H53: No | K53: 42156 | L53: 1 | M53: 1 | N53: =M53-L53 -> 0 | O53: SEC | P53: Al Hassa | Q53: Approved
B54: PE161 | C54: AL -MANSURAH 115/13.8kV S/S TO 115/13.8KV GIS S/S IN AL-HASSA | D54: =VLOOKUP(B54,'Updated Progress % + TCC'!B:D,3,FALSE) -> #N/A | E54: Eastern | F54: =IF(M54>70.01%,"No","Yes") -> No | G54: No | H54: No | K54: 42156 | L54: 1 | M54: 1 | N54: =M54-L54 -> 0 | O54: SEC | P54: Al Hassa | Q54: Approved
B55: PE-166 | C55: Construction of Dammam North 380/115/33 KV BSP | D55: =VLOOKUP(B55,'Updated Progress % + TCC'!B:D,3,FALSE) -> #N/A | E55: Eastern | F55: =IF(M55>70.01%,"No","Yes") -> No | G55: No | H55: No | K55: 42180 | L55: 1 | M55: 1 | N55: =M55-L55 -> 0 | O55: SEC | P55: Dammam | Q55: Approved
B56: PE167 | C56: Construction of Nariyah North 380/115/33kV BSP | D56: =VLOOKUP(B56,'Updated Progress % + TCC'!B:D,3,FALSE) -> #N/A | E56: Eastern | F56: =IF(M56>70.01%,"No","Yes") -> No | G56: No | H56: No | K56: 42263 | L56: 1 | M56: 0.999 | N56: =M56-L56 -> -0.001 | O56: SEC | P56: Nariyah | Q56: Approved
B57: PE-168 | C57: Construction of Dammam Housing-1 115/13.8kV Substation | D57: =VLOOKUP(B57,'Updated Progress % + TCC'!B:D,3,FALSE) -> #N/A | E57: Eastern | F57: =IF(M57>70.01%,"No","Yes") -> No | G57: No | H57: No | K57: 42263 | L57: 1 | M57: 1 | N57: =M57-L57 -> 0 | O57: SEC | P57: Dammam | Q57: Approved
... B64: PE-177 | C64: ADDITION OF MV SWITCH GEAR IN JUBAIL | D64: =VLOOKUP(B64,'Updated Progress % + TCC'!B:D,3,FALSE) -> #N/A | E64: Eastern | F64: =IF(M64>70.01%,"No","Yes") -> No | G64: No | H64: No | K64: 42368 | L64: 1 | M64: 1 | N64: =M64-L64 -> 0 | O64: SEC | P64: Jubail | Q64: Approved
B65: PE-181 | C65: =VLOOKUP(B65,'Detailed Update'!B:C,2,FALSE) -> EPC OF PRIMARY ELECTRICAL SUSBSTATION #3 | D65: =VLOOKUP(B65,'Updated Progress % + TCC'!B:D,3,FALSE) -> Sami Atta | E65: Eastern | F65: =IF(M65>70.01%,"No","Yes") -> No | G65: No | H65: No | L65: 1 | M65: 1 | N65: =M65-L65 -> 0 | O65: SEC | P65: Ras Al Khair | Q65: Approved | R65: =VLOOKUP(B65,'Detailed Update'!B:T,11,FALSE) -> 44560 | S65: =VLOOKUP(B65,'Detailed Update'!B:T,12,FALSE) -> 44560 | T65: =VLOOKUP(B65,'Detailed Update'!B:T,13,FALSE) -> 44552 | U65: =VLOOKUP(B65,'Detailed Update'!B:T,17,FALSE) -> 44560 | V65: =VLOOKUP(B65,'Detailed Update'!B:S,18,FALSE) -> 44560 | W65: =VLOOKUP(B65,'Detailed Update'!B:T,19,FALSE) -> 46022 | X65: =VLOOKUP(B65,'Detailed Update'!B:U,20,FALSE) -> All Certificates Recieved
B66: PE-199 | C66: Construction of SPARK 380/115 KV BSP | D66: =VLOOKUP(B66,'Updated Progress % + TCC'!B:D,3,FALSE) -> Walid Ahmed Khater | E66: Eastern | F66: =IF(M66>70.01%,"No","Yes") -> No | G66: No | H66: No | K66: 43435 | L66: 1 | M66: 0.999 | N66: =M66-L66 -> -0.001 | O66: SEC | P66: Abqaiq | Q66: Approved | R66: =VLOOKUP(B66,'Detailed Update'!B:T,11,FALSE) -> 44104 | S66: =VLOOKUP(B66,'Detailed Update'!B:T,12,FALSE) -> 44104 | T66: =VLOOKUP(B66,'Detailed Update'!B:T,13,FALSE) -> 44316 | U66: =VLOOKUP(B66,'Detailed Update'!B:T,17,FALSE) -> 45838 | V66: =VLOOKUP(B66,'Detailed Update'!B:S,18,FALSE) -> 45838 | W66: =VLOOKUP(B66,'Detailed Update'!B:T,19,FALSE) -> 45808 | X66: =VLOOKUP(B66,'Detailed Update'!B:U,20,FALSE) -> All Certificates Recieved
B67: PE209 | C67: Reinforcement of Fadhili Gas Plant (FGP) and Qaisumah 380kV BSP Interconnection | D67: =VLOOKUP(B67,'Updated Progress % + TCC'!B:D,3,FALSE) -> #N/A | E67: Eastern | F67: =IF(M67>70.01%,"No","Yes") -> No | G67: No | H67: No | K67: 43767 | L67: 1 | M67: 1 | N67: =M67-L67 -> 0 | O67: SEC | P67: Fadhili | Q67: Approved | R67: =VLOOKUP(B67,'Detailed Update'!B:T,11,FALSE) -> #N/A | S67: =VLOOKUP(B67,'Detailed Update'!B:T,12,FALSE) -> #N/A | T67: =VLOOKUP(B67,'Detailed Update'!B:T,13,FALSE) -> #N/A | U67: =VLOOKUP(B67,'Detailed Update'!B:T,17,FALSE) -> #N/A | V67: =VLOOKUP(B67,'Detailed Update'!B:S,18,FALSE) -> #N/A | W67: =VLOOKUP(B67,'Detailed Update'!B:T,19,FALSE) -> #N/A | X67: =VLOOKUP(B67,'Detailed Update'!B:U,20,FALSE) -> #N/A
B68: PE-213 | C68: Construction of Hawiyah Unayzah Gas Reservoir Storage (HUGRS) 380/230 kV BSP and Expansion of Al-Uqair 380kV BSP | D68: =VLOOKUP(B68,'Updated Progress % + TCC'!B:D,3,FALSE) -> Moath Ahmad Mahmoud Almousa | E68: Eastern | F68: =IF(M68>70.01%,"No","Yes") -> No | G68: No | H68: No | K68: 43853 | L68: 1 | M68: 0.999 | N68: =M68-L68 -> -0.001 | O68: SEC | P68: Huwyha | Q68: Approved | R68: =VLOOKUP(B68,'Detailed Update'!B:T,11,FALSE) -> HUW : 30-Jul-22 UQA : 30-Apr-23 | S68: =VLOOKUP(B68,'Detailed Update'!B:T,12,FALSE) -> HUW : 30-Jul-22 UQA : 30-Apr-23 | T68: =VLOOKUP(B68,'Detailed Update'!B:T,13,FALSE) -> HUW : 30-Sep-22 UQA :30-Aug-26 | U68: =VLOOKUP(B68,'Detailed Update'!B:T,17,FALSE) -> HUW :31-Dec-22 UQA : 30-Sep-23 | V68: =VLOOKUP(B68,'Detailed Update'!B:S,18,FALSE) -> HUW :31-Dec-22 UQA : 30-Sep-23 | W68: =VLOOKUP(B68,'Detailed Update'!B:T,19,FALSE) -> HUW :27-May-25 UQA :30-Nov-26 | X68: =VLOOKUP(B68,'Detailed Update'!B:U,20,FALSE) -> P1: All Certificates Recieved P2: No Certificates Recieved
B69: PE220 | C69: INSTALLATION OF REACTOR IN QAISUMAH 380/115KV BSP | D69: =VLOOKUP(B69,'Updated Progress % + TCC'!B:D,3,FALSE) -> #N/A | E69: Eastern | F69: =IF(M69>70.01%,"No","Yes") -> No | G69: No | H69: No | K69: 44155 | L69: 1 | M69: 1 | N69: =M69-L69 -> 0 | O69: SEC | P69: Qaisumha | Q69: Approved | R69: =VLOOKUP(B69,'Detailed Update'!B:T,11,FALSE) -> #N/A | S69: =VLOOKUP(B69,'Detailed Update'!B:T,12,FALSE) -> #N/A | T69: =VLOOKUP(B69,'Detailed Update'!B:T,13,FALSE) -> #N/A | U69: =VLOOKUP(B69,'Detailed Update'!B:T,17,FALSE) -> #N/A | V69: =VLOOKUP(B69,'Detailed Update'!B:S,18,FALSE) -> #N/A | W69: =VLOOKUP(B69,'Detailed Update'!B:T,19,FALSE) -> #N/A | X69: =VLOOKUP(B69,'Detailed Update'!B:U,20,FALSE) -> #N/A
B70: PE-229 | C70: Construction of Temporary Rail Line (CO project of PE-181) | D70: =VLOOKUP(B70,'Updated Progress % + TCC'!B:D,3,FALSE) -> Sami Atta | E70: Eastern | F70: =IF(M70>70.01%,"No","Yes") -> No | G70: No | H70: No | L70: 1 | M70: 1 | N70: =M70-L70 -> 0 | O70: SEC | P70: Ras Al Khair | Q70: Approved | R70: =VLOOKUP(B70,'Detailed Update'!B:T,11,FALSE) -> NA | S70: =VLOOKUP(B70,'Detailed Update'!B:T,12,FALSE) -> NA | T70: =VLOOKUP(B70,'Detailed Update'!B:T,13,FALSE) -> NA | U70: =VLOOKUP(B70,'Detailed Update'!B:T,17,FALSE) -> 45605 | V70: =VLOOKUP(B70,'Detailed Update'!B:S,18,FALSE) -> 45605 | W70: =VLOOKUP(B70,'Detailed Update'!B:T,19,FALSE) -> 46022 | X70: =VLOOKUP(B70,'Detailed Update'!B:U,20,FALSE) -> All Certificates Recieved
B71: PE-240 | C71: SWCC | OHTL Portion | D71: =VLOOKUP(B71,'Updated Progress % + TCC'!B:D,3,FALSE) -> Moath Ahmad Mahmoud Almousa | E71: Eastern | F71: =IF(M71>70.01%,"No","Yes") -> No | G71: No | H71: No | K71: 44704 | L71: 1 | M71: 0.999 | N71: =M71-L71 -> -0.001 | O71: SWCC | P71: Jubail | Q71: Under Approval | R71: =VLOOKUP(B71,'Detailed Update'!B:T,11,FALSE) -> 45345 | S71: =VLOOKUP(B71,'Detailed Update'!B:T,12,FALSE) -> 45345 | T71: =VLOOKUP(B71,'Detailed Update'!B:T,13,FALSE) -> 46053 | U71: =VLOOKUP(B71,'Detailed Update'!B:T,17,FALSE) -> 45345 | V71: =VLOOKUP(B71,'Detailed Update'!B:S,18,FALSE) -> 45345 | W71: =VLOOKUP(B71,'Detailed Update'!B:T,19,FALSE) -> 46053 | X71: =VLOOKUP(B71,'Detailed Update'!B:U,20,FALSE) -> PAC Partially Recieved Waiting for final approval of Time Extension on Etimad For FAC Pending on PE-238
A72: 41 | B72: PE-214 | C72: =VLOOKUP(B72,'Detailed Update'!B:C,2,FALSE) -> UTHMANIYAH | D72: =VLOOKUP(B72,'Updated Progress % + TCC'!B:D,3,FALSE) -> Munther Alkhatib | E72: =VLOOKUP(B72,'Updated Progress % + TCC'!B:J,9,FALSE) -> Eastern | F72: =IF(M72>70.01%,"No","Yes") -> No | G72: No | H72: No | I72: No | K72: =VLOOKUP(B72,'Detailed Update'!B:D,3,FALSE) -> 43884 | L72: =VLOOKUP(B72,'Detailed Update'!B:I,4,FALSE) -> 1 | M72: =VLOOKUP(B72,'Detailed Update'!B:I,5,FALSE) -> 0.999775 | N72: =M72-L72 -> -0.000225 | O72: =VLOOKUP(B72,'Detailed Update'!B:I,6,FALSE) -> Aramco | P72: =VLOOKUP(B72,'Detailed Update'!B:I,8,FALSE) -> Dammam | Q72: Approved | R72: =VLOOKUP(B72,'Detailed Update'!B:T,11,FALSE) -> 45134 | S72: =VLOOKUP(B72,'Detailed Update'!B:T,12,FALSE) -> 45626 | T72: =VLOOKUP(B72,'Detailed Update'!B:T,13,FALSE) -> 45550 | U72: =VLOOKUP(B72,'Detailed Update'!B:T,17,FALSE) -> 45234 | V72: =VLOOKUP(B72,'Detailed Update'!B:S,18,FALSE) -> 45626 | W72: =VLOOKUP(B72,'Detailed Update'!B:T,19,FALSE) -> 46142 | X72: =VLOOKUP(B72,'Detailed Update'!B:U,20,FALSE) -> All Certificates Recieved FAC not Not applicable/MCC
A73: 42 | B73: PE-227 | C73: =VLOOKUP(B73,'Detailed Update'!B:C,2,FALSE) -> Ibn zahr Expn. | D73: =VLOOKUP(B73,'Updated Progress % + TCC'!B:D,3,FALSE) -> Walid Khater | E73: =VLOOKUP(B73,'Updated Progress % + TCC'!B:J,9,FALSE) -> Eastern | F73: =IF(M73>70.01%,"No","Yes") -> No | G73: No | H73: No | I73: No | J73: No | K73: =VLOOKUP(B73,'Detailed Update'!B:D,3,FALSE) -> 44357 | L73: =VLOOKUP(B73,'Detailed Update'!B:I,4,FALSE) -> 1 | M73: =VLOOKUP(B73,'Detailed Update'!B:I,5,FALSE) -> 0.88294 | N73: =M73-L73 -> -0.11706 | O73: =VLOOKUP(B73,'Detailed Update'!B:I,6,FALSE) -> SEC | P73: =VLOOKUP(B73,'Detailed Update'!B:I,8,FALSE) -> Dammam | Q73: Approved | R73: =VLOOKUP(B73,'Detailed Update'!B:T,11,FALSE) -> 44814 | S73: =VLOOKUP(B73,'Detailed Update'!B:T,12,FALSE) -> 45412 | T73: =VLOOKUP(B73,'Detailed Update'!B:T,13,FALSE) -> 46331 | U73: =VLOOKUP(B73,'Detailed Update'!B:T,17,FALSE) -> 44875 | V73: =VLOOKUP(B73,'Detailed Update'!B:S,18,FALSE) -> 45473 | W73: =VLOOKUP(B73,'Detailed Update'!B:T,19,FALSE) -> 46392 | X73: =VLOOKUP(B73,'Detailed Update'!B:U,20,FALSE) -> -
A74: 43 | B74: PE-238 | C74: =VLOOKUP(B74,'Detailed Update'!B:C,2,FALSE) -> SWCC | BSP Portion | D74: =VLOOKUP(B74,'Updated Progress % + TCC'!B:D,3,FALSE) -> Sami Abdou Sayed Atta | E74: =VLOOKUP(B74,'Updated Progress % + TCC'!B:J,9,FALSE) -> Eastern | F74: =IF(M74>70.01%,"No","Yes") -> No | G74: No | H74: No | I74: No | K74: =VLOOKUP(B74,'Detailed Update'!B:D,3,FALSE) -> 44704 | L74: =VLOOKUP(B74,'Detailed Update'!B:I,4,FALSE) -> 1 | M74: =VLOOKUP(B74,'Detailed Update'!B:I,5,FALSE) -> 0.981722 | N74: =M74-L74 -> -0.018278 | O74: =VLOOKUP(B74,'Detailed Update'!B:I,6,FALSE) -> SWCC | P74: =VLOOKUP(B74,'Detailed Update'!B:I,8,FALSE) -> Jubail | Q74: Under Approval | R74: =VLOOKUP(B74,'Detailed Update'!B:T,11,FALSE) -> 45345 | S74: =VLOOKUP(B74,'Detailed Update'!B:T,12,FALSE) -> 45345 | T74: =VLOOKUP(B74,'Detailed Update'!B:T,13,FALSE) -> 46053 | U74: =VLOOKUP(B74,'Detailed Update'!B:T,17,FALSE) -> 45345 | V74: =VLOOKUP(B74,'Detailed Update'!B:S,18,FALSE) -> 45345 | W74: =VLOOKUP(B74,'Detailed Update'!B:T,19,FALSE) -> 46203 | X74: =VLOOKUP(B74,'Detailed Update'!B:U,20,FALSE) -> PAC Partially Recieved Waiting for final approval of Time Extension on Etimad For FAC
A75: 44 | B75: PE-239 | C75: =VLOOKUP(B75,'Detailed Update'!B:C,2,FALSE) -> SWCC | Solar Package | D75: =VLOOKUP(B75,'Updated Progress % + TCC'!B:D,3,FALSE) -> Walid Khater | E75: =VLOOKUP(B75,'Updated Progress % + TCC'!B:J,9,FALSE) -> Eastern | F75: =IF(M75>70.01%,"No","Yes") -> No | G75: No | H75: No | I75: No | K75: =VLOOKUP(B75,'Detailed Update'!B:D,3,FALSE) -> 45336 | L75: =VLOOKUP(B75,'Detailed Update'!B:I,4,FALSE) -> 1 | M75: =VLOOKUP(B75,'Detailed Update'!B:I,5,FALSE) -> 0.907 | N75: =M75-L75 -> -0.093 | O75: =VLOOKUP(B75,'Detailed Update'!B:I,6,FALSE) -> SWCC | P75: =VLOOKUP(B75,'Detailed Update'!B:I,8,FALSE) -> Jubail | Q75: Under Approval | R75: =VLOOKUP(B75,'Detailed Update'!B:T,11,FALSE) -> 45702 | S75: =VLOOKUP(B75,'Detailed Update'!B:T,12,FALSE) -> 45702 | T75: =VLOOKUP(B75,'Detailed Update'!B:T,13,FALSE) -> 46203 | U75: =VLOOKUP(B75,'Detailed Update'!B:T,17,FALSE) -> 45702 | V75: =VLOOKUP(B75,'Detailed Update'!B:S,18,FALSE) -> 45702 | W75: =VLOOKUP(B75,'Detailed Update'!B:T,19,FALSE) -> 46203 | X75: =VLOOKUP(B75,'Detailed Update'!B:U,20,FALSE) -> -
A76: 45 | B76: PE-277 | C76: =VLOOKUP(B76,'Detailed Update'!B:C,2,FALSE) -> Thuqbah BSP 380/115KV | D76: =VLOOKUP(B76,'Updated Progress % + TCC'!B:D,3,FALSE) -> Mohammed Kutkut | E76: =VLOOKUP(B76,'Updated Progress % + TCC'!B:J,9,FALSE) -> Eastern | F76: =IF(M76>70.01%,"No","Yes") -> No | G76: No | H76: No | I76: No | K76: =VLOOKUP(B76,'Detailed Update'!B:D,3,FALSE) -> 45218 | L76: =VLOOKUP(B76,'Detailed Update'!B:I,4,FALSE) -> 0.98825 | M76: =VLOOKUP(B76,'Detailed Update'!B:I,5,FALSE) -> 0.966064 | N76: =M76-L76 -> -0.022186 | O76: =VLOOKUP(B76,'Detailed Update'!B:I,6,FALSE) -> SEC | P76: =VLOOKUP(B76,'Detailed Update'!B:I,8,FALSE) -> Thuqbah | Q76: Approved | R76: =VLOOKUP(B76,'Detailed Update'!B:T,11,FALSE) -> 45766 | S76: =VLOOKUP(B76,'Detailed Update'!B:T,12,FALSE) -> 46173 | T76: =VLOOKUP(B76,'Detailed Update'!B:T,13,FALSE) -> 46173 | U76: =VLOOKUP(B76,'Detailed Update'!B:T,17,FALSE) -> 45919 | V76: =VLOOKUP(B76,'Detailed Update'!B:S,18,FALSE) -> 46326 | W76: =VLOOKUP(B76,'Detailed Update'!B:T,19,FALSE) -> 46418 | X76: =VLOOKUP(B76,'Detailed Update'!B:U,20,FALSE) -> -
A77: 46 | B77: PE-288 | C77: =VLOOKUP(B77,'Detailed Update'!B:C,2,FALSE) -> Repl. of Berry Gas Plant 230/115KV SS | D77: =VLOOKUP(B77,'Updated Progress % + TCC'!B:D,3,FALSE) -> Moath Ahmad Mahmoud Almousa | E77: =VLOOKUP(B77,'Updated Progress % + TCC'!B:J,9,FALSE) -> Eastern | F77: =IF(M77>70.01%,"No","Yes") -> No | G77: =IF(N77>70.01%,"No","Yes") -> Yes | H77: No | I77: No | J77: No | K77: =VLOOKUP(B77,'Detailed Update'!B:D,3,FALSE) -> 45431 | L77: =VLOOKUP(B77,'Detailed Update'!B:I,4,FALSE) -> 0.92007823 | M77: =VLOOKUP(B77,'Detailed Update'!B:I,5,FALSE) -> 0.85511484 | N77: =M77-L77 -> -0.064963387 | O77: =VLOOKUP(B77,'Detailed Update'!B:I,6,FALSE) -> SEC | P77: =VLOOKUP(B77,'Detailed Update'!B:I,8,FALSE) -> Jubail | Q77: Under Approval | R77: =VLOOKUP(B77,'Detailed Update'!B:T,11,FALSE) -> 46041 | S77: =VLOOKUP(B77,'Detailed Update'!B:T,12,FALSE) -> 46041 | T77: =VLOOKUP(B77,'Detailed Update'!B:T,13,FALSE) -> 46305 | U77: =VLOOKUP(B77,'Detailed Update'!B:T,17,FALSE) -> 46526 | V77: =VLOOKUP(B77,'Detailed Update'!B:S,18,FALSE) -> 46526 | W77: =VLOOKUP(B77,'Detailed Update'!B:T,19,FALSE) -> 46701 | X77: =VLOOKUP(B77,'Detailed Update'!B:U,20,FALSE) -> OHTL Portion after 11 months from SS which is shown here
A78: 47 | B78: PE-302 | C78: =VLOOKUP(B78,'Detailed Update'!B:C,2,FALSE) -> AL RAMES 380/115 KV BSP | D78: =VLOOKUP(B78,'Updated Progress % + TCC'!B:D,3,FALSE) -> Mohamed Ali Hafez Aman | E78: =VLOOKUP(B78,'Updated Progress % + TCC'!B:J,9,FALSE) -> Eastern | F78: =IF(M78>70.01%,"No","Yes") -> No | G78: No | H78: No | I78: No | K78: =VLOOKUP(B78,'Detailed Update'!B:D,3,FALSE) -> 45218 | L78: =VLOOKUP(B78,'Detailed Update'!B:I,4,FALSE) -> 0.99474531 | M78: =VLOOKUP(B78,'Detailed Update'!B:I,5,FALSE) -> 0.99269133 | N78: =M78-L78 -> -0.0020539761 | O78: =VLOOKUP(B78,'Detailed Update'!B:I,6,FALSE) -> SEC | P78: =VLOOKUP(B78,'Detailed Update'!B:I,8,FALSE) -> Dammam | Q78: Approved | R78: =VLOOKUP(B78,'Detailed Update'!B:T,11,FALSE) -> 45766 | S78: =VLOOKUP(B78,'Detailed Update'!B:T,12,FALSE) -> 46356 | T78: =VLOOKUP(B78,'Detailed Update'!B:T,13,FALSE) -> 46173 | U78: =VLOOKUP(B78,'Detailed Update'!B:T,17,FALSE) -> 45918 | V78: =VLOOKUP(B78,'Detailed Update'!B:S,18,FALSE) -> 46507 | W78: =VLOOKUP(B78,'Detailed Update'!B:T,19,FALSE) -> 46568 | X78: =VLOOKUP(B78,'Detailed Update'!B:U,20,FALSE) -> Expected TCC will be on 13 Dec 26 due to delay of FOC readiness (31 Aug 2026) / Disconnector Switch
A79: 48 | B79: PE-334 | C79: =VLOOKUP(B79,'Detailed Update'!B:C,2,FALSE) -> Ghazlan-3 BSP | D79: =VLOOKUP(B79,'Updated Progress % + TCC'!B:D,3,FALSE) -> Mahmoud Abdelaal | E79: =VLOOKUP(B79,'Updated Progress % + TCC'!B:J,9,FALSE) -> Eastern | F79: =IF(M79>70.01%,"No","Yes") -> Yes | K79: =VLOOKUP(B79,'Detailed Update'!B:D,3,FALSE) -> 45697 | L79: =VLOOKUP(B79,'Detailed Update'!B:I,4,FALSE) -> 0.72111 | M79: =VLOOKUP(B79,'Detailed Update'!B:I,5,FALSE) -> 0.465294 | N79: =M79-L79 -> -0.255816 | O79: =VLOOKUP(B79,'Detailed Update'!B:I,6,FALSE) -> SEC | P79: =VLOOKUP(B79,'Detailed Update'!B:I,8,FALSE) -> Ghazlan | Q79: Under Approval | R79: =VLOOKUP(B79,'Detailed Update'!B:T,11,FALSE) -> 46212 | S79: =VLOOKUP(B79,'Detailed Update'!B:T,12,FALSE) -> 46212 | T79: =VLOOKUP(B79,'Detailed Update'!B:T,13,FALSE) -> 46500 | U79: =VLOOKUP(B79,'Detailed Update'!B:T,17,FALSE) -> 46365 | V79: =VLOOKUP(B79,'Detailed Update'!B:S,18,FALSE) -> 46365 | W79: =VLOOKUP(B79,'Detailed Update'!B:T,19,FALSE) -> 46660 | X79: =VLOOKUP(B79,'Detailed Update'!B:U,20,FALSE) -> Planned % is based on orginal baseline however we have a submitted revised schedule showing 80% used for internal reporting
A80: 49 | B80: PE-344 | C80: =VLOOKUP(B80,'Detailed Update'!B:C,2,FALSE) -> Nariyah BSP | D80: =VLOOKUP(B80,'Updated Progress % + TCC'!B:D,3,FALSE) -> Mohamed Elhag | E80: =VLOOKUP(B80,'Updated Progress % + TCC'!B:J,9,FALSE) -> Eastern | F80: =IF(M80>70.01%,"No","Yes") -> Yes | G80: No | K80: =VLOOKUP(B80,'Detailed Update'!B:D,3,FALSE) -> 45715 | L80: =VLOOKUP(B80,'Detailed Update'!B:I,4,FALSE) -> 0.954856 | M80: =VLOOKUP(B80,'Detailed Update'!B:I,5,FALSE) -> 0.56828 | N80: =M80-L80 -> -0.386576 | O80: =VLOOKUP(B80,'Detailed Update'!B:I,6,FALSE) -> SEC | P80: =VLOOKUP(B80,'Detailed Update'!B:I,8,FALSE) -> Nariyah | Q80: N/A | R80: =VLOOKUP(B80,'Detailed Update'!B:T,11,FALSE) -> 46291 | S80: =VLOOKUP(B80,'Detailed Update'!B:T,12,FALSE) -> 46291 | T80: =VLOOKUP(B80,'Detailed Update'!B:T,13,FALSE) -> 46544 | U80: =VLOOKUP(B80,'Detailed Update'!B:T,17,FALSE) -> 46444 | V80: =VLOOKUP(B80,'Detailed Update'!B:S,18,FALSE) -> 46444 | W80: =VLOOKUP(B80,'Detailed Update'!B:T,19,FALSE) -> 46699 | X80: =VLOOKUP(B80,'Detailed Update'!B:U,20,FALSE) -> Delayed due to the delivery of GIS equipment Delayed 2times 1st delay till 25-June-26 2nd Delay till 25-Aug-26
A81: 50 | B81: PE-355 | C81: =VLOOKUP(B81,'Detailed Update'!B:C,2,FALSE) -> Construction of King Saud Air Base Facilities | D81: =VLOOKUP(B81,'Updated Progress % + TCC'!B:D,3,FALSE) -> Mohammed Kutkut | E81: =VLOOKUP(B81,'Updated Progress % + TCC'!B:J,9,FALSE) -> Eastern | F81: =IF(M81>70.01%,"No","Yes") -> Yes | G81: Yes | H81: No | K81: =VLOOKUP(B81,'Detailed Update'!B:D,3,FALSE) -> 45879 | L81: =VLOOKUP(B81,'Detailed Update'!B:I,4,FALSE) -> 0.1757 | M81: =VLOOKUP(B81,'Detailed Update'!B:I,5,FALSE) -> 0.12 | N81: =M81-L81 -> -0.0557 | O81: =VLOOKUP(B81,'Detailed Update'!B:I,6,FALSE) -> RSAF | P81: =VLOOKUP(B81,'Detailed Update'!B:I,8,FALSE) -> Haffr Albatan | Q81: N/A | R81: =VLOOKUP(B81,'Detailed Update'!B:T,11,FALSE) -> 46609 | S81: =VLOOKUP(B81,'Detailed Update'!B:T,12,FALSE) -> 46609 | T81: =VLOOKUP(B81,'Detailed Update'!B:T,13,FALSE) -> 46657 | U81: =VLOOKUP(B81,'Detailed Update'!B:T,17,FALSE) -> 47097 | V81: =VLOOKUP(B81,'Detailed Update'!B:S,18,FALSE) -> 47097 | W81: =VLOOKUP(B81,'Detailed Update'!B:T,19,FALSE) -> 47097 | X81: =VLOOKUP(B81,'Detailed Update'!B:U,20,FALSE) -> Only Scope Alfanar / There is no FAC only based on the 40 Months Completion
A82: 51 | B82: PE-304 | C82: =VLOOKUP(B82,'Detailed Update'!B:C,2,FALSE) -> 230/115kV SS | JUBAIL SW REPLACEMENT | D82: =VLOOKUP(B82,'Updated Progress % + TCC'!B:D,3,FALSE) -> Munther Alkhatib | E82: =VLOOKUP(B82,'Updated Progress % + TCC'!B:J,9,FALSE) -> Eastern | F82: =IF(M82>70.01%,"No","Yes") -> Yes | G82: No | K82: =VLOOKUP(B82,'Detailed Update'!B:D,3,FALSE) -> 45900 | L82: =VLOOKUP(B82,'Detailed Update'!B:I,4,FALSE) -> 0.1969 | M82: =VLOOKUP(B82,'Detailed Update'!B:I,5,FALSE) -> 0.126 | N82: =M82-L82 -> -0.0709 | O82: =VLOOKUP(B82,'Detailed Update'!B:I,6,FALSE) -> SEC | P82: =VLOOKUP(B82,'Detailed Update'!B:I,8,FALSE) -> Jubail | Q82: N/A | R82: =VLOOKUP(B82,'Detailed Update'!B:T,11,FALSE) -> 46630 | S82: =VLOOKUP(B82,'Detailed Update'!B:T,12,FALSE) -> 46630 | T82: =VLOOKUP(B82,'Detailed Update'!B:T,13,FALSE) -> 46870 | U82: =VLOOKUP(B82,'Detailed Update'!B:T,17,FALSE) -> 46783 | V82: =VLOOKUP(B82,'Detailed Update'!B:S,18,FALSE) -> 46783 | W82: =VLOOKUP(B82,'Detailed Update'!B:T,19,FALSE) -> 47023 | X82: =VLOOKUP(B82,'Detailed Update'!B:U,20,FALSE) -> Delayed due to site accessibility issues and Water leakage incident
A83: 52 | B83: PE-302 | C83: =VLOOKUP(B83,'Detailed Update'!B:C,2,FALSE) -> AL RAMES 380/115 KV BSP | D83: =VLOOKUP(B83,'Updated Progress % + TCC'!B:D,3,FALSE) -> Mohamed Ali Hafez Aman | E83: =VLOOKUP(B83,'Updated Progress % + TCC'!B:J,9,FALSE) -> Eastern | F83: =IF(M83>70.01%,"No","Yes") -> No | G83: No | K83: =VLOOKUP(B83,'Detailed Update'!B:D,3,FALSE) -> 45218 | L83: =VLOOKUP(B83,'Detailed Update'!B:I,4,FALSE) -> 0.99474531 | M83: =VLOOKUP(B83,'Detailed Update'!B:I,5,FALSE) -> 0.99269133 | N83: =M83-L83 -> -0.0020539761 | O83: =VLOOKUP(B83,'Detailed Update'!B:I,6,FALSE) -> SEC | P83: =VLOOKUP(B83,'Detailed Update'!B:I,8,FALSE) -> Dammam | Q83: N/A | R83: =VLOOKUP(B83,'Detailed Update'!B:T,11,FALSE) -> 45766 | S83: =VLOOKUP(B83,'Detailed Update'!B:T,12,FALSE) -> 46356 | T83: =VLOOKUP(B83,'Detailed Update'!B:T,13,FALSE) -> 46173 | U83: =VLOOKUP(B83,'Detailed Update'!B:T,17,FALSE) -> 45918 | V83: =VLOOKUP(B83,'Detailed Update'!B:S,18,FALSE) -> 46507 | W83: =VLOOKUP(B83,'Detailed Update'!B:T,19,FALSE) -> 46568 | X83: =VLOOKUP(B83,'Detailed Update'!B:U,20,FALSE) -> Expected TCC will be on 13 Dec 26 due to delay of FOC readiness (31 Aug 2026) / Disconnector Switch
A84: 53 | B84: PE-334 | C84: =VLOOKUP(B84,'Detailed Update'!B:C,2,FALSE) -> Ghazlan-3 BSP | D84: =VLOOKUP(B84,'Updated Progress % + TCC'!B:D,3,FALSE) -> Mahmoud Abdelaal | E84: =VLOOKUP(B84,'Updated Progress % + TCC'!B:J,9,FALSE) -> Eastern | F84: =IF(M84>70.01%,"No","Yes") -> Yes | G84: Yes | K84: =VLOOKUP(B84,'Detailed Update'!B:D,3,FALSE) -> 45697 | L84: =VLOOKUP(B84,'Detailed Update'!B:I,4,FALSE) -> 0.72111 | M84: =VLOOKUP(B84,'Detailed Update'!B:I,5,FALSE) -> 0.465294 | N84: =M84-L84 -> -0.255816 | O84: =VLOOKUP(B84,'Detailed Update'!B:I,6,FALSE) -> SEC | P84: =VLOOKUP(B84,'Detailed Update'!B:I,8,FALSE) -> Ghazlan | Q84: N/A | R84: =VLOOKUP(B84,'Detailed Update'!B:T,11,FALSE) -> 46212 | S84: =VLOOKUP(B84,'Detailed Update'!B:T,12,FALSE) -> 46212 | T84: =VLOOKUP(B84,'Detailed Update'!B:T,13,FALSE) -> 46500 | U84: =VLOOKUP(B84,'Detailed Update'!B:T,17,FALSE) -> 46365 | V84: =VLOOKUP(B84,'Detailed Update'!B:S,18,FALSE) -> 46365 | W84: =VLOOKUP(B84,'Detailed Update'!B:T,19,FALSE) -> 46660 | X84: =VLOOKUP(B84,'Detailed Update'!B:U,20,FALSE) -> Planned % is based on orginal baseline however we have a submitted revised schedule showing 80% used for internal reporting
A85: 54 | B85: PE-344 | C85: =VLOOKUP(B85,'Detailed Update'!B:C,2,FALSE) -> Nariyah BSP | D85: =VLOOKUP(B85,'Updated Progress % + TCC'!B:D,3,FALSE) -> Mohamed Elhag | E85: =VLOOKUP(B85,'Updated Progress % + TCC'!B:J,9,FALSE) -> Eastern | F85: =IF(M85>70.01%,"No","Yes") -> Yes | G85: no | K85: =VLOOKUP(B85,'Detailed Update'!B:D,3,FALSE) -> 45715 | L85: =VLOOKUP(B85,'Detailed Update'!B:I,4,FALSE) -> 0.954856 | M85: =VLOOKUP(B85,'Detailed Update'!B:I,5,FALSE) -> 0.56828 | N85: =M85-L85 -> -0.386576 | O85: =VLOOKUP(B85,'Detailed Update'!B:I,6,FALSE) -> SEC | P85: =VLOOKUP(B85,'Detailed Update'!B:I,8,FALSE) -> Nariyah | Q85: N/A | R85: =VLOOKUP(B85,'Detailed Update'!B:T,11,FALSE) -> 46291 | S85: =VLOOKUP(B85,'Detailed Update'!B:T,12,FALSE) -> 46291 | T85: =VLOOKUP(B85,'Detailed Update'!B:T,13,FALSE) -> 46544 | U85: =VLOOKUP(B85,'Detailed Update'!B:T,17,FALSE) -> 46444 | V85: =VLOOKUP(B85,'Detailed Update'!B:S,18,FALSE) -> 46444 | W85: =VLOOKUP(B85,'Detailed Update'!B:T,19,FALSE) -> 46699 | X85: =VLOOKUP(B85,'Detailed Update'!B:U,20,FALSE) -> Delayed due to the delivery of GIS equipment Delayed 2times 1st delay till 25-June-26 2nd Delay till 25-Aug-26
A86: 55 | B86: PE-355 | C86: =VLOOKUP(B86,'Detailed Update'!B:C,2,FALSE) -> Construction of King Saud Air Base Facilities | D86: =VLOOKUP(B86,'Updated Progress % + TCC'!B:D,3,FALSE) -> Mohammed Kutkut | E86: =VLOOKUP(B86,'Updated Progress % + TCC'!B:J,9,FALSE) -> Eastern | F86: =IF(M86>70.01%,"No","Yes") -> Yes | G86: Yes | K86: =VLOOKUP(B86,'Detailed Update'!B:D,3,FALSE) -> 45879 | L86: =VLOOKUP(B86,'Detailed Update'!B:I,4,FALSE) -> 0.1757 | M86: =VLOOKUP(B86,'Detailed Update'!B:I,5,FALSE) -> 0.12 | N86: =M86-L86 -> -0.0557 | O86: =VLOOKUP(B86,'Detailed Update'!B:I,6,FALSE) -> RSAF | P86: =VLOOKUP(B86,'Detailed Update'!B:I,8,FALSE) -> Haffr Albatan | Q86: N/A | R86: =VLOOKUP(B86,'Detailed Update'!B:T,11,FALSE) -> 46609 | S86: =VLOOKUP(B86,'Detailed Update'!B:T,12,FALSE) -> 46609 | T86: =VLOOKUP(B86,'Detailed Update'!B:T,13,FALSE) -> 46657 | U86: =VLOOKUP(B86,'Detailed Update'!B:T,17,FALSE) -> 47097 | V86: =VLOOKUP(B86,'Detailed Update'!B:S,18,FALSE) -> 47097 | W86: =VLOOKUP(B86,'Detailed Update'!B:T,19,FALSE) -> 47097 | X86: =VLOOKUP(B86,'Detailed Update'!B:U,20,FALSE) -> Only Scope Alfanar / There is no FAC only based on the 40 Months Completion
A87: 56 | B87: PE-304 | C87: =VLOOKUP(B87,'Detailed Update'!B:C,2,FALSE) -> 230/115kV SS | JUBAIL SW REPLACEMENT | D87: =VLOOKUP(B87,'Updated Progress % + TCC'!B:D,3,FALSE) -> Munther Alkhatib | E87: =VLOOKUP(B87,'Updated Progress % + TCC'!B:J,9,FALSE) -> Eastern | F87: =IF(M87>70.01%,"No","Yes") -> Yes | G87: No | K87: =VLOOKUP(B87,'Detailed Update'!B:D,3,FALSE) -> 45900 | L87: =VLOOKUP(B87,'Detailed Update'!B:I,4,FALSE) -> 0.1969 | M87: =VLOOKUP(B87,'Detailed Update'!B:I,5,FALSE) -> 0.126 | N87: =M87-L87 -> -0.0709 | O87: =VLOOKUP(B87,'Detailed Update'!B:I,6,FALSE) -> SEC | P87: =VLOOKUP(B87,'Detailed Update'!B:I,8,FALSE) -> Jubail | Q87: N/A | R87: =VLOOKUP(B87,'Detailed Update'!B:T,11,FALSE) -> 46630 | S87: =VLOOKUP(B87,'Detailed Update'!B:T,12,FALSE) -> 46630 | T87: =VLOOKUP(B87,'Detailed Update'!B:T,13,FALSE) -> 46870 | U87: =VLOOKUP(B87,'Detailed Update'!B:T,17,FALSE) -> 46783 | V87: =VLOOKUP(B87,'Detailed Update'!B:S,18,FALSE) -> 46783 | W87: =VLOOKUP(B87,'Detailed Update'!B:T,19,FALSE) -> 47023 | X87: =VLOOKUP(B87,'Detailed Update'!B:U,20,FALSE) -> Delayed due to site accessibility issues and Water leakage incident
A88: 57 | B88: PE-366 | C88: =VLOOKUP(B88,'Detailed Update'!B:C,2,FALSE) -> Qulayyib 380 kV BSP | D88: =VLOOKUP(B88,'Updated Progress % + TCC'!B:D,3,FALSE) -> Tarig Mohammed | E88: =VLOOKUP(B88,'Updated Progress % + TCC'!B:J,9,FALSE) -> Eastern | F88: =IF(M88>70.01%,"No","Yes") -> Yes | K88: =VLOOKUP(B88,'Detailed Update'!B:D,3,FALSE) -> 46113 | L88: =VLOOKUP(B88,'Detailed Update'!B:I,4,FALSE) -> 0.06743 | M88: =VLOOKUP(B88,'Detailed Update'!B:I,5,FALSE) -> 0.03998 | N88: =M88-L88 -> -0.02745 | O88: =VLOOKUP(B88,'Detailed Update'!B:I,6,FALSE) -> MGC-Mutlaq Al Gowairi Company | P88: =VLOOKUP(B88,'Detailed Update'!B:I,8,FALSE) -> Qulayyib Area | Q88: N/A | R88: =VLOOKUP(B88,'Detailed Update'!B:T,11,FALSE) -> 46905 | S88: =VLOOKUP(B88,'Detailed Update'!B:T,12,FALSE) -> 46905 | T88: =VLOOKUP(B88,'Detailed Update'!B:T,13,FALSE) -> 46943 | U88: =VLOOKUP(B88,'Detailed Update'!B:T,17,FALSE) -> 47270 | V88: =VLOOKUP(B88,'Detailed Update'!B:S,18,FALSE) -> 47270 | W88: =VLOOKUP(B88,'Detailed Update'!B:T,19,FALSE) -> 47308 | X88: =VLOOKUP(B88,'Detailed Update'!B:U,20,FALSE) -> -
A89: 58 | B89: PE-354 | C89: =VLOOKUP(B89,'Detailed Update'!B:C,2,FALSE) -> Construction of NEW VSC HVDC Overhead Transmission Line for EOA-COA Link 1 | D89: =VLOOKUP(B89,'Updated Progress % + TCC'!B:D,3,FALSE) -> Moath Ahmad Mahmoud Almousa | E89: =VLOOKUP(B89,'Updated Progress % + TCC'!B:J,9,FALSE) -> Eastern | F89: =IF(M89>70.01%,"No","Yes") -> Yes | K89: =VLOOKUP(B89,'Detailed Update'!B:D,3,FALSE) -> 46146 | L89: =VLOOKUP(B89,'Detailed Update'!B:I,4,FALSE) -> 0.029387 | M89: =VLOOKUP(B89,'Detailed Update'!B:I,5,FALSE) -> 0.01827 | N89: =M89-L89 -> -0.011117 | O89: =VLOOKUP(B89,'Detailed Update'!B:I,6,FALSE) -> SEC | P89: =VLOOKUP(B89,'Detailed Update'!B:I,8,FALSE) -> Nariyah | Q89: N/A | R89: =VLOOKUP(B89,'Detailed Update'!B:T,11,FALSE) -> 47061 | S89: =VLOOKUP(B89,'Detailed Update'!B:T,12,FALSE) -> 47061 | T89: =VLOOKUP(B89,'Detailed Update'!B:T,13,FALSE) -> 47079 | U89: =VLOOKUP(B89,'Detailed Update'!B:T,17,FALSE) -> 47212 | V89: =VLOOKUP(B89,'Detailed Update'!B:S,18,FALSE) -> 47212 | W89: =VLOOKUP(B89,'Detailed Update'!B:T,19,FALSE) -> 47236 | X89: -
C90: WESTERN REGION UNIT (MOHAMMED ALBAZIE)
A91: 59 | B91: PE-243 | C91: =VLOOKUP(B91,'Detailed Update'!B:C,2,FALSE) -> Installation of Dynamic Reactive Power Compensation(DRPC) at Tabuk 380KV BSP | D91: =VLOOKUP(B91,'Updated Progress % + TCC'!B:D,3,FALSE) -> Shafqat Zia | E91: =VLOOKUP(B91,'Updated Progress % + TCC'!B:J,9,FALSE) -> Western | F91: =IF(M91>70.01%,"No","Yes") -> No | K91: =VLOOKUP(B91,'Detailed Update'!B:D,3,FALSE) -> 44700 | L91: =VLOOKUP(B91,'Detailed Update'!B:I,4,FALSE) -> 1 | M91: =VLOOKUP(B91,'Detailed Update'!B:I,5,FALSE) -> 1 | N91: =M91-L91 -> 0 | O91: =VLOOKUP(B91,'Detailed Update'!B:I,6,FALSE) -> SEC | P91: =VLOOKUP(B91,'Detailed Update'!B:I,8,FALSE) -> Tabuk | Q91: N/A | R91: =VLOOKUP(B91,'Detailed Update'!B:T,11,FALSE) -> 45492 | S91: =VLOOKUP(B91,'Detailed Update'!B:T,12,FALSE) -> 45777 | T91: =VLOOKUP(B91,'Detailed Update'!B:T,13,FALSE) -> 45777 | U91: =VLOOKUP(B91,'Detailed Update'!B:T,17,FALSE) -> 45615 | V91: =VLOOKUP(B91,'Detailed Update'!B:S,18,FALSE) -> 46052 | W91: =VLOOKUP(B91,'Detailed Update'!B:T,19,FALSE) -> 46446 | X91: =VLOOKUP(B91,'Detailed Update'!B:U,20,FALSE) -> Energization done without TSC Panel, TCC received. Partial PAC (21-Jan-2026) also received; Balance PAC & FAC upon delivery of remaining TSC Panel; Alfanar requested for FAC invoice and under discussion with SEC.
A92: 60 | B92: PE-241 | C92: =VLOOKUP(B92,'Detailed Update'!B:C,2,FALSE) -> Expansion of Existing Yanbu Central (YCNT) | D92: =VLOOKUP(B92,'Updated Progress % + TCC'!B:D,3,FALSE) -> Zohaib Iqbal | E92: =VLOOKUP(B92,'Updated Progress % + TCC'!B:J,9,FALSE) -> Western | F92: =IF(M92>70.01%,"No","Yes") -> No | K92: =VLOOKUP(B92,'Detailed Update'!B:D,3,FALSE) -> 44598 | L92: =VLOOKUP(B92,'Detailed Update'!B:I,4,FALSE) -> 1 | M92: =VLOOKUP(B92,'Detailed Update'!B:I,5,FALSE) -> 0.989 | N92: =M92-L92 -> -0.011 | O92: =VLOOKUP(B92,'Detailed Update'!B:I,6,FALSE) -> SEC | P92: =VLOOKUP(B92,'Detailed Update'!B:I,8,FALSE) -> Yanbu,Umluj& Alwajh | Q92: N/A | R92: =VLOOKUP(B92,'Detailed Update'!B:T,11,FALSE) -> 45297 | S92: =VLOOKUP(B92,'Detailed Update'!B:T,12,FALSE) -> 45565 | T92: =VLOOKUP(B92,'Detailed Update'!B:T,13,FALSE) -> 45565 | U92: =VLOOKUP(B92,'Detailed Update'!B:T,17,FALSE) -> 45449 | V92: =VLOOKUP(B92,'Detailed Update'!B:S,18,FALSE) -> 45716 | W92: =VLOOKUP(B92,'Detailed Update'!B:T,19,FALSE) -> 46285 | X92: =VLOOKUP(B92,'Detailed Update'!B:U,20,FALSE) -> PAC received, not yet energized due to SE shutdown issues for all the area
A93: 61 | B93: PE-257 | C93: =VLOOKUP(B93,'Detailed Update'!B:C,2,FALSE) -> Expansions of Existing MHD 380 KV BSP | D93: =VLOOKUP(B93,'Updated Progress % + TCC'!B:D,3,FALSE) -> Omar Samman | E93: =VLOOKUP(B93,'Updated Progress % + TCC'!B:J,9,FALSE) -> Western | F93: =IF(M93>70.01%,"No","Yes") -> No | K93: =VLOOKUP(B93,'Detailed Update'!B:D,3,FALSE) -> 44868 | L93: =VLOOKUP(B93,'Detailed Update'!B:I,4,FALSE) -> 1 | M93: =VLOOKUP(B93,'Detailed Update'!B:I,5,FALSE) -> 0.9989 | N93: =M93-L93 -> -0.0011 | O93: =VLOOKUP(B93,'Detailed Update'!B:I,6,FALSE) -> SEC | P93: =VLOOKUP(B93,'Detailed Update'!B:I,8,FALSE) -> Madinah | Q93: N/A | R93: =VLOOKUP(B93,'Detailed Update'!B:T,11,FALSE) -> 45415 | S93: =VLOOKUP(B93,'Detailed Update'!B:T,12,FALSE) -> 45960 | T93: =VLOOKUP(B93,'Detailed Update'!B:T,13,FALSE) -> 46021 | U93: =VLOOKUP(B93,'Detailed Update'!B:T,17,FALSE) -> 45567 | V93: =VLOOKUP(B93,'Detailed Update'!B:S,18,FALSE) -> 46111 | W93: =VLOOKUP(B93,'Detailed Update'!B:T,19,FALSE) -> 46174 | X93: =VLOOKUP(B93,'Detailed Update'!B:U,20,FALSE) -> As-built drawings under SEC review & approval. FAC certification waiting from SE; Request for issuance of FAC / Commitment for Completion of Outstanding Work was submitted on 20-Jul-26.
A94: 62 | B94: PE-258 | C94: =VLOOKUP(B94,'Detailed Update'!B:C,2,FALSE) -> Taif East Governorate Project | D94: =VLOOKUP(B94,'Updated Progress % + TCC'!B:D,3,FALSE) -> Mahmoud Sobhy El Sayed | E94: =VLOOKUP(B94,'Updated Progress % + TCC'!B:J,9,FALSE) -> Western | F94: =IF(M94>70.01%,"No","Yes") -> No | G94: No | K94: =VLOOKUP(B94,'Detailed Update'!B:D,3,FALSE) -> 44882 | L94: =VLOOKUP(B94,'Detailed Update'!B:I,4,FALSE) -> 1 | M94: =VLOOKUP(B94,'Detailed Update'!B:I,5,FALSE) -> 0.9 | N94: =M94-L94 -> -0.1 | O94: =VLOOKUP(B94,'Detailed Update'!B:I,6,FALSE) -> SEC | P94: =VLOOKUP(B94,'Detailed Update'!B:I,8,FALSE) -> Taif | Q94: N/A | R94: =VLOOKUP(B94,'Detailed Update'!B:T,11,FALSE) -> 45399 | S94: =VLOOKUP(B94,'Detailed Update'!B:T,12,FALSE) -> 45643 | T94: =VLOOKUP(B94,'Detailed Update'!B:T,13,FALSE) -> 46295 | U94: =VLOOKUP(B94,'Detailed Update'!B:T,17,FALSE) -> 45552 | V94: =VLOOKUP(B94,'Detailed Update'!B:S,18,FALSE) -> 45793 | W94: =VLOOKUP(B94,'Detailed Update'!B:T,19,FALSE) -> 46414 | X94: =VLOOKUP(B94,'Detailed Update'!B:U,20,FALSE) -> 1. EOT-1 Approved upto 14-Dec-24, EOT-2 submitted on 12th Aug 25, TCC upto 17th Jun 26. (Under SEC Approval). EOT to be resubmitted. 2. SAS testing pending due to EWS V.O finalization and delivery (V.O) 3. OHTL Line readiness pending from SE, no clarity on readiness
A95: 63 | B95: PE-270 | C95: =VLOOKUP(B95,'Detailed Update'!B:C,2,FALSE) -> 110/13.8KV HARAZAT SUB JEDDAH | D95: =VLOOKUP(B95,'Updated Progress % + TCC'!B:D,3,FALSE) -> Muhammad Ilyas | E95: =VLOOKUP(B95,'Updated Progress % + TCC'!B:J,9,FALSE) -> Western | F95: =IF(M95>70.01%,"No","Yes") -> No | G95: No | H95: No | I95: No | K95: =VLOOKUP(B95,'Detailed Update'!B:D,3,FALSE) -> 45120 | L95: =VLOOKUP(B95,'Detailed Update'!B:I,4,FALSE) -> 1 | M95: =VLOOKUP(B95,'Detailed Update'!B:I,5,FALSE) -> 0.9841 | N95: =M95-L95 -> -0.0159 | O95: =VLOOKUP(B95,'Detailed Update'!B:I,6,FALSE) -> SEC | P95: =VLOOKUP(B95,'Detailed Update'!B:I,8,FALSE) -> Jeddah | Q95: N/A | R95: =VLOOKUP(B95,'Detailed Update'!B:T,11,FALSE) -> 45609 | S95: =VLOOKUP(B95,'Detailed Update'!B:T,12,FALSE) -> 45729 | T95: =VLOOKUP(B95,'Detailed Update'!B:T,13,FALSE) -> 45867 | U95: =VLOOKUP(B95,'Detailed Update'!B:T,17,FALSE) -> 45760 | V95: =VLOOKUP(B95,'Detailed Update'!B:S,18,FALSE) -> 45882 | W95: =VLOOKUP(B95,'Detailed Update'!B:T,19,FALSE) -> 46295 | X95: =VLOOKUP(B95,'Detailed Update'!B:U,20,FALSE) -> Remote End Works: 1. Installation of Telecom Panels completed, testing will be done, once line readiness from client. (Dependent on Line Readiness from Client) 2. Final Settings of Line Protection Panels. (Dependent on Line Readiness from Client) Punchlist & As built works are in progress, completion date 30-Sep-26. Punchlist:Total 309 nos, 295 Completed, 5 nos ready to close. Asbuilt: 90% completed.
A96: 64 | B96: PE-290 | C96: =VLOOKUP(B96,'Detailed Update'!B:C,2,FALSE) -> Fadelah 110/13.8KV SS - JEDDAH | D96: =VLOOKUP(B96,'Updated Progress % + TCC'!B:D,3,FALSE) -> Khaled Abdelaty Hassan Emara Shehata | E96: =VLOOKUP(B96,'Updated Progress % + TCC'!B:J,9,FALSE) -> Western | F96: =IF(M96>70.01%,"No","Yes") -> No | G96: No | H96: No | I96: No | K96: =VLOOKUP(B96,'Detailed Update'!B:D,3,FALSE) -> 45131 | L96: =VLOOKUP(B96,'Detailed Update'!B:I,4,FALSE) -> 1 | M96: =VLOOKUP(B96,'Detailed Update'!B:I,5,FALSE) -> 0.9842 | N96: =M96-L96 -> -0.0158 | O96: =VLOOKUP(B96,'Detailed Update'!B:I,6,FALSE) -> SEC | P96: =VLOOKUP(B96,'Detailed Update'!B:I,8,FALSE) -> Jeddah | Q96: N/A | R96: =VLOOKUP(B96,'Detailed Update'!B:T,11,FALSE) -> 45620 | S96: =VLOOKUP(B96,'Detailed Update'!B:T,12,FALSE) -> 45924 | T96: =VLOOKUP(B96,'Detailed Update'!B:T,13,FALSE) -> 45834 | U96: =VLOOKUP(B96,'Detailed Update'!B:T,17,FALSE) -> 45771 | V96: =VLOOKUP(B96,'Detailed Update'!B:S,18,FALSE) -> 46138 | W96: =VLOOKUP(B96,'Detailed Update'!B:T,19,FALSE) -> 46295 | X96: =VLOOKUP(B96,'Detailed Update'!B:U,20,FALSE) -> 1) Energization done with temporary line, (Permanent line readiness Dependent on Client). 2) AMI integration with WRCC. (Dependent on Line Readiness from Client). 3) Modon GIS extension bays (Shutdown -Relay setting ) 85% completed. Punchlist & As built works are in progress, completion date 30-Sep-26. Punch points : Out of 10, 2 completed, 3 ready to close. As built status: out of 12, 12 ready to close.
A97: 65 | B97: PE-254 | C97: =VLOOKUP(B97,'Detailed Update'!B:C,2,FALSE) -> HENAKIYAH BSP 380 KV | D97: =VLOOKUP(B97,'Updated Progress % + TCC'!B:D,3,FALSE) -> Mahmoud Sobhy El Sayed | E97: =VLOOKUP(B97,'Updated Progress % + TCC'!B:J,9,FALSE) -> Western | F97: =IF(M97>70.01%,"No","Yes") -> No | G97: No | H97: No | I97: No | K97: =VLOOKUP(B97,'Detailed Update'!B:D,3,FALSE) -> 44861 | L97: =VLOOKUP(B97,'Detailed Update'!B:I,4,FALSE) -> 1 | M97: =VLOOKUP(B97,'Detailed Update'!B:I,5,FALSE) -> 1 | N97: =M97-L97 -> 0 | O97: =VLOOKUP(B97,'Detailed Update'!B:I,6,FALSE) -> SEC | P97: =VLOOKUP(B97,'Detailed Update'!B:I,8,FALSE) -> Madinah | Q97: N/A | R97: =VLOOKUP(B97,'Detailed Update'!B:T,11,FALSE) -> 45562 | S97: =VLOOKUP(B97,'Detailed Update'!B:T,12,FALSE) -> 45657 | T97: =VLOOKUP(B97,'Detailed Update'!B:T,13,FALSE) -> 45754 | U97: =VLOOKUP(B97,'Detailed Update'!B:T,17,FALSE) -> 45715 | V97: =VLOOKUP(B97,'Detailed Update'!B:S,18,FALSE) -> 45807 | W97: =VLOOKUP(B97,'Detailed Update'!B:T,19,FALSE) -> 46149 | X97: =VLOOKUP(B97,'Detailed Update'!B:U,20,FALSE) -> FAC received
A98: 66 | B98: PE-260 | C98: =VLOOKUP(B98,'Detailed Update'!B:C,2,FALSE) -> Sanabel con.at Jeddah | D98: =VLOOKUP(B98,'Updated Progress % + TCC'!B:D,3,FALSE) -> Abdelazeem Morsy | E98: =VLOOKUP(B98,'Updated Progress % + TCC'!B:J,9,FALSE) -> Western | F98: =IF(M98>70.01%,"No","Yes") -> No | G98: No | H98: No | I98: No | K98: =VLOOKUP(B98,'Detailed Update'!B:D,3,FALSE) -> 44924 | L98: =VLOOKUP(B98,'Detailed Update'!B:I,4,FALSE) -> 1 | M98: =VLOOKUP(B98,'Detailed Update'!B:I,5,FALSE) -> 0.975 | N98: =M98-L98 -> -0.025 | O98: =VLOOKUP(B98,'Detailed Update'!B:I,6,FALSE) -> SEC | P98: =VLOOKUP(B98,'Detailed Update'!B:I,8,FALSE) -> Jeddah | Q98: Approved | R98: =VLOOKUP(B98,'Detailed Update'!B:T,11,FALSE) -> 45594 | S98: =VLOOKUP(B98,'Detailed Update'!B:T,12,FALSE) -> 45687 | T98: =VLOOKUP(B98,'Detailed Update'!B:T,13,FALSE) -> 45992 | U98: =VLOOKUP(B98,'Detailed Update'!B:T,17,FALSE) -> 45744 | V98: =VLOOKUP(B98,'Detailed Update'!B:S,18,FALSE) -> 45841 | W98: =VLOOKUP(B98,'Detailed Update'!B:T,19,FALSE) -> 46298 | X98: =VLOOKUP(B98,'Detailed Update'!B:U,20,FALSE) -> SAS Configuration and testing pending, due to AES team mobilization pending
A99: 67 | B99: PE-262 | C99: =VLOOKUP(B99,'Detailed Update'!B:C,2,FALSE) -> Reinf. of Thuwal Town KAUST 2 | D99: =VLOOKUP(B99,'Updated Progress % + TCC'!B:D,3,FALSE) -> Abdelazeem Morsy | E99: =VLOOKUP(B99,'Updated Progress % + TCC'!B:J,9,FALSE) -> Western | F99: =IF(M99>70.01%,"No","Yes") -> No | G99: No | H99: No | I99: No | K99: =VLOOKUP(B99,'Detailed Update'!B:D,3,FALSE) -> 44924 | L99: =VLOOKUP(B99,'Detailed Update'!B:I,4,FALSE) -> 1 | M99: =VLOOKUP(B99,'Detailed Update'!B:I,5,FALSE) -> 0.9696 | N99: =M99-L99 -> -0.0304 | O99: =VLOOKUP(B99,'Detailed Update'!B:I,6,FALSE) -> SEC | P99: =VLOOKUP(B99,'Detailed Update'!B:I,8,FALSE) -> Jeddah | Q99: Approved | R99: =VLOOKUP(B99,'Detailed Update'!B:T,11,FALSE) -> 45533 | S99: =VLOOKUP(B99,'Detailed Update'!B:T,12,FALSE) -> 45656 | T99: =VLOOKUP(B99,'Detailed Update'!B:T,13,FALSE) -> 45992 | U99: =VLOOKUP(B99,'Detailed Update'!B:T,17,FALSE) -> 45685 | V99: =VLOOKUP(B99,'Detailed Update'!B:S,18,FALSE) -> 45811 | W99: =VLOOKUP(B99,'Detailed Update'!B:T,19,FALSE) -> 46298 | X99: =VLOOKUP(B99,'Detailed Update'!B:U,20,FALSE) -> SAS Configuration and testing pending
A100: 68 | B100: PE-296 | C100: =VLOOKUP(B100,'Detailed Update'!B:C,2,FALSE) -> Waly Alahad-4 110/13.8KV SS | D100: =VLOOKUP(B100,'Updated Progress % + TCC'!B:D,3,FALSE) -> Moustafa Elkayyal | E100: =VLOOKUP(B100,'Updated Progress % + TCC'!B:J,9,FALSE) -> Western | F100: =IF(M100>70.01%,"No","Yes") -> No | G100: No | H100: No | I100: No | K100: =VLOOKUP(B100,'Detailed Update'!B:D,3,FALSE) -> 45218 | L100: =VLOOKUP(B100,'Detailed Update'!B:I,4,FALSE) -> 1 | M100: =VLOOKUP(B100,'Detailed Update'!B:I,5,FALSE) -> 0.9453 | N100: =M100-L100 -> -0.0547 | O100: =VLOOKUP(B100,'Detailed Update'!B:I,6,FALSE) -> SEC | P100: =VLOOKUP(B100,'Detailed Update'!B:I,8,FALSE) -> Makkah | Q100: N/A | R100: =VLOOKUP(B100,'Detailed Update'!B:T,11,FALSE) -> 45707 | S100: =VLOOKUP(B100,'Detailed Update'!B:T,12,FALSE) -> 45980 | T100: =VLOOKUP(B100,'Detailed Update'!B:T,13,FALSE) -> 45980 | U100: =VLOOKUP(B100,'Detailed Update'!B:T,17,FALSE) -> 45857 | V100: =VLOOKUP(B100,'Detailed Update'!B:S,18,FALSE) -> 46131 | W100: =VLOOKUP(B100,'Detailed Update'!B:T,19,FALSE) -> 46321 | X100: =VLOOKUP(B100,'Detailed Update'!B:U,20,FALSE) -> 1) Line readiness pending from SEC
A101: 69 | B101: PE-281 | C101: =VLOOKUP(B101,'Detailed Update'!B:C,2,FALSE) -> 110KV SS - KAEC-3 | D101: =VLOOKUP(B101,'Updated Progress % + TCC'!B:D,3,FALSE) -> Hossam Amin | E101: =VLOOKUP(B101,'Updated Progress % + TCC'!B:J,9,FALSE) -> Western | F101: =IF(M101>70.01%,"No","Yes") -> No | G101: No | H101: No | I101: No | K101: =VLOOKUP(B101,'Detailed Update'!B:D,3,FALSE) -> 45442 | L101: =VLOOKUP(B101,'Detailed Update'!B:I,4,FALSE) -> 1 | M101: =VLOOKUP(B101,'Detailed Update'!B:I,5,FALSE) -> 0.99 | N101: =M101-L101 -> -0.01 | O101: =VLOOKUP(B101,'Detailed Update'!B:I,6,FALSE) -> SEC | P101: =VLOOKUP(B101,'Detailed Update'!B:I,8,FALSE) -> Jeddah | Q101: N/A | R101: =VLOOKUP(B101,'Detailed Update'!B:T,11,FALSE) -> 45991 | S101: =VLOOKUP(B101,'Detailed Update'!B:T,12,FALSE) -> 45991 | T101: =VLOOKUP(B101,'Detailed Update'!B:T,13,FALSE) -> 45991 | U101: =VLOOKUP(B101,'Detailed Update'!B:T,17,FALSE) -> 46141 | V101: =VLOOKUP(B101,'Detailed Update'!B:S,18,FALSE) -> 46141 | W101: =VLOOKUP(B101,'Detailed Update'!B:T,19,FALSE) -> 46203 | X101: =VLOOKUP(B101,'Detailed Update'!B:U,20,FALSE) -> TCC, PAC Received. FAC Letter Submitted to Client
A102: 70 | B102: PE-185 | C102: =VLOOKUP(B102,'Detailed Update'!B:C,2,FALSE) -> NG Taif | D102: =VLOOKUP(B102,'Updated Progress % + TCC'!B:D,3,FALSE) -> Omar Samman | E102: =VLOOKUP(B102,'Updated Progress % + TCC'!B:J,9,FALSE) -> Western | F102: =IF(M102>70.01%,"No","Yes") -> No | G102: No | H102: No | I102: No | K102: =VLOOKUP(B102,'Detailed Update'!B:D,3,FALSE) -> 43156 | L102: =VLOOKUP(B102,'Detailed Update'!B:I,4,FALSE) -> 1 | M102: =VLOOKUP(B102,'Detailed Update'!B:I,5,FALSE) -> 0.9965 | N102: =M102-L102 -> -0.0035 | O102: =VLOOKUP(B102,'Detailed Update'!B:I,6,FALSE) -> NG | P102: =VLOOKUP(B102,'Detailed Update'!B:I,8,FALSE) -> Taif | Q102: Under Approval | R102: =VLOOKUP(B102,'Detailed Update'!B:T,11,FALSE) -> NA | S102: =VLOOKUP(B102,'Detailed Update'!B:T,12,FALSE) -> NA | T102: =VLOOKUP(B102,'Detailed Update'!B:T,13,FALSE) -> NA | U102: =VLOOKUP(B102,'Detailed Update'!B:T,17,FALSE) -> 44252 | V102: =VLOOKUP(B102,'Detailed Update'!B:S,18,FALSE) -> 46217 | W102: =VLOOKUP(B102,'Detailed Update'!B:T,19,FALSE) -> 46568 | X102: =VLOOKUP(B102,'Detailed Update'!B:U,20,FALSE) -> EOT: Contract amendment approved,PCC on 14th Jul 25, EOT-2 submitted on 4th Nov 25, with 8 months (PCC: 14th Mar 26), Under SEC approval 1) All cable ceiling end joints works replacing works in progress, expected compeltion by 30th May 26. 2) Remote end-1 final setting done, Remote end 2 final setting completion by 10th May. 3) HV Test and end to end test pending expected completion by 15th Jun and 30th Jun
A103: 71 | B103: PE-246 | C103: =VLOOKUP(B103,'Detailed Update'!B:C,2,FALSE) -> UM-AL-JOUD BSP | D103: =VLOOKUP(B103,'Updated Progress % + TCC'!B:D,3,FALSE) -> Bander Khalid Al Qalah | E103: =VLOOKUP(B103,'Updated Progress % + TCC'!B:J,9,FALSE) -> Western | F103: =IF(M103>70.01%,"No","Yes") -> No | G103: No | H103: No | I103: No | K103: =VLOOKUP(B103,'Detailed Update'!B:D,3,FALSE) -> 44812 | L103: =VLOOKUP(B103,'Detailed Update'!B:I,4,FALSE) -> 1 | M103: =VLOOKUP(B103,'Detailed Update'!B:I,5,FALSE) -> 0.8895 | N103: =M103-L103 -> -0.1105 | O103: =VLOOKUP(B103,'Detailed Update'!B:I,6,FALSE) -> SEC | P103: =VLOOKUP(B103,'Detailed Update'!B:I,8,FALSE) -> Makkah | Q103: Under Approval | R103: =VLOOKUP(B103,'Detailed Update'!B:T,11,FALSE) -> 45238 | S103: =VLOOKUP(B103,'Detailed Update'!B:T,12,FALSE) -> 45695 | T103: =VLOOKUP(B103,'Detailed Update'!B:T,13,FALSE) -> 46264 | U103: =VLOOKUP(B103,'Detailed Update'!B:T,17,FALSE) -> 45390 | V103: =VLOOKUP(B103,'Detailed Update'!B:S,18,FALSE) -> 45845 | W103: =VLOOKUP(B103,'Detailed Update'!B:T,19,FALSE) -> 46417 | X103: =VLOOKUP(B103,'Detailed Update'!B:U,20,FALSE) -> 1) EOT-2 submitted to client on 8th Jan 25, Revised TCC date confirmation is pending by SEC (Due to no clarity in readiness of remote end i.e. Fahya SS). EOT-2 resubmitted on 14-June-26 for Revised TCC on 31-July-27. Once approved, TCC letter will be submitted. 2) Remote end protection desing approval pending from SEC. Holding the procurement of loose material & modification work at remote end. 3) Protection scope for Fahya Substation is unknown: Due to which Design submission and approval for modification and procuring loose material is still not finalized 4) Restriction to work inside Rusifah Substation: No confirmation on Panel Installation is provided in Rusifah Substation due to limitations of space. Also, FOC cable pulling & termination inside SS is on hold. 5) Testing of Fiber & High Voltage cable is required to start. Waiting for SEC witness. 6) Shut down from SEC is required for Replacing Relay from Rushifah to Umaljoud. Still no clarity on shutdown also.
A104: 72 | B104: PE-263 | C104: =VLOOKUP(B104,'Detailed Update'!B:C,2,FALSE) -> MOWAIH PV 380/110V BSP | D104: =VLOOKUP(B104,'Updated Progress % + TCC'!B:D,3,FALSE) -> Mohammed Fathy | E104: =VLOOKUP(B104,'Updated Progress % + TCC'!B:J,9,FALSE) -> Western | F104: =IF(M104>70.01%,"No","Yes") -> No | G104: No | H104: No | I104: No | K104: =VLOOKUP(B104,'Detailed Update'!B:D,3,FALSE) -> 45014 | L104: =VLOOKUP(B104,'Detailed Update'!B:I,4,FALSE) -> 1 | M104: =VLOOKUP(B104,'Detailed Update'!B:I,5,FALSE) -> 0.99 | N104: =M104-L104 -> -0.01 | O104: =VLOOKUP(B104,'Detailed Update'!B:I,6,FALSE) -> SEC | P104: =VLOOKUP(B104,'Detailed Update'!B:I,8,FALSE) -> Taif | Q104: Under Approval | R104: =VLOOKUP(B104,'Detailed Update'!B:T,11,FALSE) -> 45745 | S104: =VLOOKUP(B104,'Detailed Update'!B:T,12,FALSE) -> 45961 | T104: =VLOOKUP(B104,'Detailed Update'!B:T,13,FALSE) -> 46028 | U104: =VLOOKUP(B104,'Detailed Update'!B:T,17,FALSE) -> 45897 | V104: =VLOOKUP(B104,'Detailed Update'!B:S,18,FALSE) -> 46081 | W104: =VLOOKUP(B104,'Detailed Update'!B:T,19,FALSE) -> 46264 | X104: =VLOOKUP(B104,'Detailed Update'!B:U,20,FALSE) -> EOT is submitted with TCC and was approved on 21st Apr 26 Energization done, and TCC was received on 21st Apr 26
A105: 73 | B105: PE-265 | C105: =VLOOKUP(B105,'Detailed Update'!B:C,2,FALSE) -> 110/33 KV ALMAHANI S/S IN TAIF | D105: =VLOOKUP(B105,'Updated Progress % + TCC'!B:D,3,FALSE) -> Mudasir Sheikh | E105: =VLOOKUP(B105,'Updated Progress % + TCC'!B:J,9,FALSE) -> Western | F105: =IF(M105>70.01%,"No","Yes") -> No | G105: No | H105: No | I105: No | K105: =VLOOKUP(B105,'Detailed Update'!B:D,3,FALSE) -> 45060 | L105: =VLOOKUP(B105,'Detailed Update'!B:I,4,FALSE) -> 1 | M105: =VLOOKUP(B105,'Detailed Update'!B:I,5,FALSE) -> 0.923 | N105: =M105-L105 -> -0.077 | O105: =VLOOKUP(B105,'Detailed Update'!B:I,6,FALSE) -> SEC | P105: =VLOOKUP(B105,'Detailed Update'!B:I,8,FALSE) -> Taif | Q105: Under Approval | R105: =VLOOKUP(B105,'Detailed Update'!B:T,11,FALSE) -> 45671 | S105: =VLOOKUP(B105,'Detailed Update'!B:T,12,FALSE) -> 45991 | T105: =VLOOKUP(B105,'Detailed Update'!B:T,13,FALSE) -> 46325 | U105: =VLOOKUP(B105,'Detailed Update'!B:T,17,FALSE) -> 45822 | V105: =VLOOKUP(B105,'Detailed Update'!B:S,18,FALSE) -> 46111 | W105: =VLOOKUP(B105,'Detailed Update'!B:T,19,FALSE) -> 46446 | X105: =VLOOKUP(B105,'Detailed Update'!B:U,20,FALSE) -> EOT: EOT submitted TCC upto 30-Nov-26. Under SEC approval. 1) delay in final setting approval for SWGR and Capacitor bank and line protection delaying open loop Tests 2) Delayed HV kit for GIS HV test (was scheduled by Jul-26) now rescheduled to 20-Aug-26 3) Delayed installations of the (HV Terminations, CSE, MV Terminations) pending subcontractor. (PO Under finalization with SCD) 4) Delayed open loop tests for the major equipment due to non-availability of SAS engineer. (Will be mobilized after Approval of final settings) 5) OHTL Line readinees (AL-mahani to MAHD), No clarity on the completion by other contractor.
A106: 74 | B106: PE-266 | C106: =VLOOKUP(B106,'Detailed Update'!B:C,2,FALSE) -> EXT. OF THE EXIS. THAGEF &ADAM | D106: =VLOOKUP(B106,'Updated Progress % + TCC'!B:D,3,FALSE) -> Sohaib Afdal | E106: =VLOOKUP(B106,'Updated Progress % + TCC'!B:J,9,FALSE) -> Western | F106: =IF(M106>70.01%,"No","Yes") -> No | G106: No | H106: No | I106: No | K106: =VLOOKUP(B106,'Detailed Update'!B:D,3,FALSE) -> 45060 | L106: =VLOOKUP(B106,'Detailed Update'!B:I,4,FALSE) -> 1 | M106: =VLOOKUP(B106,'Detailed Update'!B:I,5,FALSE) -> 0.8663 | N106: =M106-L106 -> -0.1337 | O106: =VLOOKUP(B106,'Detailed Update'!B:I,6,FALSE) -> SEC | P106: =VLOOKUP(B106,'Detailed Update'!B:I,8,FALSE) -> Taif | Q106: Under Approval | R106: =VLOOKUP(B106,'Detailed Update'!B:T,11,FALSE) -> 45671 | S106: =VLOOKUP(B106,'Detailed Update'!B:T,12,FALSE) -> 45944 | T106: =VLOOKUP(B106,'Detailed Update'!B:T,13,FALSE) -> 46356 | U106: =VLOOKUP(B106,'Detailed Update'!B:T,17,FALSE) -> 45822 | V106: =VLOOKUP(B106,'Detailed Update'!B:S,18,FALSE) -> 46067 | W106: =VLOOKUP(B106,'Detailed Update'!B:T,19,FALSE) -> 46476 | X106: =VLOOKUP(B106,'Detailed Update'!B:U,20,FALSE) -> EOT: EOT-2 submitted with TCC date of 27-Jul-26. (Under SEC Approval) 1) AES Control panel (Mosaic and Annciator) detail design still under approval & no clarity on FAT date. (expected by Sep-26). 2) Missing BCU units for ADAM LCC (Hyundai), Provided by AES (Purchased from SIEMENS) Delayed since Feb-26, Latest provided date by AES is by Oct-26 3) Loose materials are required from AES for Protection, LCC Panels. To be compatible with existing systems and proceed commissioning activities 4) Delayed delivery of the PC Workstation (EWS) and the PO is still under Finalization with SCD 4) No Clarity of OHTL Line readiness.
...

Sheet Detailed Update
B1: Project Code | C1: Project Name | D1: Start Date | E1: Planned % | F1: Actual % | G1: Client | H1: Region | I1: City | J1: Latest EOT approved Date | K1: EOT STATUS (Submitted/Approved/Under Approval/ N/A) | M1: TCC | P1: PAC | R1: FAC / Overall Project | U1: Remarks
D2: Start Date | L2: TCC | M2: Revised Date | N2: Forecast Date | O2: Contract Date | P2: Revised Date | Q2: Forecast Date | R2: Contract Date | S2: Revised Date | T2: Forecast Date
C3: CENTRAL REGION UNIT
A4: 1 | B4: PE-215 | C4: SMP - O&M 3 Yrs | D4: 44652 | E4: 1 | F4: 1 | G4: SEC | H4: Central | I4: Riyadh | K4: Approved | L4: 45442 | M4: 45812 | N4: 45812 | O4: 45442 | P4: 45812 | Q4: 45812 | R4: 45442 | S4: 45812 | T4: 45812 | U4: All certification Received
A5: =A4+1 -> 2 | B5: PE-226 | C5: KHASM-AL-AAN BSP | D5: 44350 | E5: 1 | F5: 0.863 | G5: SEC | H5: Central | I5: Riyadh | J5: 45386 | K5: Approved | L5: 44960 | M5: 45657 | N5: 46411 | O5: 45049 | P5: 45716 | Q5: =N5+60 -> 46471 | R5: 45141 | S5: 45808 | T5: =Q5+(S5-P5) -> 46563 | U5: Partial TCC Received | Project on Hold
A6: =A5+1 -> 3 | B6: PM-223 | C6: GASCO - 2 | D6: 44368 | E6: 1 | F6: 0.9991 | G6: GASCO | H6: Central | I6: Riyadh | K6: Approved | L6: 45136 | M6: 45747 | N6: 45961 | O6: 45136 | P6: 45747 | Q6: 45961 | R6: 45136 | S6: 45747 | T6: 45961 | U6: Initial Handing over received
A7: =A6+1 -> 4 | B7: PE-228 | C7: SVC QASSIM -2 | D7: 44444 | E7: 1 | F7: 0.9928 | G7: SEC | H7: Central | I7: Riyadh | K7: Approved | L7: 45235 | M7: 45733 | N7: 45733 | O7: 45296 | P7: 45794 | Q7: 46203 | R7: 45356 | S7: 45855 | T7: =Q7+(S7-P7) -> 46264 | U7: TCC Received.
A8: =A7+1 -> 5 | B8: PE-233 | C8: Tabarjal 380KV BSP Expn. | D8: 44542 | E8: 1 | F8: 0.99 | G8: SEC | H8: Central | I8: Riyadh | K8: Approved | L8: 45272 | M8: 46021 | N8: 46233 | O8: 45334 | P8: 46081 | Q8: 46295 | R8: 45424 | S8: 46172 | T8: =Q8+(S8-P8) -> 46386 | U8: Partial TCC received on 16-Jan-24
A9: =A8+1 -> 6 | B9: PE-245 | C9: Hail OHTL | D9: 44788 | E9: 1 | F9: 0.9612 | G9: SEC | H9: Central | I9: Riyadh | J9: 45476 | K9: Approved | L9: 45427 | M9: 45656 | N9: 46193 | O9: 45488 | P9: 45716 | Q9: =N9+60 -> 46253 | R9: 45580 | S9: 45804 | T9: =Q9+(S9-P9) -> 46341 | U9: One line Energizaed. Another line by 20-Jun-26. Change Order approval is critical
A10: =A9+1 -> 7 | B10: PE-247 | C10: RIYADH SEDRA-2 | D10: 44833 | E10: 1 | F10: 0.991 | G10: Roshn | H10: Central | I10: Riyadh | K10: Under Approval | L10: 45538 | M10: 45538 | N10: 45920 | O10: 45568 | P10: 45568 | Q10: 46233 | R10: 45599 | S10: 45599 | T10: =Q10+(S10-P10) -> 46264 | U10: Partial TCC received & 90% invoice approved
A11: =A10+1 -> 8 | B11: PE-248 | C11: PP10 Conv. | D11: 44847 | E11: 1 | F11: 0.9576 | G11: SEC | H11: Central | I11: Riyadh | J11: 45553 | K11: Approved | L11: 45517 | M11: 46018 | N11: 46263 | O11: 45609 | P11: 46112 | Q11: 46355 | R11: 45974 | S11: 46477 | T11: =Q11+(S11-P11) -> 46720 | U11: TCC milestone achieved. Certification not receied. Punchlist Clearance is critical
A12: =A11+1 -> 9 | B12: PE-255 | C12: 380kv D/C OHTL LILO SAAD OHTL | D12: 44857 | E12: 0.8998 | F12: 0.7518 | G12: SEC | H12: Central | I12: Riyadh | J12: 45449 | K12: Approved | L12: 45283 | M12: 45813 | N12: 46386 | O12: 45374 | P12: 45905 | Q12: =N12+(P12-M12) -> 46478 | R12: 45466 | S12: 45996 | T12: =Q12+(S12-P12) -> 46569 | U12: 1. Amendment for New circuit Arrangement at Tapping Point . 2. Outage requirements 3. Hardware fittings material for re-route portion
A13: =A12+1 -> 10 | B13: PE-256 | C13: Sudair PV 380KV BSP | D13: 44867 | E13: 1 | F13: 0.7877 | G13: SEC | H13: Central | I13: Riyadh | K13: Under Approval | L13: 45537 | M13: 45537 | N13: 46325 | O13: 45598 | P13: 45598 | Q13: =N13+(P13-M13) -> 46386 | R13: 45690 | S13: 45690 | T13: =Q13+(S13-P13) -> 46478 | U13: SS portion energized. Delay in Receiving Permit UGC works and inside PP9 works (MTO,LOA& ARAMCO Permits)
A14: =A13+1 -> 11 | B14: PE-259 | C14: WAAD AL SHAMAAL 380KV BSP | D14: 44871 | E14: 1 | F14: 0.9693 | G14: SEC | H14: Central | I14: Riyadh | K14: Approved | L14: 45611 | M14: 45807 | N14: 46356 | O14: 45672 | P14: 45868 | Q14: =N14+(P14-M14) -> 46417 | R14: 45762 | S14: 45960 | T14: =Q14+(S14-P14) -> 46509 | U14: Paritally Energized on 09-Feb-26 | Delay in receiving outage to enrgize CKT 2 Wind to Waad Alshamaal & Wind to TABARJAL energization (expected by Oct 26)
A15: =A14+1 -> 12 | B15: PE-264 | C15: TABARJAL-B 13213.8 KV S/S IN JOUF | D15: 45063 | E15: 1 | F15: 0.9918 | G15: SEC | H15: Central | I15: Riyadh | K15: Approved | L15: 45732 | M15: 45838 | N15: 46202 | O15: 45793 | P15: 45899 | Q15: =N15+(P15-M15) -> 46263 | R15: 45885 | S15: 45991 | T15: =Q15+(S15-P15) -> 46355 | U15: 1.Total of four circuits are planned; two are scheduled for energization by June 2026. 2.SE confirmation is still pending for the remaining two circuits.
A16: =A15+1 -> 13 | B16: PE-271 | C16: AL-DAR AL-BAIDHA 132/13.8KV SUB | D16: 45120 | E16: 1 | F16: 0.985 | G16: SEC | H16: Central | I16: Riyadh | J16: 46039 | K16: Approved | L16: 45608 | M16: 46081 | N16: 46098 | O16: 45669 | P16: 46140 | Q16: 46325 | R16: 45759 | S16: 46231 | T16: =Q16+(S16-P16) -> 46416 | U16: Energized on 17-Mar-26 | Other Circuit depends on Outage | Expected - 31-Oct-26
A17: =A16+1 -> 14 | B17: PE-272 | C17: AL-MUNSIYAH 132/13.8KV SUB # 8273 | D17: 45120 | E17: 1 | F17: 0.9613 | G17: SEC | H17: Central | I17: Riyadh | K17: Under Approval | L17: 45609 | M17: 45609 | N17: 46272 | O17: 45670 | P17: 45670 | Q17: =N17+(P17-M17) -> 46333 | R17: 45760 | S17: 45760 | T17: =Q17+(S17-P17) -> 46423 | U17: One Circuit Energized. Other Circuit depends on Outage | Expected - 31-Oct-26
A18: =A17+1 -> 15 | B18: PE-273 | C18: ALMANFOHA 132/13.8KV SUB # 8138 | D18: 45119 | E18: 1 | F18: 0.986 | G18: SEC | H18: Central | I18: Riyadh | K18: Approved | L18: 45608 | M18: 45991 | N18: 45991 | O18: 45669 | P18: 46052 | Q18: 46325 | R18: 45759 | S18: 46142 | T18: =Q18+(S18-P18) -> 46415 | U18: One Circuit Energized on 21-Dec-25
A19: =A18+1 -> 16 | B19: PE-274 | C19: NASIRIYAH 132/13.8KV SUB # 8154 | D19: 45119 | E19: 1 | F19: 0.927 | G19: SEC | H19: Central | I19: Riyadh | K19: Approved | L19: 45608 | M19: 46034 | N19: 46022 | O19: 45669 | P19: 46093 | Q19: 46203 | R19: 45759 | S19: 46185 | T19: =Q19+(S19-P19) -> 46295 | U19: One Energized on 11-Feb-26. TCC received with dated 31-Dec-2025
A20: =A19+1 -> 17 | B20: PE-275 | C20: 380kV Diriyah Gate-2 BSP # 9080 | D20: 45246 | E20: 0.5084 | F20: 0.4512 | G20: SEC | H20: Central | I20: Riyadh | K20: Under Approval | L20: 45977 | M20: 46490 | N20: 46547 | O20: 46038 | P20: 46550 | Q20: =N20+(P20-M20) -> 46607 | R20: 46128 | S20: 46641 | T20: =Q20+(S20-P20) -> 46698 | U20: Progress based on Internal Baseline. 1-Delay in approval of water proofing VO & removal of loose material, which affects the construction works. 2- Negative Cash flow. 3-Claim Approval 201 Mn for prolongation & inflation costs. 4- Delivery for disconnector switch expected to be delayed.
A21: =A20+1 -> 18 | B21: PE-276 | C21: SHARAFIYAH 380 KV SS | D21: 45139 | E21: 1 | F21: 0.9378 | G21: SEC | H21: Central | I21: Riyadh | K21: Under Approval | L21: 45689 | M21: 45689 | N21: 46183 | O21: 45748 | P21: 45748 | Q21: =N21+(P21-M21) -> 46242 | R21: 45839 | S21: 45839 | T21: =Q21+(S21-P21) -> 46333 | U21: Partially Energized. 1.Taihan - Oil Joints 2.Design Approval - 6 Remote end ( 132 kV) 3.Gantry Foundation for Existing Substation 4.Unclear Shutdown schedule for Power and Communication link with all remote ends 5. Delay in Micro Trenching of FOC 25km
A22: =A21+1 -> 19 | B22: PE-279 | C22: AL-NAZEEM 132/13.8KV SS # 8271 | D22: 45131 | E22: 1 | F22: 0.9085 | G22: SEC | H22: Central | I22: Riyadh | K22: Approved | L22: 45619 | M22: 45831 | N22: 46387 | O22: 45680 | P22: 45892 | Q22: =N22+(P22-M22) -> 46448 | R22: 45770 | S22: 45984 | T22: =Q22+(S22-P22) -> 46540 | U22: Commissioing on Hold due to non-readiness of UG Contractor
A23: =A22+1 -> 20 | B23: PE-299 | C23: Reinf of 132KV Network of Baqaa | D23: 45238 | E23: 0.9992 | F23: 0.9358 | G23: SEC | H23: Central | I23: Riyadh | J23: 45931 | K23: Approved | L23: 45784 | M23: 45981 | N23: 46326 | O23: 45876 | P23: 46073 | Q23: =N23+(P23-M23) -> 46418 | R23: 45937 | S23: 46132 | T23: =Q23+(S23-P23) -> 46477 | U23: 1.OHTL S/C & D/C crossing - Delay in HOT permits 2.Cutting point outage at TEE OFF location. 3.ERS System & TEE- OFF Tower Installation 4.Design Approval of Flood Protection
A24: =A23+1 -> 21 | B24: PE-300 | C24: 300 MVAR STATCOM | D24: 45357 | E24: 0.7928 | F24: 0.6916 | G24: SEC | H24: Central | I24: Riyadh | J24: 46127 | K24: Under Approval | L24: 46087 | M24: 46271 | N24: 46315 | O24: 46148 | P24: 46332 | Q24: =N24+(P24-M24) -> 46376 | R24: 46240 | S24: 46059 | T24: =Q24+(S24-P24) -> 46103 | U24: 1.Delay in delivery of AES scope material. (delay in these materials ,impact the project completion ) 2.Delay in 380 kv insulator (Lapp) 3.New fire pump-Delivery (change order), 4.Delay in delivery of MV grounding transformer
A25: =A24+1 -> 22 | B25: PE-306 | C25: NEW AL-ARED 380/132KV BSP | D25: 45218 | E25: 1 | F25: 0.9468 | G25: SEC | H25: Central | I25: Riyadh | J25: 45963 | K25: Under Approval | L25: 45766 | M25: 45888 | N25: 46203 | O25: 45829 | P25: 45949 | Q25: =N25+(P25-M25) -> 46264 | R25: 45919 | S25: 46041 | T25: =Q25+(S25-P25) -> 46356 | U25: 1.Slow Punch list - Transformers ,GIS, AES 2.Delay in SEC UG Cable Vendor - New Line( Circuits 3 )
A26: =A25+1 -> 23 | B26: PE-309 | C26: Reliablity Enh.for SS of 9011 in Sudair | D26: 46015 | E26: 0.4504 | F26: 0.2189 | G26: SEC | H26: Central | I26: Riyadh | K26: N/A | L26: 46349 | M26: 46349 | N26: 46498 | O26: 46410 | P26: 46410 | Q26: =N26+(P26-M26) -> 46559 | R26: 46500 | S26: 46500 | T26: =Q26+(S26-P26) -> 46649 | U26: Current issues 1.Delay in Plan & Profile - OHTL 2.Delay in Plan & Profile - UG Cable ( T- off Tower Location) 3.Delay in SE supply GIS Bays 4.Delay in Material :- Tower, Hardware, Insulator 5. Delay in providing existing Design : Remote End, U/G 8500 to 8521, Basement & Sleeves Details, Telecom Room, Control Room Layouts 6.Delay in Mobilization of Project Team OHTL Site Engr & Project Engr, QA & QC Civil & Electrical 7. Unclear Shutdown for Project
A27: =A26+1 -> 24 | B27: PE-310 | C27: Al Shifa Housing 132/13.8KV SS | D27: 45313 | E27: 0.946 | F27: 0.8692 | G27: SEC | H27: Central | I27: Riyadh | J27: 46049 | K27: Approved | L27: 45983 | M27: 46194 | N27: 46251 | O27: 46043 | P27: 46255 | Q27: =N27+(P27-M27) -> 46312 | R27: 46133 | S27: 46347 | T27: =Q27+(S27-P27) -> 46404 | U27: 1.Incomplete HV underground cable works under another contractor’s scope are impacting the substation energization activities. 2.STATCOM PQS approval remains pending with SEC/vendor, affecting material delivery and subsequent installation. 3.Delay in remote end (8131) works due to pending C1 work permit
A28: =A27+1 -> 25 | B28: PE-326 | C28: Shaqra Wind 380/132kV SS | D28: 45589 | E28: 0.9675 | F28: 0.6877 | G28: SEC | H28: Central | I28: Riyadh | K28: Under Approval | L28: 46165 | M28: 46165 | N28: 46387 | O28: 46226 | P28: 46226 | Q28: =N28+(P28-M28) -> 46448 | R28: 46318 | S28: 46318 | T28: =Q28+(S28-P28) -> 46540 | U28: 1-Delay in the delivery of 132kV and 380kV GIB and Hybrid GIS (SEC Direct purchase) beyond the scheduled dates, where the original plan was December 2025; however, only the 132kV GIB was delivered in end of May 2026, while the 380kV GIB and Hybrid GIS are still pending. 2-Delay in the supply of AC and DC panels from AES up to date. 3- Delay in obtaining ITP approvals for DSM and TFR systems AES prequalification to perform the FAT in AES factory. 4-Change order confirmation for the additional scope , which holding following activities (Civil work for Search facilities - Guard house - security building and along with all septic tank and water connections , HCIS stage 3 finalization and approval , Procurement of all electrical , mechanical , security material related to this pending . 5-Delay in the approval of firefighting system designs due to changing multiple changes in the review process from SEC and adding new comments with each revision. 6- After approval of lightening panels design (MS Hawaa ) SEC insist to change the manufactural to new alternate as (MS hawaa )is currently suspended in the system 7- Confirmation of EOT which submitted 9-Apr-26.
A29: =A28+1 -> 26 | B29: PE-335 | C29: Battery Energy (BESS) - Qaisumah | D29: 45642 | E29: 1 | F29: 0.9563 | G29: SEC | H29: Central | I29: Riyadh | K29: N/A | L29: 46158 | M29: 46158 | N29: 46153 | O29: 46219 | P29: 46219 | Q29: =N29+(P29-M29) -> 46214 | R29: 46311 | S29: 46311 | T29: =Q29+(S29-P29) -> 46306 | U29: Energized.
A30: =A29+1 -> 27 | B30: PE-336 | C30: Battery Energy (BESS) - Dawadmi | D30: 45642 | E30: 1 | F30: 0.9766 | G30: SEC | H30: Central | I30: Riyadh | K30: N/A | L30: 46158 | M30: 46158 | N30: 46152 | O30: 46219 | P30: 46219 | Q30: =N30+(P30-M30) -> 46213 | R30: 46311 | S30: 46311 | T30: =Q30+(S30-P30) -> 46305 | U30: Energized.
A31: =A30+1 -> 28 | B31: PE-337 | C31: Battery Energy (BESS) - Airport | D31: 45642 | E31: 1 | F31: 0.9883 | G31: SEC | H31: Central | I31: Riyadh | K31: N/A | L31: 46158 | M31: 46158 | N31: 46148 | O31: 46219 | P31: 46219 | Q31: =N31+(P31-M31) -> 46209 | R31: 46311 | S31: 46311 | T31: =Q31+(S31-P31) -> 46301 | U31: Energized.
A32: =A31+1 -> 29 | B32: PE-339 | C32: Battery Energy (BESS) - Jouf | D32: 45642 | E32: 1 | F32: 0.9862 | G32: SEC | H32: Central | I32: Jouf | K32: N/A | L32: 46158 | M32: 46158 | N32: 46158 | O32: 46219 | P32: 46219 | Q32: =N32+(P32-M32) -> 46219 | R32: 46311 | S32: 46311 | T32: =Q32+(S32-P32) -> 46311 | U32: Energized.
A33: =A32+1 -> 30 | B33: PE-348 | C33: Construction of Hail-2 Substation for BESS | D33: 45841 | E33: 0.8873 | F33: 0.4661 | G33: SEC | H33: Central | I33: Hail | K33: N/A | L33: 46176 | M33: 46176 | N33: 46280 | O33: 46237 | P33: 46237 | Q33: =N33+(P33-M33) -> 46341 | R33: 46329 | S33: 46329 | T33: =Q33+(S33-P33) -> 46433 | U33: 1-Delay in approving critical designs such as FF designs, & Remote end AMI , with some submittals open for more than 3 months 2- Delay in design inputs has delayed grid studies submission & approval cycles 3- Delay in Alfanar equipment delivery: - Auxiliary transformer - AC & DC Panels - TFR & DSM - Remote End AMI & Metering 4- Delay in BESS Supplier fire fighting protion delivery (BESS gas pipes) 5- Delay in Firefighting pumps delivery 6- Delay in surge arrestors, and post insulators delivery 7- Delay in 33Kv SWGR termination kits delivery 8- Delay in HGIS Delivery: 1 out of 2 Bays delivered 9- Delay in UPS delivery
A34: =A33+1 -> 31 | B34: PE-353 | C34: Conv of Riyadh CC PP10 - Phase 2 | D34: 45785 | E34: 0.4019 | F34: 0.1642 | G34: SEC | H34: Central | I34: Riyadh | K34: N/A | L34: 46515 | M34: 46515 | N34: 46765 | O34: 46546 | P34: 46546 | Q34: =N34+(P34-M34) -> 46796 | R34: 46912 | S34: 46912 | T34: =Q34+(S34-P34) -> 47162 | U34: 1.Base Design Approval : Disagreement with SE on interpretation of the Contract. 2.Engineering Review Cycle Delays : Agreed timelines for review are not being adhered. 3.Delivery durations for critical (LLIs) exceed the Contractual timeline, creating a significant risk to meeting the contractual milestones. 4.Accelerated Dec 2026 completion requested by SE for GT 1st Fire. 5.Site Access Gate Permits & Work Permit issues.
A35: =A34+1 -> 32 | B35: PE-356 | C35: 380KV OHTL | MAWQAQ BSP CONNECTION | D35: 45897 | E35: 0.5331 | F35: 0.1606 | G35: SEC | H35: Central | I35: Riyadh | K35: Under Approval | L35: 46446 | M35: 46446 | N35: 46723 | O35: 46504 | P35: 46504 | Q35: 46783 | R35: 46595 | S35: 46595 | T35: 46873 | U35: 1) Revised Route with additional change order.Revised Route under approval 2) Finalization of the route is pending for the portion that falls under KSRR. 3) Cost and time impact resulting from the increased transmission line route length and associated scope changes. 4) Delay in approval of plan and profile
A36: =A35+1 -> 33 | B36: PE-360 | C36: SMP|OPERATION & PROF. SERVICES (HES&HHU) | D36: 45853 | E36: 0.8333 | F36: 0.8333 | G36: SEC | H36: Central | I36: Riyadh | K36: N/A | L36: 46217 | M36: 46309 | N36: 46309 | O36: 46217 | P36: 46309 | Q36: =N36+(P36-M36) -> 46309 | R36: 46217 | S36: 46309 | T36: =Q36+(S36-P36) -> 46309 | U36: Extension of 1 quarter received
A37: =A36+1 -> 34 | B37: PE-362 | C37: 132KV SS |CONST. SPORTS BOULEVARD-RIYADH | D37: 45882 | E37: 0.3324 | F37: 0.2194 | G37: SEC | H37: Central | I37: Riyadh | K37: N/A | L37: 46429 | M37: 46429 | N37: 46660 | O37: 46488 | P37: 46488 | Q37: =N37+(P37-M37) -> 46719 | R37: 46579 | S37: 46579 | T37: =Q37+(S37-P37) -> 46810 | U37: Delay in Site Handing Over. Not handed over yet
A38: =A37+1 -> 35 | B38: PE-316 | C38: HVDC-1 | COA-WOA | RUH-9022 | D38: 45470 | E38: 0.7932 | F38: 0.6971 | G38: SEC | H38: Central | I38: Riyadh | K38: N/A | L38: 46387 | M38: 46387 | N38: 46418 | O38: 46446 | P38: 46446 | Q38: =N38+(P38-M38) -> 46477 | R38: 46538 | S38: 46538 | T38: =Q38+(S38-P38) -> 46569 | U38: -
A39: =A38+1 -> 36 | B39: PE-317 | C39: HVDC-2 | COA-SOA | RUH-9041 | D39: 45470 | E39: 0.8948 | F39: 0.7873 | G39: SEC | H39: Central | I39: Riyadh | K39: N/A | L39: 46387 | M39: 46387 | N39: 46446 | O39: 46446 | P39: 46446 | Q39: =N39+(P39-M39) -> 46505 | R39: 46538 | S39: 46538 | T39: =Q39+(S39-P39) -> 46597 | U39: -
A40: =A39+1 -> 37 | B40: PE-363 | C40: SULYBIAH SS 8823 132/33KV | D40: 46047 | E40: 0.0505 | F40: 0.0342 | G40: SEC | H40: Central | I40: Qassim | K40: N/A | L40: 46593 | M40: 46593 | N40: 46673 | O40: 46655 | P40: 46655 | Q40: =N40+(P40-M40) -> 46735 | R40: 46746 | S40: 46746 | T40: =Q40+(S40-P40) -> 46826 | U40: 1. Delay in Receiving Design for GIS Package Supplied by SEC Vendor 2. Delay in soil investigation activities due to one corner of the substation located on farmland 3. Terminal compound 1 location changed 4. Repetition of soil investigation activities due to the client's rejection of the proposed vendor
A41: =A40+1 -> 38 | B41: PE-372 | C41: AL-DWADMI SS 8618 132/33KV | D41: 46036 | E41: 0.0858 | F41: 0.0579 | G41: SEC | H41: Central | I41: Riyadh | K41: N/A | L41: 46580 | M41: 46580 | N41: 46660 | O41: 46642 | P41: 46642 | Q41: =N41+(P41-M41) -> 46722 | R41: 46733 | S41: 46733 | T41: =Q41+(S41-P41) -> 46813 | U41: 1. Delay in approval of GEL 2. Delay of Receiving Design for GIS Package Supplied by SEC (GIS Delivery delayed ) 3. Delay in municipality approval 4. Delay in Issuance Of P.O Transformer
A42: =A41+1 -> 39 | B42: PE-394 | C42: NEW AL-GHADIR SS#8237 132/33K | D42: 46043 | E42: 0.0739 | F42: 0.0563 | G42: SEC | H42: Central | I42: Riyadh | K42: N/A | L42: 46651 | M42: 46651 | N42: 46681 | O42: 46712 | P42: 46712 | Q42: =N42+(P42-M42) -> 46742 | R42: 46804 | S42: 46804 | T42: =Q42+(S42-P42) -> 46834 | U42: -
A43: =A42+1 -> 40 | B43: PE-395 | C43: New Al- Wadi 132/13.8Kv substation #8224 and its Connection in Riyadh City | D43: 46064 | E43: 0.0236 | F43: 0.039 | G43: SEC-COA | H43: Central | I43: Riyadh | K43: N/A | L43: 46671 | M43: 46671 | N43: 46695 | O43: 46732 | P43: 46732 | Q43: =N43+(P43-M43) -> 46756 | R43: 46823 | S43: 46823 | T43: =Q43+(S43-P43) -> 46847 | U43: 1- Civil construction and related engineering/design activities suspended due to site cavities discovered after Soil investigation report. 2- Under Ground cables radar scanning & cable route layout submission.
B44: PE-389 | C44: CONSTRUCTION OF AL-MAJMAA HOUSING 132/13.8KV SUBSTATION# 8534 | D44: 46142 | E44: 0.0335 | F44: 0.0145 | G44: SE | H44: Central | I44: Riyadh | K44: N/A | L44: 46751 | M44: 46751 | N44: 46802 | O44: 46446 | P44: 46812 | Q44: =N44+(P44-M44) -> 46863 | R44: 46903 | S44: 46903 | T44: =Q44+(S44-P44) -> 46954 | U44: 1-Soil investigation not started due to the final approval of Borehole location submittal 2- GIS design not finilzed yet with the designer
B45: PE-381 | C45: CONSTRUCTION OF 132/13.8KV ALARIDH-3 SUBSTATION # 8363 IN RIYADH CITY
B46: PE-373 | C46: Replacement of the existing 132/33/13.8kV Al-Githamiyah S/S # 8903 by Constructing of new 132/33/13.8kV Al-Githamiyah S/S # 8933-Hail Area | D46: 46097 | E46: 0.1281 | F46: 0.0517 | G46: SE | H46: Central | I46: Hail | K46: N/A | L46: 46584 | M46: 46584 | N46: 46669 | O46: 46646 | P46: 46646 | Q46: 46732 | R46: 46733 | S46: 46733 | T46: 46823 | U46: 1-MISSING C1 & C2 CERTIFIED EMPLOYEE, WHICH AFFECTS SOIL INVESTIGATION WORKS. 2-DELAY IN REMOVAL OBSTACLES(LIVE TRANSFORMER & UNDER GROUND CABLES PASSING BY THE MAIN BUILDING) BY SE.
B47: PE-393 | C47: CONSTRUCTION OF NEW 132/13.8KV SUBSTATION # 8721 IN NORTH OF AL KHARJ
B48: PE-361 | C48: Construction of New Al Sahafa 132/13.8KV S/S # 8316 and its connection in Riyadh city | D48: 46191 | E48: 0.0219 | F48: 0.0142 | G48: SE | H48: Central | I48: Riyadh | K48: N/A | L48: 46801 | M48: 46801 | N48: 46801 | O48: 46861 | P48: 46861 | Q48: 46861 | R48: 46952 | S48: 46952 | T48: 46952 | U48: 1- Baseline not approve yet ,try to fix comment and send it 2-Soil investigation not started due to the final approval of Borehole location submittal
C50: EASTERN REGION UNIT | U50: - | W50: Planned % | X50: Performed % | Y50: TCC | Z50: PAC | AA50: FAC
A51: =A43+1 -> 41 | B51: PE-181 | C51: EPC OF PRIMARY ELECTRICAL SUSBSTATION #3 | D51: 43884 | E51: 1 | F51: 1 | G51: RC | H51: Eastern | I51: Ras Al Khair | K51: Approved | L51: 44560 | M51: 44560 | N51: 44552 | O51: NA | P51: NA | Q51: 45589 | R51: 44560 | S51: 44560 | T51: 46022 | U51: All Certificates Recieved | W51: =_xlfn.XLOOKUP($B51,'[1]03-Project Information'!$E:$E,'[1]03-Project Information'!AZ:AZ) -> 1 | X51: =_xlfn.XLOOKUP($B51,'[1]03-Project Information'!$E:$E,'[1]03-Project Information'!BA:BA) -> 1 | Y51: =_xlfn.XLOOKUP($B51,'[1]03-Project Information'!$E:$E,'[1]03-Project Information'!AE:AE) -> 44560 | Z51: =_xlfn.XLOOKUP($B51,'[1]03-Project Information'!$E:$E,'[1]03-Project Information'!AF:AF) -> 45589 | AA51: =_xlfn.XLOOKUP($B51,'[1]03-Project Information'!$E:$E,'[1]03-Project Information'!AG:AG) -> 46022
A52: =A51+1 -> 42 | B52: PE-199 | C52: SPARK 380/115/13.8KV BSP | D52: 43435 | E52: 1 | F52: 1 | G52: SEC | H52: Eastern | I52: Abqaiq | K52: Approved | L52: 44104 | M52: 44104 | N52: 44316 | O52: 44165 | P52: 44165 | Q52: 44377 | R52: 45838 | S52: 45838 | T52: 45808 | U52: All Certificates Recieved | W52: =_xlfn.XLOOKUP($B52,'[1]03-Project Information'!$E:$E,'[1]03-Project Information'!AZ:AZ) -> 1 | X52: =_xlfn.XLOOKUP($B52,'[1]03-Project Information'!$E:$E,'[1]03-Project Information'!BA:BA) -> 1 | Y52: =_xlfn.XLOOKUP($B52,'[1]03-Project Information'!$E:$E,'[1]03-Project Information'!AE:AE) -> 44316 | Z52: =_xlfn.XLOOKUP($B52,'[1]03-Project Information'!$E:$E,'[1]03-Project Information'!AF:AF) -> 44377 | AA52: =_xlfn.XLOOKUP($B52,'[1]03-Project Information'!$E:$E,'[1]03-Project Information'!AG:AG) -> 45808
A53: =A52+1 -> 43 | B53: PE-213 | C53: Construction Of Hawayah 380 KV S/S | D53: 43853 | E53: 1 | F53: 1 | G53: SEC | H53: Eastern | I53: Huwyha | K53: N/A | L53: HUW : 30-Jul-22 UQA : 30-Apr-23 | M53: HUW : 30-Jul-22 UQA : 30-Apr-23 | N53: HUW : 30-Sep-22 UQA :30-Aug-26 | O53: HUW : 30-Sep-22 UQA : 30-Jun-23 | P53: HUW : 30-Sep-22 UQA : 30-Jun-23 | Q53: HUW : 30-Sep-22 UQA :30-Sep-26 | R53: HUW :31-Dec-22 UQA : 30-Sep-23 | S53: HUW :31-Dec-22 UQA : 30-Sep-23 | T53: HUW :27-May-25 UQA :30-Nov-26 | U53: P1: All Certificates Recieved P2: No Certificates Recieved | W53: =_xlfn.XLOOKUP($B53,'[1]03-Project Information'!$E:$E,'[1]03-Project Information'!AZ:AZ) -> 1 | X53: =_xlfn.XLOOKUP($B53,'[1]03-Project Information'!$E:$E,'[1]03-Project Information'!BA:BA) -> 1 | Y53: =_xlfn.XLOOKUP($B53,'[1]03-Project Information'!$E:$E,'[1]03-Project Information'!AE:AE) -> 45565 | Z53: =_xlfn.XLOOKUP($B53,'[1]03-Project Information'!$E:$E,'[1]03-Project Information'!AF:AF) -> 45626 | AA53: =_xlfn.XLOOKUP($B53,'[1]03-Project Information'!$E:$E,'[1]03-Project Information'!AG:AG) -> 45716
A54: =A53+1 -> 44 | B54: PE-229 | C54: Construction of Temporary Rail Line (CO project of PE-181) | E54: 1 | F54: 1 | G54: RC | H54: Eastern | I54: Ras Al Khair | K54: Approved | L54: NA | M54: NA | N54: NA | O54: NA | P54: NA | Q54: NA | R54: 45605 | S54: 45605 | T54: 46022 | U54: All Certificates Recieved | W54: =_xlfn.XLOOKUP($B54,'[1]03-Project Information'!$E:$E,'[1]03-Project Information'!AZ:AZ) -> 1 | X54: =_xlfn.XLOOKUP($B54,'[1]03-Project Information'!$E:$E,'[1]03-Project Information'!BA:BA) -> 1 | Y54: =_xlfn.XLOOKUP($B54,'[1]03-Project Information'!$E:$E,'[1]03-Project Information'!AE:AE) -> 46022 | Z54: =_xlfn.XLOOKUP($B54,'[1]03-Project Information'!$E:$E,'[1]03-Project Information'!AF:AF) -> 46022 | AA54: =_xlfn.XLOOKUP($B54,'[1]03-Project Information'!$E:$E,'[1]03-Project Information'!AG:AG) -> 46022
A55: =A54+1 -> 45 | B55: PE-240 | C55: JSWCC|OHTL Package | D55: 44704 | E55: 1 | F55: 1 | G55: SWCC | H55: Eastern | I55: Jubail | K55: Under Approval | L55: 45345 | M55: 45345 | N55: 46053 | O55: 45345 | P55: 45345 | Q55: 46053 | R55: 45345 | S55: 45345 | T55: 46053 | U55: PAC Partially Recieved Waiting for final approval of Time Extension on Etimad For FAC Pending on PE-238 | W55: =_xlfn.XLOOKUP($B55,'[1]03-Project Information'!$E:$E,'[1]03-Project Information'!AZ:AZ) -> 1 | X55: =_xlfn.XLOOKUP($B55,'[1]03-Project Information'!$E:$E,'[1]03-Project Information'!BA:BA) -> 1 | Y55: =_xlfn.XLOOKUP($B55,'[1]03-Project Information'!$E:$E,'[1]03-Project Information'!AE:AE) -> 46053 | Z55: =_xlfn.XLOOKUP($B55,'[1]03-Project Information'!$E:$E,'[1]03-Project Information'!AF:AF) -> 46053 | AA55: =_xlfn.XLOOKUP($B55,'[1]03-Project Information'!$E:$E,'[1]03-Project Information'!AG:AG) -> 46053
A56: =A55+1 -> 46 | B56: PE-214 | C56: UTHMANIYAH | D56: 43884 | E56: 1 | F56: 0.999775 | G56: Aramco | H56: Eastern | I56: Dammam | K56: Approved | L56: 45134 | M56: 45626 | N56: 45550 | O56: 45234 | P56: 45626 | Q56: 45589 | R56: 45234 | S56: 45626 | T56: 46142 | U56: All Certificates Recieved FAC not Not applicable/MCC | W56: =_xlfn.XLOOKUP($B56,'[1]03-Project Information'!$E:$E,'[1]03-Project Information'!AZ:AZ) -> 1 | X56: =_xlfn.XLOOKUP($B56,'[1]03-Project Information'!$E:$E,'[1]03-Project Information'!BA:BA) -> 0.999775 | Y56: =_xlfn.XLOOKUP($B56,'[1]03-Project Information'!$E:$E,'[1]03-Project Information'!AE:AE) -> 45550 | Z56: =_xlfn.XLOOKUP($B56,'[1]03-Project Information'!$E:$E,'[1]03-Project Information'!AF:AF) -> 45589 | AA56: =_xlfn.XLOOKUP($B56,'[1]03-Project Information'!$E:$E,'[1]03-Project Information'!AG:AG) -> 46142
A57: =A56+1 -> 47 | B57: PE-227 | C57: Ibn zahr Expn. | D57: 44357 | E57: 1 | F57: 0.88294 | G57: SEC | H57: Eastern | I57: Dammam | K57: Approved | L57: 44814 | M57: 45412 | N57: 46331 | O57: 44844 | P57: 45442 | Q57: 46361 | R57: 44875 | S57: 45473 | T57: 46392 | U57: - | W57: =_xlfn.XLOOKUP($B57,'[1]03-Project Information'!$E:$E,'[1]03-Project Information'!AZ:AZ) -> 1 | X57: =_xlfn.XLOOKUP($B57,'[1]03-Project Information'!$E:$E,'[1]03-Project Information'!BA:BA) -> 0.88294 | Y57: =_xlfn.XLOOKUP($B57,'[1]03-Project Information'!$E:$E,'[1]03-Project Information'!AE:AE) -> 46331 | Z57: =_xlfn.XLOOKUP($B57,'[1]03-Project Information'!$E:$E,'[1]03-Project Information'!AF:AF) -> 46361 | AA57: =_xlfn.XLOOKUP($B57,'[1]03-Project Information'!$E:$E,'[1]03-Project Information'!AG:AG) -> 46392
A58: =A57+1 -> 48 | B58: PE-238 | C58: SWCC | BSP Portion | D58: 44704 | E58: 1 | F58: 0.981722 | G58: SWCC | H58: Eastern | I58: Jubail | K58: Under Approval | L58: 45345 | M58: 45345 | N58: 46053 | O58: 45345 | P58: 45345 | Q58: 46053 | R58: 45345 | S58: 45345 | T58: 46203 | U58: PAC Partially Recieved Waiting for final approval of Time Extension on Etimad For FAC | W58: =_xlfn.XLOOKUP($B58,'[1]03-Project Information'!$E:$E,'[1]03-Project Information'!AZ:AZ) -> 1 | X58: =_xlfn.XLOOKUP($B58,'[1]03-Project Information'!$E:$E,'[1]03-Project Information'!BA:BA) -> 0.981722 | Y58: =_xlfn.XLOOKUP($B58,'[1]03-Project Information'!$E:$E,'[1]03-Project Information'!AE:AE) -> 46053 | Z58: =_xlfn.XLOOKUP($B58,'[1]03-Project Information'!$E:$E,'[1]03-Project Information'!AF:AF) -> 46053 | AA58: =_xlfn.XLOOKUP($B58,'[1]03-Project Information'!$E:$E,'[1]03-Project Information'!AG:AG) -> 46203
A59: =A58+1 -> 49 | B59: PE-239 | C59: SWCC | Solar Package | D59: 45336 | E59: 1 | F59: 0.907 | G59: SWCC | H59: Eastern | I59: Jubail | K59: Under Approval | L59: 45702 | M59: 45702 | N59: 46203 | O59: 45702 | P59: 45702 | Q59: 46203 | R59: 45702 | S59: 45702 | T59: 46203 | U59: - | W59: =_xlfn.XLOOKUP($B59,'[1]03-Project Information'!$E:$E,'[1]03-Project Information'!AZ:AZ) -> 1 | X59: =_xlfn.XLOOKUP($B59,'[1]03-Project Information'!$E:$E,'[1]03-Project Information'!BA:BA) -> 0.907 | Y59: =_xlfn.XLOOKUP($B59,'[1]03-Project Information'!$E:$E,'[1]03-Project Information'!AE:AE) -> 46234 | Z59: =_xlfn.XLOOKUP($B59,'[1]03-Project Information'!$E:$E,'[1]03-Project Information'!AF:AF) -> 46234 | AA59: =_xlfn.XLOOKUP($B59,'[1]03-Project Information'!$E:$E,'[1]03-Project Information'!AG:AG) -> 46234
A60: =A59+1 -> 50 | B60: PE-277 | C60: Thuqbah BSP 380/115KV | D60: 45218 | E60: 0.98825 | F60: 0.966064 | G60: SEC | H60: Eastern | I60: Thuqbah | K60: Approved | L60: 45766 | M60: 46173 | N60: 46173 | O60: 45827 | P60: =EDATE(M60,2) -> 46234 | Q60: 46306 | R60: 45919 | S60: =EDATE(P60,3) -> 46326 | T60: 46418 | U60: - | W60: =_xlfn.XLOOKUP($B60,'[1]03-Project Information'!$E:$E,'[1]03-Project Information'!AZ:AZ) -> 0.98825 | X60: =_xlfn.XLOOKUP($B60,'[1]03-Project Information'!$E:$E,'[1]03-Project Information'!BA:BA) -> 0.966064 | Y60: =_xlfn.XLOOKUP($B60,'[1]03-Project Information'!$E:$E,'[1]03-Project Information'!AE:AE) -> 46173 | Z60: =_xlfn.XLOOKUP($B60,'[1]03-Project Information'!$E:$E,'[1]03-Project Information'!AF:AF) -> 46306 | AA60: =_xlfn.XLOOKUP($B60,'[1]03-Project Information'!$E:$E,'[1]03-Project Information'!AG:AG) -> 46418
A61: =A60+1 -> 51 | B61: PE-288 | C61: Repl. of Berry Gas Plant 230/115KV SS | D61: 45431 | E61: 0.92007823 | F61: 0.85511484 | G61: SEC | H61: Eastern | I61: Jubail | J61: Not Yet | K61: Under Approval | L61: 46041 | M61: 46041 | N61: 46305 | O61: 46437 | P61: 46437 | Q61: 46670 | R61: 46526 | S61: 46526 | T61: 46701 | U61: OHTL Portion after 11 months from SS which is shown here | W61: =_xlfn.XLOOKUP($B61,'[1]03-Project Information'!$E:$E,'[1]03-Project Information'!AZ:AZ) -> 0.92007823 | X61: =_xlfn.XLOOKUP($B61,'[1]03-Project Information'!$E:$E,'[1]03-Project Information'!BA:BA) -> 0.85511484 | Y61: =_xlfn.XLOOKUP($B61,'[1]03-Project Information'!$E:$E,'[1]03-Project Information'!AE:AE) -> 46305 | Z61: =_xlfn.XLOOKUP($B61,'[1]03-Project Information'!$E:$E,'[1]03-Project Information'!AF:AF) -> 46670 | AA61: =_xlfn.XLOOKUP($B61,'[1]03-Project Information'!$E:$E,'[1]03-Project Information'!AG:AG) -> 46701
A62: =A61+1 -> 52 | B62: PE-302 | C62: AL RAMES 380/115 KV BSP | D62: 45218 | E62: 0.99474531 | F62: 0.99269133 | G62: SEC | H62: Eastern | I62: Dammam | K62: Approved | L62: 45766 | M62: 46356 | N62: 46173 | O62: 45827 | P62: =EDATE(M62,2) -> 46417 | Q62: 46457 | R62: 45918 | S62: =EDATE(P62,3) -> 46507 | T62: 46568 | U62: Expected TCC will be on 13 Dec 26 due to delay of FOC readiness (31 Aug 2026) / Disconnector Switch | W62: =_xlfn.XLOOKUP($B62,'[1]03-Project Information'!$E:$E,'[1]03-Project Information'!AZ:AZ) -> 0.99474531 | X62: =_xlfn.XLOOKUP($B62,'[1]03-Project Information'!$E:$E,'[1]03-Project Information'!BA:BA) -> 0.99269133 | Y62: =_xlfn.XLOOKUP($B62,'[1]03-Project Information'!$E:$E,'[1]03-Project Information'!AE:AE) -> 46173 | Z62: =_xlfn.XLOOKUP($B62,'[1]03-Project Information'!$E:$E,'[1]03-Project Information'!AF:AF) -> 46457 | AA62: =_xlfn.XLOOKUP($B62,'[1]03-Project Information'!$E:$E,'[1]03-Project Information'!AG:AG) -> 46568
A63: =A62+1 -> 53 | B63: PE-334 | C63: Ghazlan-3 BSP | D63: 45697 | E63: 0.72111 | F63: 0.465294 | G63: SEC | H63: Eastern | I63: Ghazlan | J63: Not Yet | K63: Under Approval | L63: 46212 | M63: =L63 -> 46212 | N63: 46500 | O63: 46274 | P63: =EDATE(M63,2) -> 46274 | Q63: 46568 | R63: 46365 | S63: =EDATE(P63,3) -> 46365 | T63: 46660 | U63: Planned % is based on orginal baseline however we have a submitted revised schedule showing 80% used for internal reporting | W63: =_xlfn.XLOOKUP($B63,'[1]03-Project Information'!$E:$E,'[1]03-Project Information'!AZ:AZ) -> 0.72111 | X63: =_xlfn.XLOOKUP($B63,'[1]03-Project Information'!$E:$E,'[1]03-Project Information'!BA:BA) -> 0.465294 | Y63: =_xlfn.XLOOKUP($B63,'[1]03-Project Information'!$E:$E,'[1]03-Project Information'!AE:AE) -> 46500 | Z63: =_xlfn.XLOOKUP($B63,'[1]03-Project Information'!$E:$E,'[1]03-Project Information'!AF:AF) -> 46568 | AA63: =_xlfn.XLOOKUP($B63,'[1]03-Project Information'!$E:$E,'[1]03-Project Information'!AG:AG) -> 46660
A64: =A63+1 -> 54 | B64: PE-344 | C64: Nariyah BSP | D64: 45715 | E64: 0.954856 | F64: 0.56828 | G64: SEC | H64: Eastern | I64: Nariyah | K64: N/A | L64: 46291 | M64: 46291 | N64: 46544 | O64: 46352 | P64: =EDATE(M64,2) -> 46352 | Q64: 46607 | R64: 46444 | S64: =EDATE(P64,3) -> 46444 | T64: 46699 | U64: Delayed due to the delivery of GIS equipment Delayed 2times 1st delay till 25-June-26 2nd Delay till 25-Aug-26 | W64: =_xlfn.XLOOKUP($B64,'[1]03-Project Information'!$E:$E,'[1]03-Project Information'!AZ:AZ) -> 0.954856 | X64: =_xlfn.XLOOKUP($B64,'[1]03-Project Information'!$E:$E,'[1]03-Project Information'!BA:BA) -> 0.56828 | Y64: =_xlfn.XLOOKUP($B64,'[1]03-Project Information'!$E:$E,'[1]03-Project Information'!AE:AE) -> 46544 | Z64: =_xlfn.XLOOKUP($B64,'[1]03-Project Information'!$E:$E,'[1]03-Project Information'!AF:AF) -> 46607 | AA64: =_xlfn.XLOOKUP($B64,'[1]03-Project Information'!$E:$E,'[1]03-Project Information'!AG:AG) -> 46699
A65: =A64+1 -> 55 | B65: PE-355 | C65: Construction of King Saud Air Base Facilities | D65: 45879 | E65: 0.1757 | F65: 0.12 | G65: RSAF | H65: Eastern | I65: Haffr Albatan | K65: N/A | L65: 46609 | M65: 46609 | N65: 46657 | O65: 46670 | P65: 46670 | Q65: =EOMONTH(N65,2) -> 46721 | R65: 47097 | S65: 47097 | T65: 47097 | U65: Only Scope Alfanar / There is no FAC only based on the 40 Months Completion | W65: =_xlfn.XLOOKUP($B65,'[1]03-Project Information'!$E:$E,'[1]03-Project Information'!AZ:AZ) -> #N/A | X65: =_xlfn.XLOOKUP($B65,'[1]03-Project Information'!$E:$E,'[1]03-Project Information'!BA:BA) -> #N/A | Y65: =_xlfn.XLOOKUP($B65,'[1]03-Project Information'!$E:$E,'[1]03-Project Information'!AE:AE) -> #N/A | Z65: =_xlfn.XLOOKUP($B65,'[1]03-Project Information'!$E:$E,'[1]03-Project Information'!AF:AF) -> #N/A | AA65: =_xlfn.XLOOKUP($B65,'[1]03-Project Information'!$E:$E,'[1]03-Project Information'!AG:AG) -> #N/A
A66: =A65+1 -> 56 | B66: PE-304 | C66: 230/115kV SS | JUBAIL SW REPLACEMENT | D66: 45900 | E66: 0.1969 | F66: 0.126 | G66: SEC | H66: Eastern | I66: Jubail | K66: N/A | L66: 46630 | M66: 46630 | N66: 46870 | O66: 46691 | P66: =EDATE(M66,2) -> 46691 | Q66: 46930 | R66: 46783 | S66: =EDATE(P66,3) -> 46783 | T66: 47023 | U66: Delayed due to site accessibility issues and Water leakage incident | W66: =_xlfn.XLOOKUP($B66,'[1]03-Project Information'!$E:$E,'[1]03-Project Information'!AZ:AZ) -> 0.1969 | X66: =_xlfn.XLOOKUP($B66,'[1]03-Project Information'!$E:$E,'[1]03-Project Information'!BA:BA) -> 0.126 | Y66: =_xlfn.XLOOKUP($B66,'[1]03-Project Information'!$E:$E,'[1]03-Project Information'!AE:AE) -> 46870 | Z66: =_xlfn.XLOOKUP($B66,'[1]03-Project Information'!$E:$E,'[1]03-Project Information'!AF:AF) -> 46930 | AA66: =_xlfn.XLOOKUP($B66,'[1]03-Project Information'!$E:$E,'[1]03-Project Information'!AG:AG) -> 47023
A67: =A66+1 -> 57 | B67: PE-366 | C67: Qulayyib 380 kV BSP | D67: 46113 | E67: 0.06743 | F67: 0.03998 | G67: MGC-Mutlaq Al Gowairi Company | H67: Eastern | I67: Qulayyib Area | K67: N/A | L67: 46905 | M67: 46905 | N67: 46943 | O67: 46905 | P67: 46905 | Q67: 46943 | R67: 47270 | S67: 47270 | T67: 47308 | U67: - | W67: =_xlfn.XLOOKUP($B67,'[1]03-Project Information'!$E:$E,'[1]03-Project Information'!AZ:AZ) -> 0.06743 | X67: =_xlfn.XLOOKUP($B67,'[1]03-Project Information'!$E:$E,'[1]03-Project Information'!BA:BA) -> 0.03998 | Y67: =_xlfn.XLOOKUP($B67,'[1]03-Project Information'!$E:$E,'[1]03-Project Information'!AE:AE) -> 46943 | Z67: =_xlfn.XLOOKUP($B67,'[1]03-Project Information'!$E:$E,'[1]03-Project Information'!AF:AF) -> 46943 | AA67: =_xlfn.XLOOKUP($B67,'[1]03-Project Information'!$E:$E,'[1]03-Project Information'!AG:AG) -> 47308
A68: =A67+1 -> 58 | B68: PE-354 | C68: Construction of NEW VSC HVDC Overhead Transmission Line for EOA-COA Link 1 | D68: 46146 | E68: 0.029387 | F68: 0.01827 | G68: SEC | H68: Eastern | I68: Nariyah | K68: N/A | L68: 47061 | M68: 47061 | N68: 47079 | O68: 47122 | P68: 47122 | Q68: 47141 | R68: 47212 | S68: 47212 | T68: 47236 | W68: =_xlfn.XLOOKUP($B68,'[1]03-Project Information'!$E:$E,'[1]03-Project Information'!AZ:AZ) -> 0.029387 | X68: =_xlfn.XLOOKUP($B68,'[1]03-Project Information'!$E:$E,'[1]03-Project Information'!BA:BA) -> 0.01827 | Y68: =_xlfn.XLOOKUP($B68,'[1]03-Project Information'!$E:$E,'[1]03-Project Information'!AE:AE) -> 47079 | Z68: =_xlfn.XLOOKUP($B68,'[1]03-Project Information'!$E:$E,'[1]03-Project Information'!AF:AF) -> 47141 | AA68: =_xlfn.XLOOKUP($B68,'[1]03-Project Information'!$E:$E,'[1]03-Project Information'!AG:AG) -> 47236
C69: WESTERN REGION UNIT | U69: -
A70: =A68+1 -> 59 | B70: PE-243 | C70: Installation of Dynamic Reactive Power Compensation(DRPC) at Tabuk 380KV BSP | D70: 44700 | E70: 1 | F70: 1 | G70: SEC | H70: Western | I70: Tabuk | J70: 45902 | K70: Approved | L70: 45492 | M70: 45777 | N70: 45777 | O70: 45554 | P70: 45991 | Q70: 46386 | R70: 45615 | S70: 46052 | T70: 46446 | U70: Energization done without TSC Panel, TCC received. Partial PAC (21-Jan-2026) also received; Balance PAC & FAC upon delivery of remaining TSC Panel; Alfanar requested for FAC invoice and under discussion with SEC.
A71: =A70+1 -> 60 | B71: PE-241 | C71: Expansion of Existing Yanbu Central (YCNT) | D71: 44598 | E71: 1 | F71: 0.989 | G71: SEC | H71: Western | I71: Yanbu,Umluj& Alwajh | K71: N/A | L71: 45297 | M71: 45565 | N71: 45565 | O71: 45357 | P71: 45626 | Q71: 46132 | R71: 45449 | S71: 45716 | T71: 46285 | U71: PAC received, not yet energized due to SE shutdown issues for all the area
A72: =A71+1 -> 61 | B72: PE-257 | C72: Expansions of Existing MHD 380 KV BSP | D72: 44868 | E72: 1 | F72: 0.9989 | G72: SEC | H72: Western | I72: Madinah | K72: N/A | L72: 45415 | M72: 45960 | N72: 46021 | O72: 45476 | P72: 46021 | Q72: 46082 | R72: 45567 | S72: 46111 | T72: 46174 | U72: As-built drawings under SEC review & approval. FAC certification waiting from SE; Request for issuance of FAC / Commitment for Completion of Outstanding Work was submitted on 20-Jul-26.
A73: =A72+1 -> 62 | B73: PE-258 | C73: Taif East Governorate Project | D73: 44882 | E73: 1 | F73: 0.9 | G73: SEC | H73: Western | I73: Taif | K73: N/A | L73: 45399 | M73: 45643 | N73: 46295 | O73: 45460 | P73: 45703 | Q73: 46324 | R73: 45552 | S73: 45793 | T73: 46414 | U73: 1. EOT-1 Approved upto 14-Dec-24, EOT-2 submitted on 12th Aug 25, TCC upto 17th Jun 26. (Under SEC Approval). EOT to be resubmitted. 2. SAS testing pending due to EWS V.O finalization and delivery (V.O) 3. OHTL Line readiness pending from SE, no clarity on readiness
A74: =A73+1 -> 63 | B74: PE-270 | C74: 110/13.8KV HARAZAT SUB JEDDAH | D74: 45120 | E74: 1 | F74: 0.9841 | G74: SEC | H74: Western | I74: Jeddah | K74: N/A | L74: 45609 | M74: 45729 | N74: 45867 | O74: 45670 | P74: 45790 | Q74: 45972 | R74: 45760 | S74: 45882 | T74: 46295 | U74: Remote End Works: 1. Installation of Telecom Panels completed, testing will be done, once line readiness from client. (Dependent on Line Readiness from Client) 2. Final Settings of Line Protection Panels. (Dependent on Line Readiness from Client) Punchlist & As built works are in progress, completion date 30-Sep-26. Punchlist:Total 309 nos, 295 Completed, 5 nos ready to close. Asbuilt: 90% completed.
A75: =A74+1 -> 64 | B75: PE-290 | C75: Fadelah 110/13.8KV SS - JEDDAH | D75: 45131 | E75: 1 | F75: 0.9842 | G75: SEC | H75: Western | I75: Jeddah | K75: N/A | L75: 45620 | M75: 45924 | N75: 45834 | O75: 45681 | P75: 45681 | Q75: 45979 | R75: 45771 | S75: 46138 | T75: 46295 | U75: 1) Energization done with temporary line, (Permanent line readiness Dependent on Client). 2) AMI integration with WRCC. (Dependent on Line Readiness from Client). 3) Modon GIS extension bays (Shutdown -Relay setting ) 85% completed. Punchlist & As built works are in progress, completion date 30-Sep-26. Punch points : Out of 10, 2 completed, 3 ready to close. As built status: out of 12, 12 ready to close.
A76: =A75+1 -> 65 | B76: PE-254 | C76: HENAKIYAH BSP 380 KV | D76: 44861 | E76: 1 | F76: 1 | G76: SEC | H76: Western | I76: Madinah | K76: N/A | L76: 45562 | M76: 45657 | N76: 45754 | O76: 45623 | P76: 45716 | Q76: 46089 | R76: 45715 | S76: 45807 | T76: 46149 | U76: FAC received
A77: =A76+1 -> 66 | B77: PE-260 | C77: Sanabel con.at Jeddah | D77: 44924 | E77: 1 | F77: 0.975 | G77: SEC | H77: Western | I77: Jeddah | K77: N/A | L77: 45594 | M77: 45687 | N77: 45992 | O77: 45655 | P77: 45748 | Q77: 46249 | R77: 45744 | S77: 45841 | T77: 46298 | U77: SAS Configuration and testing pending, due to AES team mobilization pending
A78: =A77+1 -> 67 | B78: PE-262 | C78: Reinf. of Thuwal Town KAUST 2 | D78: 44924 | E78: 1 | F78: 0.9696 | G78: SEC | H78: Western | I78: Jeddah | K78: N/A | L78: 45533 | M78: 45656 | N78: 45992 | O78: 45594 | P78: 45717 | Q78: 46249 | R78: 45685 | S78: 45811 | T78: 46298 | U78: SAS Configuration and testing pending
A79: =A78+1 -> 68 | B79: PE-296 | C79: Waly Alahad-4 110/13.8KV SS | D79: 45218 | E79: 1 | F79: 0.9453 | G79: SEC | H79: Western | I79: Makkah | K79: N/A | L79: 45707 | M79: 45980 | N79: 45980 | O79: 45766 | P79: 46041 | Q79: 8 | R79: 45857 | S79: 46131 | T79: 46321 | U79: 1) Line readiness pending from SEC
A80: =A79+1 -> 69 | B80: PE-281 | C80: 110KV SS - KAEC-3 | D80: 45442 | E80: 1 | F80: 0.99 | G80: SEC | H80: Western | I80: Jeddah | K80: N/A | L80: 45991 | M80: 45991 | N80: 45991 | O80: 46052 | P80: 46052 | Q80: 46093 | R80: 46141 | S80: 46141 | T80: 46203 | U80: TCC, PAC Received. FAC Letter Submitted to Client
A81: =A80+1 -> 70 | B81: PE-280 | C81: 110KV SS - KAEC-2 | D81: 45442 | E81: 1 | F81: 1 | G81: SEC | H81: Western | I81: Jeddah | K81: N/A | L81: 45991 | M81: 45991 | N81: 45991 | O81: 46052 | P81: 46052 | Q81: 46093 | R81: 46141 | S81: 46141 | T81: 46141 | U81: FAC received
A82: =A81+1 -> 71 | B82: PE-185 | C82: NG Taif | D82: 43156 | E82: 1 | F82: 0.9965 | G82: NG | H82: Western | I82: Taif | K82: N/A | L82: NA | M82: NA | N82: NA | O82: 43886 | P82: 45852 | Q82: 46249 | R82: 44252 | S82: 46217 | T82: 46568 | U82: EOT: Contract amendment approved,PCC on 14th Jul 25, EOT-2 submitted on 4th Nov 25, with 8 months (PCC: 14th Mar 26), Under SEC approval 1) All cable ceiling end joints works replacing works in progress, expected compeltion by 30th May 26. 2) Remote end-1 final setting done, Remote end 2 final setting completion by 10th May. 3) HV Test and end to end test pending expected completion by 15th Jun and 30th Jun
A83: =A82+1 -> 72 | B83: PE-267 | C83: CONST KAR 380 110KV BSP | D83: 45078 | E83: 1 | F83: 0.9794 | G83: Masar | H83: Western | I83: Makkah | J83: 45901 | K83: Approved | L83: 45808 | M83: 46022 | N83: 46022 | O83: 45868 | P83: 46082 | Q83: 46303 | R83: 45930 | S83: 46143 | T83: 46364 | U83: 1.Close loop test completed 2. HVAC Testing: Completed 3. FF & FA Testing: All testing is completed and Remaining Final testing with ISD is in progress. 4. C04 modification work will be started after Energization of C06 Feeder as per SEC instruction. This will required 2 months to complete the task. 5. TCC received 6. New Change Order (confrimed) i.e. Duct Bank for future Area.-Completed 7.End to end test in progress, Expected engization by Aug'26 end.
A84: =A83+1 -> 73 | B84: PE-291 | C84: HAMRA AL ASAD 110/13.8 KV SUB | D84: 45133 | E84: 1 | F84: 0.9998 | G84: SEC | H84: Western | I84: Madinah | K84: Approved | L84: 45622 | M84: 45930 | N84: 46163 | O84: 45683 | P84: 45991 | Q84: 46233 | R84: 45773 | S84: 46081 | T84: 46295 | U84: 1) TCC received on 21-May-26. PAC received on 30-Jul-26. (Energization done through the AZIZIA remote-end and TCC was obtained. Remaining interface works at the MICY remote end are ongoing and are expected to be completed by end of Aug 2026.) 2) Target is to energize both remaining feeders with remote end by 1st week of Sep. 2026
A85: =A84+1 -> 74 | B85: PE-292 | C85: Shoran-2 110/13.8 KV - Madinah | D85: 45131 | E85: 1 | F85: 0.9925 | G85: SEC | H85: Western | I85: Madinah | K85: Under Approval | L85: 45620 | M85: 45620 | N85: 46265 | O85: 45682 | P85: 45682 | Q85: 46326 | R85: 45771 | S85: 45771 | T85: 46417 | U85: 1) TCC is requested , still not issued. Readiness of UGC circuits have delayed energization of the substation and TCC issuance. 2) Expected energization by end of Aug. 2026 if the UGC Feeders passed ongoing Tests by Cable contractor.
A86: =A85+1 -> 75 | B86: PE-315 | C86: 110KV Salam Royal Palace | D86: 45386 | E86: 1 | F86: 0.959 | G86: SEC | H86: Western | I86: Jeddah | K86: N/A | L86: 45934 | M86: 45934 | N86: 46037 | O86: 45995 | P86: 45995 | Q86: 46093 | R86: 46085 | S86: 46085 | T86: 46264 | U86: 1) EOT-1 Submitted on 13th Aug 25, with TCC date on 23rd Jul 26. Under SEC approval 2) Energization actual date 15th Jan 26
A87: =A86+1 -> 76 | B87: PE-263 | C87: MOWAIH PV 380/110V BSP | D87: 45014 | E87: 1 | F87: 0.99 | G87: SEC | H87: Western | I87: Taif | K87: N/A | L87: 45745 | M87: 45961 | N87: 46028 | O87: 45806 | P87: 46021 | Q87: 46150 | R87: 45897 | S87: 46081 | T87: 46264 | U87: EOT is submitted with TCC and was approved on 21st Apr 26 Energization done, and TCC was received on 21st Apr 26
A88: =A87+1 -> 77 | B88: PE-246 | C88: UM-AL-JOUD BSP | D88: 44812 | E88: 1 | F88: 0.8895 | G88: SEC | H88: Western | I88: Makkah | K88: Under Approval | L88: 45238 | M88: 45695 | N88: 46264 | O88: 45299 | P88: 45754 | Q88: 46325 | R88: 45390 | S88: 45845 | T88: 46417 | U88: 1) EOT-2 submitted to client on 8th Jan 25, Revised TCC date confirmation is pending by SEC (Due to no clarity in readiness of remote end i.e. Fahya SS). EOT-2 resubmitted on 14-June-26 for Revised TCC on 31-July-27. Once approved, TCC letter will be submitted. 2) Remote end protection desing approval pending from SEC. Holding the procurement of loose material & modification work at remote end. 3) Protection scope for Fahya Substation is unknown: Due to which Design submission and approval for modification and procuring loose material is still not finalized 4) Restriction to work inside Rusifah Substation: No confirmation on Panel Installation is provided in Rusifah Substation due to limitations of space. Also, FOC cable pulling & termination inside SS is on hold. 5) Testing of Fiber & High Voltage cable is required to start. Waiting for SEC witness. 6) Shut down from SEC is required for Replacing Relay from Rushifah to Umaljoud. Still no clarity on shutdown also.
A89: =A88+1 -> 78 | B89: PE-265 | C89: 110/33 KV ALMAHANI S/S IN TAIF | D89: 45060 | E89: 1 | F89: 0.923 | G89: SEC | H89: Western | I89: Taif | J89: 45690 | K89: Under Approval | L89: 45671 | M89: 45991 | N89: 46325 | O89: 45730 | P89: 46052 | Q89: 46386 | R89: 45822 | S89: 46111 | T89: 46446 | U89: EOT: EOT submitted TCC upto 30-Nov-26. Under SEC approval. 1) delay in final setting approval for SWGR and Capacitor bank and line protection delaying open loop Tests 2) Delayed HV kit for GIS HV test (was scheduled by Jul-26) now rescheduled to 20-Aug-26 3) Delayed installations of the (HV Terminations, CSE, MV Terminations) pending subcontractor. (PO Under finalization with SCD) 4) Delayed open loop tests for the major equipment due to non-availability of SAS engineer. (Will be mobilized after Approval of final settings) 5) OHTL Line readinees (AL-mahani to MAHD), No clarity on the completion by other contractor.
A90: =A89+1 -> 79 | B90: PE-266 | C90: EXT. OF THE EXIS. THAGEF &ADAM | D90: 45060 | E90: 1 | F90: 0.8663 | G90: SEC | H90: Western | I90: Taif | J90: 45944 | K90: Under Approval | L90: 45671 | M90: 45944 | N90: 46356 | O90: 45731 | P90: 46005 | Q90: 46417 | R90: 45822 | S90: 46067 | T90: 46476 | U90: EOT: EOT-2 submitted with TCC date of 27-Jul-26. (Under SEC Approval) 1) AES Control panel (Mosaic and Annciator) detail design still under approval & no clarity on FAT date. (expected by Sep-26). 2) Missing BCU units for ADAM LCC (Hyundai), Provided by AES (Purchased from SIEMENS) Delayed since Feb-26, Latest provided date by AES is by Oct-26 3) Loose materials are required from AES for Protection, LCC Panels. To be compatible with existing systems and proceed commissioning activities 4) Delayed delivery of the PC Workstation (EWS) and the PO is still under Finalization with SCD 4) No Clarity of OHTL Line readiness.
A91: =A90+1 -> 80 | B91: PE-286 | C91: SEC Smart Distribution Control Centre | D91: 45498 | E91: 0.9831 | F91: 0.9021 | G91: SEC | H91: Western | I91: Jeddah | K91: N/A | L91: 46228 | M91: 46228 | N91: 46387 | O91: 46290 | P91: 46290 | Q91: 46437 | R91: 46654 | S91: 46654 | T91: 46801 | U91: 1. SLD Submission for Downstream : CET/NARI Shortage on Manpower where current manpower is 28 and plan to be 39 by 31-Jul-26 , Target Completion Madinah : 05-Sep-26 , Jeddah :06-Oct-26 ,Makkah : 06-Oct-26 ,Abha :03-Sep-26 , Jizan : 16-Sep-26. 2. Abha ADMS System Crash: SLD NDesigner application crashed during implementation activities in Abha, resulting in delays to SLD preparation, submission, and validation activities. 3. Cyber Security Audit : Audit plan not yet Approved by SE and the PO (Third Party) has not been issued by NARI (affecting Cutover). The audit requires approximately 10 weeks after PO issuance. 4. NARI End-to-End Testing Team : A dedicated NARI team is required to focus exclusively on End-to-End testing activities. A total of nine engineers are expected to be mobilized by the 31 July 2026. 5. Delay in Telecom Panel Local Test for Remote End (MADINAH LDC). 6. Delay delivery of DWDM (PO issued to AES) – waiting the final confirmation for the recent traffic plan in Madina, Abha & Jizan. 7. All Submittal under review with FEC / HSSE. 8. Requirements from STC connectivity regarding IP Telephone (SIP) services. 9.1 ICT reviewer’s new comments regarding the passive scope and Beit Al Anzima rejection._x000B_9.2 ICT rejected the material in Rev-02 although no comments were received in Rev-01._x000B_9.3 The material has already been delivered and installed on site. 9.4 The ICT reviewer has been rejecting every submitted versions without providing any specific technical comments or justified reasons, Also rejecting both of the approved Design Consultant and the Contractor. This repeated rejection practice is causing significant delays to the project and directly impacting the implementation and activation of critical ICT services, including Internet connectivity, IP Telephony, and system integrations.
A92: =A91+1 -> 81 | B92: PE-287 | C92: Exp. of YCNT BSP for Power to Neom | D92: 45139 | E92: 0.9338 | F92: 0.9508 | G92: NEOM / SEC | H92: Western | I92: Yanbu | K92: N/A | L92: 46357 | M92: 46357 | N92: 46357 | O92: 46539 | P92: 46539 | Q92: 46539 | R92: 46600 | S92: 46600 | T92: 46600 | U92: 1) 2 Nos GIS breakers damaged due to heavy wind (Fell down, no major damage), need to close the issues with GE Team, Breakers are sent to France Factory to get the repaired materials expected Repaired materials delivery by End of Sep-26. 2) HV Test Equipment delivery pending from GE, due to lack of equipment (Used for other site)
A93: =A92+1 -> 82 | B93: PE-294 | C93: Airport C (KAIA) Interconnection REINF. | D93: 45231 | E93: 1 | F93: 0.8399 | G93: SEC | H93: Western | I93: Jeddah | K93: N/A | L93: 46054 | M93: 46054 | N93: 46054 | O93: 46113 | P93: 46113 | Q93: 46335 | R93: 46174 | S93: 46174 | T93: 46392 | U93: 1) TCC Received on 09-Aug-26 as per Contractual TCC Date i.e. 01-Feb-26. 2) Remaining work cannot be proceeded due to HV Cable issue from SE. Project currently onhold from SE so manpower to be demobilized accordingly. 3) CSD refused to start T&C Activities because of the unavailability of existing HV cable from SE. 4) Change order (Approx.. 47 million) submitted to SE for additional HV cable work. Waiting for their approval.
A94: =A93+1 -> 83 | B94: PE-295 | C94: Interconnection of AJM-1 (New Jamoom) | D94: 45299 | E94: 1 | F94: 0.9052 | G94: SEC | H94: Western | I94: Makkah | K94: N/A | L94: 46120 | M94: 46120 | N94: 46120 | O94: 46181 | P94: 46181 | Q94: 46267 | R94: 46242 | S94: 46242 | T94: 46329 | U94: 1) T.C.C received. 2)Shutdown required for Connecting existing GIS to new GIS bay, expected in Aug-26.
A95: =A94+1 -> 84 | B95: PE-301 | C95: Expansion of Mowaih PV 380kV BSP | D95: 45551 | E95: 1 | F95: 0.985 | G95: SEC | H95: Western | I95: Mowaih | K95: Under Approval | L95: 45946 | M95: 45946 | N95: 46264 | O95: 46007 | P95: 46007 | Q95: 46295 | R95: 46097 | S95: 46097 | T95: 46385 | U95: 1) EOT-1 submitted on 16th Oct 25, with TCC Date on 27-5-26. Rejected by SEC on 21-Oct-25, Resubmitted, under approval with SE. 2) TCC delayed by SE, Due to SE-MOD time extension approval 2) 48 V DC system: FAT done delivery delayed expected delivery in Sep-26 3) Remote End Substations are not ready
A96: =A95+1 -> 85 | B96: PE-305 | C96: 110kV SS Kar-2 | D96: 45532 | E96: 0.93 | F96: 0.9 | G96: Masar | H96: Western | I96: Makkah | J96: 46036 | K96: Approved | L96: 46139 | M96: 46323 | N96: 46323 | O96: 46200 | P96: 46353 | Q96: 46353 | R96: 46261 | S96: 46383 | T96: 46383 | U96: 1) Delay in Mechanical materials i.e. HVAC system (PACU), Expected material delivery by Mid Aug-26 due to current Geo-political instability.
A97: =A96+1 -> 86 | B97: PE-307 | C97: 132/13.8KV Sub Industrial City Tabuk | D97: 45321 | E97: 0.9806 | F97: 0.9831 | G97: MODON | H97: Western | I97: Tabuk | K97: N/A | L97: NA | M97: NA | N97: NA | O97: 46248 | P97: 46248 | Q97: 46238 | R97: 46613 | S97: 46613 | T97: 46603 | U97: Critical Issues: OLT & CLT Completed and final testing like trip test, end to end test ongoing. However, PAC form signed after mutual site visit from SE, MODON & Alfanar. All pending works to be completed to target energization.
A98: =A97+1 -> 87 | B98: PE-308 | C98: 110KV Salam Royal | D98: 46153 | E98: 0.1002 | F98: 0.1933 | G98: SEC | H98: Western | I98: Jeddah | K98: N/A | L98: 46701 | M98: 46701 | N98: 46701 | O98: 46763 | P98: 46763 | Q98: 46763 | R98: 46854 | S98: 46854 | T98: 46854 | U98: 1) Baldia Permit required to avoid any delay in civil activities. Discussion under process. 2) AES to expedite submission of remaining Telecom drawings & also to close SE comments for submitted drawings to avoid any delay in material delivery. 3) AES to expedite to close SE comments for Protection Relay List to avoid any delay in material delivery. Protection Detail Design to be submitted. 4) AES to expedite submission of Switchgear Detail Design.
A99: =A98+1 -> 88 | B99: PE-312 | C99: Const of Southern 380KV BSP | Al Ula | D99: 45299 | E99: 0.9864 | F99: 0.9615 | G99: SEC | H99: Western | I99: Al Ula | J99: 46096 | K99: Approved | L99: 46030 | M99: 46203 | N99: 46203 | O99: 46089 | P99: 46264 | Q99: 46264 | R99: 46181 | S99: 46356 | T99: 46356 | U99: 1) TCC received. 2) External road: Road marking 3) Testing 85% completed. 4)Finishing work and punch points in progress.
A100: =A99+1 -> 89 | B100: PE-314 | C100: Expansion of Tabuk BSP & Duba BSP | D100: 45305 | E100: 0.9223 | F100: 0.9198 | G100: SEC | H100: Western | I100: Tabuk & Duba | J100: 46127 | K100: Approved | L100: 46036 | M100: 46356 | N100: 46356 | O100: 46095 | P100: 46417 | Q100: 46417 | R100: 46187 | S100: 46507 | T100: 46507 | U100: EOT: EOT approved with revised TCC date of 30-Nov-26. 1) Duba BSP: C5 Dia. SEC granted outage on 30-Apr-26. Dismantling of Reactor, dismantling civil foundation removal completed & construction of new foundation under progress & to be completed before 28-Sep-26. Energization as per revised TCC 30-Nov-26. 2) Tabuk BSP C02 Dia: Outage for bus-bar coupling submitted to SE, however SE informed outage will not be received during current season due to peak load. Expected outage will be around Sep’26. Hence, TCC Request submitted to SE for C02 Dia & under review
A101: =A100+1 -> 90 | B101: PE-319 | C101: HVDC-4 | COA-WOA | JED-HHR1 | D101: 45470 | E101: 0.9717 | F101: 0.9434 | G101: SEC | H101: Western | I101: Jeddah | K101: N/A | L101: 46387 | M101: 46387 | N101: 46408 | O101: 46446 | P101: 46446 | Q101: 46468 | R101: 46538 | S101: 46538 | T101: 46559 | U101: 1) Remote end works. 2) Pole 1 & Pole 2 valve hall equipment installation. 3) Pending materials delivery (CET partial materials and FF Materials).
...

Sheet Updated Progress % + TCC
A1: S.N. | B1: Project Code | C1: Project Name | D1: Project Managers Name | E1: Start Date | F1: Planned % | G1: Actual % | H1: Var. | I1: Client | J1: Region | K1: City | L1: EOT STATUS (Submitted/Approved/Under Approval/ N/A) | M1: TCC | P1: Remarks
E2: Start Date | M2: Contract Date | N2: Revised Date | O2: Forecast Date | P2: Remarks
C3: CENTRAL REGION UNIT (BASIL ALHAKAMI)
A4: 1 | B4: PE-215 | C4: =VLOOKUP(B4,'Detailed Update'!B:C,2,FALSE) -> SMP - O&M 3 Yrs | D4: Mohamed Sabri | E4: 44652 | F4: 1 | G4: 1 | H4: =G4-F4 -> 0 | I4: =VLOOKUP(B4,'Detailed Update'!B:I,6,FALSE) -> SEC | J4: =VLOOKUP(B4,'Detailed Update'!B:I,7,FALSE) -> Central | K4: =VLOOKUP(B4,'Detailed Update'!B:I,8,FALSE) -> Riyadh | L4: Approved | M4: =VLOOKUP(B4,'Detailed Update'!B:T,11,FALSE) -> 45442 | N4: =VLOOKUP(B4,'Detailed Update'!B:T,12,FALSE) -> 45812 | O4: =VLOOKUP(B4,'Detailed Update'!B:T,13,FALSE) -> 45812 | P4: =VLOOKUP(B4,'Detailed Update'!B:U,20,FALSE) -> All certification Received
A5: =A4+1 -> 2 | B5: PE-226 | C5: =VLOOKUP(B5,'Detailed Update'!B:C,2,FALSE) -> KHASM-AL-AAN BSP | D5: Amin El Sayed | E5: 44350 | F5: 1 | G5: 0.863 | H5: =G5-F5 -> -0.137 | I5: =VLOOKUP(B5,'Detailed Update'!B:I,6,FALSE) -> SEC | J5: =VLOOKUP(B5,'Detailed Update'!B:I,7,FALSE) -> Central | K5: =VLOOKUP(B5,'Detailed Update'!B:I,8,FALSE) -> Riyadh | L5: Approved | M5: =VLOOKUP(B5,'Detailed Update'!B:T,11,FALSE) -> 44960 | N5: =VLOOKUP(B5,'Detailed Update'!B:T,12,FALSE) -> 45657 | O5: =VLOOKUP(B5,'Detailed Update'!B:T,13,FALSE) -> 46411 | P5: =VLOOKUP(B5,'Detailed Update'!B:U,20,FALSE) -> Partial TCC Received | Project on Hold
A6: =A5+1 -> 3 | B6: PM-223 | C6: =VLOOKUP(B6,'Detailed Update'!B:C,2,FALSE) -> GASCO - 2 | D6: Fathi Mohamed | E6: 44368 | F6: 1 | G6: 0.9991 | H6: =G6-F6 -> -0.0009 | I6: =VLOOKUP(B6,'Detailed Update'!B:I,6,FALSE) -> GASCO | J6: =VLOOKUP(B6,'Detailed Update'!B:I,7,FALSE) -> Central | K6: =VLOOKUP(B6,'Detailed Update'!B:I,8,FALSE) -> Riyadh | L6: Approved | M6: =VLOOKUP(B6,'Detailed Update'!B:T,11,FALSE) -> 45136 | N6: =VLOOKUP(B6,'Detailed Update'!B:T,12,FALSE) -> 45747 | O6: =VLOOKUP(B6,'Detailed Update'!B:T,13,FALSE) -> 45961 | P6: =VLOOKUP(B6,'Detailed Update'!B:U,20,FALSE) -> Initial Handing over received
A7: =A6+1 -> 4 | B7: PE-228 | C7: =VLOOKUP(B7,'Detailed Update'!B:C,2,FALSE) -> SVC QASSIM -2 | D7: Hany Kamal | E7: 44444 | F7: 1 | G7: 0.9928 | H7: =G7-F7 -> -0.0072 | I7: =VLOOKUP(B7,'Detailed Update'!B:I,6,FALSE) -> SEC | J7: =VLOOKUP(B7,'Detailed Update'!B:I,7,FALSE) -> Central | K7: =VLOOKUP(B7,'Detailed Update'!B:I,8,FALSE) -> Riyadh | L7: Approved | M7: =VLOOKUP(B7,'Detailed Update'!B:T,11,FALSE) -> 45235 | N7: =VLOOKUP(B7,'Detailed Update'!B:T,12,FALSE) -> 45733 | O7: =VLOOKUP(B7,'Detailed Update'!B:T,13,FALSE) -> 45733 | P7: =VLOOKUP(B7,'Detailed Update'!B:U,20,FALSE) -> TCC Received.
A8: =A7+1 -> 5 | B8: PE-233 | C8: =VLOOKUP(B8,'Detailed Update'!B:C,2,FALSE) -> Tabarjal 380KV BSP Expn. | D8: Malik Qarioutyee | E8: 44542 | F8: 1 | G8: 0.99 | H8: =G8-F8 -> -0.01 | I8: =VLOOKUP(B8,'Detailed Update'!B:I,6,FALSE) -> SEC | J8: =VLOOKUP(B8,'Detailed Update'!B:I,7,FALSE) -> Central | K8: =VLOOKUP(B8,'Detailed Update'!B:I,8,FALSE) -> Riyadh | L8: Approved | M8: =VLOOKUP(B8,'Detailed Update'!B:T,11,FALSE) -> 45272 | N8: =VLOOKUP(B8,'Detailed Update'!B:T,12,FALSE) -> 46021 | O8: =VLOOKUP(B8,'Detailed Update'!B:T,13,FALSE) -> 46233 | P8: =VLOOKUP(B8,'Detailed Update'!B:U,20,FALSE) -> Partial TCC received on 16-Jan-24
A9: =A8+1 -> 6 | B9: PE-245 | C9: =VLOOKUP(B9,'Detailed Update'!B:C,2,FALSE) -> Hail OHTL | D9: Rafa Awad Al Hassan | E9: 44788 | F9: 1 | G9: 0.9612 | H9: =G9-F9 -> -0.0388 | I9: =VLOOKUP(B9,'Detailed Update'!B:I,6,FALSE) -> SEC | J9: =VLOOKUP(B9,'Detailed Update'!B:I,7,FALSE) -> Central | K9: =VLOOKUP(B9,'Detailed Update'!B:I,8,FALSE) -> Riyadh | L9: Approved | M9: =VLOOKUP(B9,'Detailed Update'!B:T,11,FALSE) -> 45427 | N9: =VLOOKUP(B9,'Detailed Update'!B:T,12,FALSE) -> 45656 | O9: =VLOOKUP(B9,'Detailed Update'!B:T,13,FALSE) -> 46193 | P9: =VLOOKUP(B9,'Detailed Update'!B:U,20,FALSE) -> One line Energizaed. Another line by 20-Jun-26. Change Order approval is critical
A10: =A9+1 -> 7 | B10: PE-247 | C10: =VLOOKUP(B10,'Detailed Update'!B:C,2,FALSE) -> RIYADH SEDRA-2 | D10: Anas Derzy | E10: 44833 | F10: 1 | G10: 0.991 | H10: =G10-F10 -> -0.009 | I10: =VLOOKUP(B10,'Detailed Update'!B:I,6,FALSE) -> Roshn | J10: =VLOOKUP(B10,'Detailed Update'!B:I,7,FALSE) -> Central | K10: =VLOOKUP(B10,'Detailed Update'!B:I,8,FALSE) -> Riyadh | L10: Under Approval | M10: =VLOOKUP(B10,'Detailed Update'!B:T,11,FALSE) -> 45538 | N10: =VLOOKUP(B10,'Detailed Update'!B:T,12,FALSE) -> 45538 | O10: =VLOOKUP(B10,'Detailed Update'!B:T,13,FALSE) -> 45920 | P10: =VLOOKUP(B10,'Detailed Update'!B:U,20,FALSE) -> Partial TCC received & 90% invoice approved
A11: =A10+1 -> 8 | B11: PE-248 | C11: =VLOOKUP(B11,'Detailed Update'!B:C,2,FALSE) -> PP10 Conv. | D11: Rabei Mohamed Mohamed Attia Daoud | E11: 44847 | F11: 1 | G11: 0.9598 | H11: =G11-F11 -> -0.0402 | I11: =VLOOKUP(B11,'Detailed Update'!B:I,6,FALSE) -> SEC | J11: =VLOOKUP(B11,'Detailed Update'!B:I,7,FALSE) -> Central | K11: =VLOOKUP(B11,'Detailed Update'!B:I,8,FALSE) -> Riyadh | L11: Approved | M11: =VLOOKUP(B11,'Detailed Update'!B:T,11,FALSE) -> 45517 | N11: =VLOOKUP(B11,'Detailed Update'!B:T,12,FALSE) -> 46018 | O11: =VLOOKUP(B11,'Detailed Update'!B:T,13,FALSE) -> 46263 | P11: =VLOOKUP(B11,'Detailed Update'!B:U,20,FALSE) -> TCC milestone achieved. Certification not receied. Punchlist Clearance is critical
A12: =A11+1 -> 9 | B12: PE-255 | C12: =VLOOKUP(B12,'Detailed Update'!B:C,2,FALSE) -> 380kv D/C OHTL LILO SAAD OHTL | D12: Malik Al Qaryotee | E12: 44857 | F12: 0.9121 | G12: 0.7562 | H12: =G12-F12 -> -0.1559 | I12: =VLOOKUP(B12,'Detailed Update'!B:I,6,FALSE) -> SEC | J12: =VLOOKUP(B12,'Detailed Update'!B:I,7,FALSE) -> Central | K12: =VLOOKUP(B12,'Detailed Update'!B:I,8,FALSE) -> Riyadh | L12: Approved | M12: =VLOOKUP(B12,'Detailed Update'!B:T,11,FALSE) -> 45283 | N12: =VLOOKUP(B12,'Detailed Update'!B:T,12,FALSE) -> 45813 | O12: =VLOOKUP(B12,'Detailed Update'!B:T,13,FALSE) -> 46386 | P12: =VLOOKUP(B12,'Detailed Update'!B:U,20,FALSE) -> 1. Amendment for New circuit Arrangement at Tapping Point . 2. Outage requirements 3. Hardware fittings material for re-route portion
A13: =A12+1 -> 10 | B13: PE-256 | C13: =VLOOKUP(B13,'Detailed Update'!B:C,2,FALSE) -> Sudair PV 380KV BSP | D13: Tariq Mahmoud Ali Alsheyab | E13: 44867 | F13: 1 | G13: 0.7902 | H13: =G13-F13 -> -0.2098 | I13: =VLOOKUP(B13,'Detailed Update'!B:I,6,FALSE) -> SEC | J13: =VLOOKUP(B13,'Detailed Update'!B:I,7,FALSE) -> Central | K13: =VLOOKUP(B13,'Detailed Update'!B:I,8,FALSE) -> Riyadh | L13: Under Approval | M13: =VLOOKUP(B13,'Detailed Update'!B:T,11,FALSE) -> 45537 | N13: =VLOOKUP(B13,'Detailed Update'!B:T,12,FALSE) -> 45537 | O13: =VLOOKUP(B13,'Detailed Update'!B:T,13,FALSE) -> 46325 | P13: =VLOOKUP(B13,'Detailed Update'!B:U,20,FALSE) -> SS portion energized. Delay in Receiving Permit UGC works and inside PP9 works (MTO,LOA& ARAMCO Permits)
A14: =A13+1 -> 11 | B14: PE-259 | C14: =VLOOKUP(B14,'Detailed Update'!B:C,2,FALSE) -> WAAD AL SHAMAAL 380KV BSP | D14: Muhannad Ibrahim Al Heh | E14: 44871 | F14: 1 | G14: 0.9698 | H14: =G14-F14 -> -0.0302 | I14: =VLOOKUP(B14,'Detailed Update'!B:I,6,FALSE) -> SEC | J14: =VLOOKUP(B14,'Detailed Update'!B:I,7,FALSE) -> Central | K14: =VLOOKUP(B14,'Detailed Update'!B:I,8,FALSE) -> Riyadh | L14: Approved | M14: =VLOOKUP(B14,'Detailed Update'!B:T,11,FALSE) -> 45611 | N14: =VLOOKUP(B14,'Detailed Update'!B:T,12,FALSE) -> 45807 | O14: =VLOOKUP(B14,'Detailed Update'!B:T,13,FALSE) -> 46356 | P14: =VLOOKUP(B14,'Detailed Update'!B:U,20,FALSE) -> Paritally Energized on 09-Feb-26 | Delay in receiving outage to enrgize CKT 2 Wind to Waad Alshamaal & Wind to TABARJAL energization (expected by Oct 26)
A15: =A14+1 -> 12 | B15: PE-264 | C15: =VLOOKUP(B15,'Detailed Update'!B:C,2,FALSE) -> TABARJAL-B 13213.8 KV S/S IN JOUF | D15: Khalid Mohamed Aql | E15: 45063 | F15: 1 | G15: 0.9925 | H15: =G15-F15 -> -0.0075 | I15: =VLOOKUP(B15,'Detailed Update'!B:I,6,FALSE) -> SEC | J15: =VLOOKUP(B15,'Detailed Update'!B:I,7,FALSE) -> Central | K15: =VLOOKUP(B15,'Detailed Update'!B:I,8,FALSE) -> Riyadh | L15: Approved | M15: =VLOOKUP(B15,'Detailed Update'!B:T,11,FALSE) -> 45732 | N15: =VLOOKUP(B15,'Detailed Update'!B:T,12,FALSE) -> 45838 | O15: =VLOOKUP(B15,'Detailed Update'!B:T,13,FALSE) -> 46202 | P15: =VLOOKUP(B15,'Detailed Update'!B:U,20,FALSE) -> 1.Total of four circuits are planned; two are scheduled for energization by June 2026. 2.SE confirmation is still pending for the remaining two circuits.
A16: =A15+1 -> 13 | B16: PE-271 | C16: =VLOOKUP(B16,'Detailed Update'!B:C,2,FALSE) -> AL-DAR AL-BAIDHA 132/13.8KV SUB | D16: Hassan Ayloti | E16: 45120 | F16: 1 | G16: 0.985 | H16: =G16-F16 -> -0.015 | I16: =VLOOKUP(B16,'Detailed Update'!B:I,6,FALSE) -> SEC | J16: =VLOOKUP(B16,'Detailed Update'!B:I,7,FALSE) -> Central | K16: =VLOOKUP(B16,'Detailed Update'!B:I,8,FALSE) -> Riyadh | L16: Approved | M16: =VLOOKUP(B16,'Detailed Update'!B:T,11,FALSE) -> 45608 | N16: =VLOOKUP(B16,'Detailed Update'!B:T,12,FALSE) -> 46081 | O16: =VLOOKUP(B16,'Detailed Update'!B:T,13,FALSE) -> 46098 | P16: =VLOOKUP(B16,'Detailed Update'!B:U,20,FALSE) -> Energized on 17-Mar-26 | Other Circuit depends on Outage | Expected - 31-Oct-26
... A43: =A42+1 -> 40 | B43: PE-395 | C43: =VLOOKUP(B43,'Detailed Update'!B:C,2,FALSE) -> New Al- Wadi 132/13.8Kv substation #8224 and its Connection in Riyadh City | D43: Osama Mahood | E43: 46064 | F43: 0.0517 | G43: 0.0571 | H43: =G43-F43 -> 0.0054 | I43: =VLOOKUP(B43,'Detailed Update'!B:I,6,FALSE) -> SEC-COA | J43: =VLOOKUP(B43,'Detailed Update'!B:I,7,FALSE) -> Central | K43: =VLOOKUP(B43,'Detailed Update'!B:I,8,FALSE) -> Riyadh | L43: N/A | M43: =VLOOKUP(B43,'Detailed Update'!B:T,11,FALSE) -> 46671 | N43: =VLOOKUP(B43,'Detailed Update'!B:T,12,FALSE) -> 46671 | O43: =VLOOKUP(B43,'Detailed Update'!B:T,13,FALSE) -> 46695 | P43: =VLOOKUP(B43,'Detailed Update'!B:U,20,FALSE) -> 1- Civil construction and related engineering/design activities suspended due to site cavities discovered after Soil investigation report. 2- Under Ground cables radar scanning & cable route layout submission.
C44: EASTERN REGION UNIT (BASIL ALHAKAMI)
A45: =A43+1 -> 41 | B45: PE-214 | C45: =VLOOKUP(B45,'Detailed Update'!B:C,2,FALSE) -> UTHMANIYAH | D45: Munther Alkhatib | E45: =VLOOKUP(B45,'Detailed Update'!B:D,3,FALSE) -> 43884 | F45: =VLOOKUP(B45,'Detailed Update'!B:T,4,FALSE) -> 1 | G45: =VLOOKUP(B45,'Detailed Update'!B:T,5,FALSE) -> 0.999775 | H45: =G45-F45 -> -0.000225 | I45: =VLOOKUP(B45,'Detailed Update'!B:I,6,FALSE) -> Aramco | J45: =VLOOKUP(B45,'Detailed Update'!B:I,7,FALSE) -> Eastern | K45: =VLOOKUP(B45,'Detailed Update'!B:I,8,FALSE) -> Dammam | L45: Approved | M45: =VLOOKUP(B45,'Detailed Update'!B:T,11,FALSE) -> 45134 | N45: =VLOOKUP(B45,'Detailed Update'!B:T,12,FALSE) -> 45626 | O45: =VLOOKUP(B45,'Detailed Update'!B:T,13,FALSE) -> 45550 | P45: =VLOOKUP(B45,'Detailed Update'!B:U,20,FALSE) -> All Certificates Recieved FAC not Not applicable/MCC
A46: =A45+1 -> 42 | B46: PE-227 | C46: =VLOOKUP(B46,'Detailed Update'!B:C,2,FALSE) -> Ibn zahr Expn. | D46: Walid Khater | E46: =VLOOKUP(B46,'Detailed Update'!B:D,3,FALSE) -> 44357 | F46: =VLOOKUP(B46,'Detailed Update'!B:T,4,FALSE) -> 1 | G46: =VLOOKUP(B46,'Detailed Update'!B:T,5,FALSE) -> 0.88294 | H46: =G46-F46 -> -0.11706 | I46: =VLOOKUP(B46,'Detailed Update'!B:I,6,FALSE) -> SEC | J46: =VLOOKUP(B46,'Detailed Update'!B:I,7,FALSE) -> Eastern | K46: =VLOOKUP(B46,'Detailed Update'!B:I,8,FALSE) -> Dammam | L46: Approved | M46: =VLOOKUP(B46,'Detailed Update'!B:T,11,FALSE) -> 44814 | N46: =VLOOKUP(B46,'Detailed Update'!B:T,12,FALSE) -> 45412 | O46: =VLOOKUP(B46,'Detailed Update'!B:T,13,FALSE) -> 46331 | P46: =VLOOKUP(B46,'Detailed Update'!B:U,20,FALSE) -> -
A47: =A46+1 -> 43 | B47: PE-238 | C47: =VLOOKUP(B47,'Detailed Update'!B:C,2,FALSE) -> SWCC | BSP Portion | D47: Sami Abdou Sayed Atta | E47: =VLOOKUP(B47,'Detailed Update'!B:D,3,FALSE) -> 44704 | F47: =VLOOKUP(B47,'Detailed Update'!B:T,4,FALSE) -> 1 | G47: =VLOOKUP(B47,'Detailed Update'!B:T,5,FALSE) -> 0.981722 | H47: =G47-F47 -> -0.018278 | I47: =VLOOKUP(B47,'Detailed Update'!B:I,6,FALSE) -> SWCC | J47: =VLOOKUP(B47,'Detailed Update'!B:I,7,FALSE) -> Eastern | K47: =VLOOKUP(B47,'Detailed Update'!B:I,8,FALSE) -> Jubail | L47: Under Approval | M47: =VLOOKUP(B47,'Detailed Update'!B:T,11,FALSE) -> 45345 | N47: =VLOOKUP(B47,'Detailed Update'!B:T,12,FALSE) -> 45345 | O47: =VLOOKUP(B47,'Detailed Update'!B:T,13,FALSE) -> 46053 | P47: =VLOOKUP(B47,'Detailed Update'!B:U,20,FALSE) -> PAC Partially Recieved Waiting for final approval of Time Extension on Etimad For FAC
A48: =A47+1 -> 44 | B48: PE-239 | C48: =VLOOKUP(B48,'Detailed Update'!B:C,2,FALSE) -> SWCC | Solar Package | D48: Walid Khater | E48: =VLOOKUP(B48,'Detailed Update'!B:D,3,FALSE) -> 45336 | F48: =VLOOKUP(B48,'Detailed Update'!B:T,4,FALSE) -> 1 | G48: =VLOOKUP(B48,'Detailed Update'!B:T,5,FALSE) -> 0.907 | H48: =G48-F48 -> -0.093 | I48: =VLOOKUP(B48,'Detailed Update'!B:I,6,FALSE) -> SWCC | J48: =VLOOKUP(B48,'Detailed Update'!B:I,7,FALSE) -> Eastern | K48: =VLOOKUP(B48,'Detailed Update'!B:I,8,FALSE) -> Jubail | L48: Under Approval | M48: =VLOOKUP(B48,'Detailed Update'!B:T,11,FALSE) -> 45702 | N48: =VLOOKUP(B48,'Detailed Update'!B:T,12,FALSE) -> 45702 | O48: =VLOOKUP(B48,'Detailed Update'!B:T,13,FALSE) -> 46203 | P48: =VLOOKUP(B48,'Detailed Update'!B:U,20,FALSE) -> -
A49: =A48+1 -> 45 | B49: PE-277 | C49: =VLOOKUP(B49,'Detailed Update'!B:C,2,FALSE) -> Thuqbah BSP 380/115KV | D49: Mohammed Kutkut | E49: =VLOOKUP(B49,'Detailed Update'!B:D,3,FALSE) -> 45218 | F49: =VLOOKUP(B49,'Detailed Update'!B:T,4,FALSE) -> 0.98825 | G49: =VLOOKUP(B49,'Detailed Update'!B:T,5,FALSE) -> 0.966064 | H49: =G49-F49 -> -0.022186 | I49: =VLOOKUP(B49,'Detailed Update'!B:I,6,FALSE) -> SEC | J49: =VLOOKUP(B49,'Detailed Update'!B:I,7,FALSE) -> Eastern | K49: =VLOOKUP(B49,'Detailed Update'!B:I,8,FALSE) -> Thuqbah | L49: Approved | M49: =VLOOKUP(B49,'Detailed Update'!B:T,11,FALSE) -> 45766 | N49: =VLOOKUP(B49,'Detailed Update'!B:T,12,FALSE) -> 46173 | O49: =VLOOKUP(B49,'Detailed Update'!B:T,13,FALSE) -> 46173 | P49: =VLOOKUP(B49,'Detailed Update'!B:U,20,FALSE) -> -
A50: =A49+1 -> 46 | B50: PE-288 | C50: =VLOOKUP(B50,'Detailed Update'!B:C,2,FALSE) -> Repl. of Berry Gas Plant 230/115KV SS | D50: Moath Ahmad Mahmoud Almousa | E50: =VLOOKUP(B50,'Detailed Update'!B:D,3,FALSE) -> 45431 | F50: =VLOOKUP(B50,'Detailed Update'!B:T,4,FALSE) -> 0.92007823 | G50: =VLOOKUP(B50,'Detailed Update'!B:T,5,FALSE) -> 0.85511484 | H50: =G50-F50 -> -0.064963387 | I50: =VLOOKUP(B50,'Detailed Update'!B:I,6,FALSE) -> SEC | J50: =VLOOKUP(B50,'Detailed Update'!B:I,7,FALSE) -> Eastern | K50: =VLOOKUP(B50,'Detailed Update'!B:I,8,FALSE) -> Jubail | L50: Under Approval | M50: =VLOOKUP(B50,'Detailed Update'!B:T,11,FALSE) -> 46041 | N50: =VLOOKUP(B50,'Detailed Update'!B:T,12,FALSE) -> 46041 | O50: =VLOOKUP(B50,'Detailed Update'!B:T,13,FALSE) -> 46305 | P50: =VLOOKUP(B50,'Detailed Update'!B:U,20,FALSE) -> OHTL Portion after 11 months from SS which is shown here
A51: =A50+1 -> 47 | B51: PE-302 | C51: =VLOOKUP(B51,'Detailed Update'!B:C,2,FALSE) -> AL RAMES 380/115 KV BSP | D51: Mohamed Ali Hafez Aman | E51: =VLOOKUP(B51,'Detailed Update'!B:D,3,FALSE) -> 45218 | F51: =VLOOKUP(B51,'Detailed Update'!B:T,4,FALSE) -> 0.99474531 | G51: =VLOOKUP(B51,'Detailed Update'!B:T,5,FALSE) -> 0.99269133 | H51: =G51-F51 -> -0.0020539761 | I51: =VLOOKUP(B51,'Detailed Update'!B:I,6,FALSE) -> SEC | J51: =VLOOKUP(B51,'Detailed Update'!B:I,7,FALSE) -> Eastern | K51: =VLOOKUP(B51,'Detailed Update'!B:I,8,FALSE) -> Dammam | L51: Approved | M51: =VLOOKUP(B51,'Detailed Update'!B:T,11,FALSE) -> 45766 | N51: =VLOOKUP(B51,'Detailed Update'!B:T,12,FALSE) -> 46356 | O51: =VLOOKUP(B51,'Detailed Update'!B:T,13,FALSE) -> 46173 | P51: =VLOOKUP(B51,'Detailed Update'!B:U,20,FALSE) -> Expected TCC will be on 13 Dec 26 due to delay of FOC readiness (31 Aug 2026) / Disconnector Switch
A52: =A51+1 -> 48 | B52: PE-334 | C52: =VLOOKUP(B52,'Detailed Update'!B:C,2,FALSE) -> Ghazlan-3 BSP | D52: Mahmoud Abdelaal | E52: =VLOOKUP(B52,'Detailed Update'!B:D,3,FALSE) -> 45697 | F52: 0.9415 | G52: 0.3488 | H52: =G52-F52 -> -0.5927 | I52: =VLOOKUP(B52,'Detailed Update'!B:I,6,FALSE) -> SEC | J52: =VLOOKUP(B52,'Detailed Update'!B:I,7,FALSE) -> Eastern | K52: =VLOOKUP(B52,'Detailed Update'!B:I,8,FALSE) -> Ghazlan | L52: Under Approval | M52: =VLOOKUP(B52,'Detailed Update'!B:T,11,FALSE) -> 46212 | N52: =VLOOKUP(B52,'Detailed Update'!B:T,12,FALSE) -> 46212 | O52: =VLOOKUP(B52,'Detailed Update'!B:T,13,FALSE) -> 46500 | P52: =VLOOKUP(B52,'Detailed Update'!B:U,20,FALSE) -> Planned % is based on orginal baseline however we have a submitted revised schedule showing 80% used for internal reporting
A53: =A52+1 -> 49 | B53: PE-344 | C53: =VLOOKUP(B53,'Detailed Update'!B:C,2,FALSE) -> Nariyah BSP | D53: Mohamed Elhag | E53: =VLOOKUP(B53,'Detailed Update'!B:D,3,FALSE) -> 45715 | F53: =VLOOKUP(B53,'Detailed Update'!B:T,4,FALSE) -> 0.954856 | G53: =VLOOKUP(B53,'Detailed Update'!B:T,5,FALSE) -> 0.56828 | H53: =G53-F53 -> -0.386576 | I53: =VLOOKUP(B53,'Detailed Update'!B:I,6,FALSE) -> SEC | J53: =VLOOKUP(B53,'Detailed Update'!B:I,7,FALSE) -> Eastern | K53: =VLOOKUP(B53,'Detailed Update'!B:I,8,FALSE) -> Nariyah | L53: N/A | M53: =VLOOKUP(B53,'Detailed Update'!B:T,11,FALSE) -> 46291 | N53: =VLOOKUP(B53,'Detailed Update'!B:T,12,FALSE) -> 46291 | O53: =VLOOKUP(B53,'Detailed Update'!B:T,13,FALSE) -> 46544 | P53: =VLOOKUP(B53,'Detailed Update'!B:U,20,FALSE) -> Delayed due to the delivery of GIS equipment Delayed 2times 1st delay till 25-June-26 2nd Delay till 25-Aug-26
A54: =A53+1 -> 50 | B54: PE-355 | C54: =VLOOKUP(B54,'Detailed Update'!B:C,2,FALSE) -> Construction of King Saud Air Base Facilities | D54: Mohammed Kutkut | E54: =VLOOKUP(B54,'Detailed Update'!B:D,3,FALSE) -> 45879 | F54: =VLOOKUP(B54,'Detailed Update'!B:T,4,FALSE) -> 0.1757 | G54: =VLOOKUP(B54,'Detailed Update'!B:T,5,FALSE) -> 0.12 | H54: =G54-F54 -> -0.0557 | I54: =VLOOKUP(B54,'Detailed Update'!B:I,6,FALSE) -> RSAF | J54: =VLOOKUP(B54,'Detailed Update'!B:I,7,FALSE) -> Eastern | K54: =VLOOKUP(B54,'Detailed Update'!B:I,8,FALSE) -> Haffr Albatan | L54: N/A | M54: =VLOOKUP(B54,'Detailed Update'!B:T,11,FALSE) -> 46609 | N54: =VLOOKUP(B54,'Detailed Update'!B:T,12,FALSE) -> 46609 | O54: =VLOOKUP(B54,'Detailed Update'!B:T,13,FALSE) -> 46657 | P54: =VLOOKUP(B54,'Detailed Update'!B:U,20,FALSE) -> Only Scope Alfanar / There is no FAC only based on the 40 Months Completion
A55: =A54+1 -> 51 | B55: PE-304 | C55: =VLOOKUP(B55,'Detailed Update'!B:C,2,FALSE) -> 230/115kV SS | JUBAIL SW REPLACEMENT | D55: Munther Alkhatib | E55: =VLOOKUP(B55,'Detailed Update'!B:D,3,FALSE) -> 45900 | F55: =VLOOKUP(B55,'Detailed Update'!B:T,4,FALSE) -> 0.1969 | G55: =VLOOKUP(B55,'Detailed Update'!B:T,5,FALSE) -> 0.126 | H55: =G55-F55 -> -0.0709 | I55: =VLOOKUP(B55,'Detailed Update'!B:I,6,FALSE) -> SEC | J55: =VLOOKUP(B55,'Detailed Update'!B:I,7,FALSE) -> Eastern | K55: =VLOOKUP(B55,'Detailed Update'!B:I,8,FALSE) -> Jubail | L55: N/A | M55: =VLOOKUP(B55,'Detailed Update'!B:T,11,FALSE) -> 46630 | N55: =VLOOKUP(B55,'Detailed Update'!B:T,12,FALSE) -> 46630 | O55: =VLOOKUP(B55,'Detailed Update'!B:T,13,FALSE) -> 46870 | P55: =VLOOKUP(B55,'Detailed Update'!B:U,20,FALSE) -> Delayed due to site accessibility issues and Water leakage incident
A56: =A55+1 -> 52 | B56: PE-181 | C56: =VLOOKUP(B56,'Detailed Update'!B:C,2,FALSE) -> EPC OF PRIMARY ELECTRICAL SUSBSTATION #3 | D56: Sami Atta | E56: =VLOOKUP(B56,'Detailed Update'!B:D,3,FALSE) -> 43884 | F56: =VLOOKUP(B56,'Detailed Update'!B:T,4,FALSE) -> 1 | G56: =VLOOKUP(B56,'Detailed Update'!B:T,5,FALSE) -> 1 | H56: =G56-F56 -> 0 | I56: =VLOOKUP(B56,'Detailed Update'!B:I,6,FALSE) -> RC | J56: =VLOOKUP(B56,'Detailed Update'!B:I,7,FALSE) -> Eastern | K56: =VLOOKUP(B56,'Detailed Update'!B:I,8,FALSE) -> Ras Al Khair | L56: Approved | M56: =VLOOKUP(B56,'Detailed Update'!B:T,11,FALSE) -> 44560 | N56: =VLOOKUP(B56,'Detailed Update'!B:T,12,FALSE) -> 44560 | O56: =VLOOKUP(B56,'Detailed Update'!B:T,13,FALSE) -> 44552 | P56: =VLOOKUP(B56,'Detailed Update'!B:U,20,FALSE) -> All Certificates Recieved
A57: =A56+1 -> 53 | B57: PE-199 | C57: =VLOOKUP(B57,'Detailed Update'!B:C,2,FALSE) -> SPARK 380/115/13.8KV BSP | D57: Walid Ahmed Khater | E57: =VLOOKUP(B57,'Detailed Update'!B:D,3,FALSE) -> 43435 | F57: =VLOOKUP(B57,'Detailed Update'!B:T,4,FALSE) -> 1 | G57: =VLOOKUP(B57,'Detailed Update'!B:T,5,FALSE) -> 1 | H57: =G57-F57 -> 0 | I57: =VLOOKUP(B57,'Detailed Update'!B:I,6,FALSE) -> SEC | J57: =VLOOKUP(B57,'Detailed Update'!B:I,7,FALSE) -> Eastern | K57: =VLOOKUP(B57,'Detailed Update'!B:I,8,FALSE) -> Abqaiq | L57: Approved | M57: =VLOOKUP(B57,'Detailed Update'!B:T,11,FALSE) -> 44104 | N57: =VLOOKUP(B57,'Detailed Update'!B:T,12,FALSE) -> 44104 | O57: =VLOOKUP(B57,'Detailed Update'!B:T,13,FALSE) -> 44316 | P57: =VLOOKUP(B57,'Detailed Update'!B:U,20,FALSE) -> All Certificates Recieved
A58: =A57+1 -> 54 | B58: PE-213 | C58: =VLOOKUP(B58,'Detailed Update'!B:C,2,FALSE) -> Construction Of Hawayah 380 KV S/S | D58: Moath Ahmad Mahmoud Almousa | E58: =VLOOKUP(B58,'Detailed Update'!B:D,3,FALSE) -> 43853 | F58: =VLOOKUP(B58,'Detailed Update'!B:T,4,FALSE) -> 1 | G58: =VLOOKUP(B58,'Detailed Update'!B:T,5,FALSE) -> 1 | H58: =G58-F58 -> 0 | I58: =VLOOKUP(B58,'Detailed Update'!B:I,6,FALSE) -> SEC | J58: =VLOOKUP(B58,'Detailed Update'!B:I,7,FALSE) -> Eastern | K58: =VLOOKUP(B58,'Detailed Update'!B:I,8,FALSE) -> Huwyha | L58: N/A | M58: =VLOOKUP(B58,'Detailed Update'!B:T,11,FALSE) -> HUW : 30-Jul-22 UQA : 30-Apr-23 | N58: =VLOOKUP(B58,'Detailed Update'!B:T,12,FALSE) -> HUW : 30-Jul-22 UQA : 30-Apr-23 | O58: =VLOOKUP(B58,'Detailed Update'!B:T,13,FALSE) -> HUW : 30-Sep-22 UQA :30-Aug-26 | P58: =VLOOKUP(B58,'Detailed Update'!B:U,20,FALSE) -> P1: All Certificates Recieved P2: No Certificates Recieved
A59: =A58+1 -> 55 | B59: PE-229 | C59: =VLOOKUP(B59,'Detailed Update'!B:C,2,FALSE) -> Construction of Temporary Rail Line (CO project of PE-181) | D59: Sami Atta | E59: =VLOOKUP(B59,'Detailed Update'!B:D,3,FALSE) -> 0 | F59: =VLOOKUP(B59,'Detailed Update'!B:T,4,FALSE) -> 1 | G59: =VLOOKUP(B59,'Detailed Update'!B:T,5,FALSE) -> 1 | H59: =G59-F59 -> 0 | I59: =VLOOKUP(B59,'Detailed Update'!B:I,6,FALSE) -> RC | J59: =VLOOKUP(B59,'Detailed Update'!B:I,7,FALSE) -> Eastern | K59: =VLOOKUP(B59,'Detailed Update'!B:I,8,FALSE) -> Ras Al Khair | L59: Approved | M59: =VLOOKUP(B59,'Detailed Update'!B:T,11,FALSE) -> NA | N59: =VLOOKUP(B59,'Detailed Update'!B:T,12,FALSE) -> NA | O59: =VLOOKUP(B59,'Detailed Update'!B:T,13,FALSE) -> NA | P59: =VLOOKUP(B59,'Detailed Update'!B:U,20,FALSE) -> All Certificates Recieved
A60: =A59+1 -> 56 | B60: PE-240 | C60: =VLOOKUP(B60,'Detailed Update'!B:C,2,FALSE) -> JSWCC|OHTL Package | D60: Moath Ahmad Mahmoud Almousa | E60: =VLOOKUP(B60,'Detailed Update'!B:D,3,FALSE) -> 44704 | F60: =VLOOKUP(B60,'Detailed Update'!B:T,4,FALSE) -> 1 | G60: =VLOOKUP(B60,'Detailed Update'!B:T,5,FALSE) -> 1 | H60: =G60-F60 -> 0 | I60: =VLOOKUP(B60,'Detailed Update'!B:I,6,FALSE) -> SWCC | J60: =VLOOKUP(B60,'Detailed Update'!B:I,7,FALSE) -> Eastern | K60: =VLOOKUP(B60,'Detailed Update'!B:I,8,FALSE) -> Jubail | L60: Under Approval | M60: =VLOOKUP(B60,'Detailed Update'!B:T,11,FALSE) -> 45345 | N60: =VLOOKUP(B60,'Detailed Update'!B:T,12,FALSE) -> 45345 | O60: =VLOOKUP(B60,'Detailed Update'!B:T,13,FALSE) -> 46053 | P60: =VLOOKUP(B60,'Detailed Update'!B:U,20,FALSE) -> PAC Partially Recieved Waiting for final approval of Time Extension on Etimad For FAC Pending on PE-238
A61: =A60+1 -> 57 | B61: PE-366 | C61: =VLOOKUP(B61,'Detailed Update'!B:C,2,FALSE) -> Qulayyib 380 kV BSP | D61: Tarig Mohammed | E61: =VLOOKUP(B61,'Detailed Update'!B:D,3,FALSE) -> 46113 | F61: =VLOOKUP(B61,'Detailed Update'!B:T,4,FALSE) -> 0.06743 | G61: =VLOOKUP(B61,'Detailed Update'!B:T,5,FALSE) -> 0.03998 | H61: =G61-F61 -> -0.02745 | I61: =VLOOKUP(B61,'Detailed Update'!B:I,6,FALSE) -> MGC-Mutlaq Al Gowairi Company | J61: =VLOOKUP(B61,'Detailed Update'!B:I,7,FALSE) -> Eastern | K61: =VLOOKUP(B61,'Detailed Update'!B:I,8,FALSE) -> Qulayyib Area | L61: N/A | M61: =VLOOKUP(B61,'Detailed Update'!B:T,11,FALSE) -> 46905 | N61: =VLOOKUP(B61,'Detailed Update'!B:T,12,FALSE) -> 46905 | O61: =VLOOKUP(B61,'Detailed Update'!B:T,13,FALSE) -> 46943 | P61: =VLOOKUP(B61,'Detailed Update'!B:U,20,FALSE) -> -
A62: =A61+1 -> 58 | B62: PE-354 | C62: =VLOOKUP(B62,'Detailed Update'!B:C,2,FALSE) -> Construction of NEW VSC HVDC Overhead Transmission Line for EOA-COA Link 1 | D62: Moath Ahmad Mahmoud Almousa | E62: =VLOOKUP(B62,'Detailed Update'!B:D,3,FALSE) -> 46146 | F62: =VLOOKUP(B62,'Detailed Update'!B:T,4,FALSE) -> 0.029387 | G62: =VLOOKUP(B62,'Detailed Update'!B:T,5,FALSE) -> 0.01827 | H62: =G62-F62 -> -0.011117 | I62: =VLOOKUP(B62,'Detailed Update'!B:I,6,FALSE) -> SEC | J62: =VLOOKUP(B62,'Detailed Update'!B:I,7,FALSE) -> Eastern | K62: =VLOOKUP(B62,'Detailed Update'!B:I,8,FALSE) -> Nariyah | L62: N/A | M62: =VLOOKUP(B62,'Detailed Update'!B:T,11,FALSE) -> 47061 | N62: =VLOOKUP(B62,'Detailed Update'!B:T,12,FALSE) -> 47061 | O62: =VLOOKUP(B62,'Detailed Update'!B:T,13,FALSE) -> 47079 | P62: -
C63: WESTERN REGION UNIT (MOHAMMED ALBAZIE)
A64: =A62+1 -> 59 | B64: PE-243 | C64: =VLOOKUP(B64,'Detailed Update'!B:C,2,FALSE) -> Installation of Dynamic Reactive Power Compensation(DRPC) at Tabuk 380KV BSP | D64: Shafqat Zia | E64: =VLOOKUP(B64,'Detailed Update'!B:D,3,FALSE) -> 44700 | F64: =VLOOKUP(B64,'Detailed Update'!B:T,4,FALSE) -> 1 | G64: =VLOOKUP(B64,'Detailed Update'!B:T,5,FALSE) -> 1 | H64: =G64-F64 -> 0 | I64: =VLOOKUP(B64,'Detailed Update'!B:I,6,FALSE) -> SEC | J64: =VLOOKUP(B64,'Detailed Update'!B:I,7,FALSE) -> Western | K64: =VLOOKUP(B64,'Detailed Update'!B:I,8,FALSE) -> Tabuk | L64: N/A | M64: =VLOOKUP(B64,'Detailed Update'!B:T,11,FALSE) -> 45492 | N64: =VLOOKUP(B64,'Detailed Update'!B:T,12,FALSE) -> 45777 | O64: =VLOOKUP(B64,'Detailed Update'!B:T,13,FALSE) -> 45777 | P64: =VLOOKUP(B64,'Detailed Update'!B:U,20,FALSE) -> Energization done without TSC Panel, TCC received. Partial PAC (21-Jan-2026) also received; Balance PAC & FAC upon delivery of remaining TSC Panel; Alfanar requested for FAC invoice and under discussion with SEC.
A65: =A64+1 -> 60 | B65: PE-241 | C65: =VLOOKUP(B65,'Detailed Update'!B:C,2,FALSE) -> Expansion of Existing Yanbu Central (YCNT) | D65: Zohaib Iqbal | E65: =VLOOKUP(B65,'Detailed Update'!B:D,3,FALSE) -> 44598 | F65: =VLOOKUP(B65,'Detailed Update'!B:T,4,FALSE) -> 1 | G65: =VLOOKUP(B65,'Detailed Update'!B:T,5,FALSE) -> 0.989 | H65: =G65-F65 -> -0.011 | I65: =VLOOKUP(B65,'Detailed Update'!B:I,6,FALSE) -> SEC | J65: =VLOOKUP(B65,'Detailed Update'!B:I,7,FALSE) -> Western | K65: =VLOOKUP(B65,'Detailed Update'!B:I,8,FALSE) -> Yanbu,Umluj& Alwajh | L65: N/A | M65: =VLOOKUP(B65,'Detailed Update'!B:T,11,FALSE) -> 45297 | N65: =VLOOKUP(B65,'Detailed Update'!B:T,12,FALSE) -> 45565 | O65: =VLOOKUP(B65,'Detailed Update'!B:T,13,FALSE) -> 45565 | P65: =VLOOKUP(B65,'Detailed Update'!B:U,20,FALSE) -> PAC received, not yet energized due to SE shutdown issues for all the area
A66: =A65+1 -> 61 | B66: PE-257 | C66: =VLOOKUP(B66,'Detailed Update'!B:C,2,FALSE) -> Expansions of Existing MHD 380 KV BSP | D66: Omar Samman | E66: =VLOOKUP(B66,'Detailed Update'!B:D,3,FALSE) -> 44868 | F66: =VLOOKUP(B66,'Detailed Update'!B:T,4,FALSE) -> 1 | G66: =VLOOKUP(B66,'Detailed Update'!B:T,5,FALSE) -> 0.9989 | H66: =G66-F66 -> -0.0011 | I66: =VLOOKUP(B66,'Detailed Update'!B:I,6,FALSE) -> SEC | J66: =VLOOKUP(B66,'Detailed Update'!B:I,7,FALSE) -> Western | K66: =VLOOKUP(B66,'Detailed Update'!B:I,8,FALSE) -> Madinah | L66: N/A | M66: =VLOOKUP(B66,'Detailed Update'!B:T,11,FALSE) -> 45415 | N66: =VLOOKUP(B66,'Detailed Update'!B:T,12,FALSE) -> 45960 | O66: =VLOOKUP(B66,'Detailed Update'!B:T,13,FALSE) -> 46021 | P66: =VLOOKUP(B66,'Detailed Update'!B:U,20,FALSE) -> As-built drawings under SEC review & approval. FAC certification waiting from SE; Request for issuance of FAC / Commitment for Completion of Outstanding Work was submitted on 20-Jul-26.
A67: =A66+1 -> 62 | B67: PE-258 | C67: =VLOOKUP(B67,'Detailed Update'!B:C,2,FALSE) -> Taif East Governorate Project | D67: Mahmoud Sobhy El Sayed | E67: =VLOOKUP(B67,'Detailed Update'!B:D,3,FALSE) -> 44882 | F67: =VLOOKUP(B67,'Detailed Update'!B:T,4,FALSE) -> 1 | G67: =VLOOKUP(B67,'Detailed Update'!B:T,5,FALSE) -> 0.9 | H67: =G67-F67 -> -0.1 | I67: =VLOOKUP(B67,'Detailed Update'!B:I,6,FALSE) -> SEC | J67: =VLOOKUP(B67,'Detailed Update'!B:I,7,FALSE) -> Western | K67: =VLOOKUP(B67,'Detailed Update'!B:I,8,FALSE) -> Taif | L67: N/A | M67: =VLOOKUP(B67,'Detailed Update'!B:T,11,FALSE) -> 45399 | N67: =VLOOKUP(B67,'Detailed Update'!B:T,12,FALSE) -> 45643 | O67: =VLOOKUP(B67,'Detailed Update'!B:T,13,FALSE) -> 46295 | P67: =VLOOKUP(B67,'Detailed Update'!B:U,20,FALSE) -> 1. EOT-1 Approved upto 14-Dec-24, EOT-2 submitted on 12th Aug 25, TCC upto 17th Jun 26. (Under SEC Approval). EOT to be resubmitted. 2. SAS testing pending due to EWS V.O finalization and delivery (V.O) 3. OHTL Line readiness pending from SE, no clarity on readiness
A68: =A67+1 -> 63 | B68: PE-270 | C68: =VLOOKUP(B68,'Detailed Update'!B:C,2,FALSE) -> 110/13.8KV HARAZAT SUB JEDDAH | D68: Muhammad Ilyas | E68: =VLOOKUP(B68,'Detailed Update'!B:D,3,FALSE) -> 45120 | F68: =VLOOKUP(B68,'Detailed Update'!B:T,4,FALSE) -> 1 | G68: =VLOOKUP(B68,'Detailed Update'!B:T,5,FALSE) -> 0.9841 | H68: =G68-F68 -> -0.0159 | I68: =VLOOKUP(B68,'Detailed Update'!B:I,6,FALSE) -> SEC | J68: =VLOOKUP(B68,'Detailed Update'!B:I,7,FALSE) -> Western | K68: =VLOOKUP(B68,'Detailed Update'!B:I,8,FALSE) -> Jeddah | L68: N/A | M68: =VLOOKUP(B68,'Detailed Update'!B:T,11,FALSE) -> 45609 | N68: =VLOOKUP(B68,'Detailed Update'!B:T,12,FALSE) -> 45729 | O68: =VLOOKUP(B68,'Detailed Update'!B:T,13,FALSE) -> 45867 | P68: =VLOOKUP(B68,'Detailed Update'!B:U,20,FALSE) -> Remote End Works: 1. Installation of Telecom Panels completed, testing will be done, once line readiness from client. (Dependent on Line Readiness from Client) 2. Final Settings of Line Protection Panels. (Dependent on Line Readiness from Client) Punchlist & As built works are in progress, completion date 30-Sep-26. Punchlist:Total 309 nos, 295 Completed, 5 nos ready to close. Asbuilt: 90% completed.
A69: =A68+1 -> 64 | B69: PE-290 | C69: =VLOOKUP(B69,'Detailed Update'!B:C,2,FALSE) -> Fadelah 110/13.8KV SS - JEDDAH | D69: Khaled Abdelaty Hassan Emara Shehata | E69: =VLOOKUP(B69,'Detailed Update'!B:D,3,FALSE) -> 45131 | F69: =VLOOKUP(B69,'Detailed Update'!B:T,4,FALSE) -> 1 | G69: =VLOOKUP(B69,'Detailed Update'!B:T,5,FALSE) -> 0.9842 | H69: =G69-F69 -> -0.0158 | I69: =VLOOKUP(B69,'Detailed Update'!B:I,6,FALSE) -> SEC | J69: =VLOOKUP(B69,'Detailed Update'!B:I,7,FALSE) -> Western | K69: =VLOOKUP(B69,'Detailed Update'!B:I,8,FALSE) -> Jeddah | L69: N/A | M69: =VLOOKUP(B69,'Detailed Update'!B:T,11,FALSE) -> 45620 | N69: =VLOOKUP(B69,'Detailed Update'!B:T,12,FALSE) -> 45924 | O69: =VLOOKUP(B69,'Detailed Update'!B:T,13,FALSE) -> 45834 | P69: =VLOOKUP(B69,'Detailed Update'!B:U,20,FALSE) -> 1) Energization done with temporary line, (Permanent line readiness Dependent on Client). 2) AMI integration with WRCC. (Dependent on Line Readiness from Client). 3) Modon GIS extension bays (Shutdown -Relay setting ) 85% completed. Punchlist & As built works are in progress, completion date 30-Sep-26. Punch points : Out of 10, 2 completed, 3 ready to close. As built status: out of 12, 12 ready to close.
A70: =A69+1 -> 65 | B70: PE-254 | C70: =VLOOKUP(B70,'Detailed Update'!B:C,2,FALSE) -> HENAKIYAH BSP 380 KV | D70: Mahmoud Sobhy El Sayed | E70: =VLOOKUP(B70,'Detailed Update'!B:D,3,FALSE) -> 44861 | F70: =VLOOKUP(B70,'Detailed Update'!B:T,4,FALSE) -> 1 | G70: =VLOOKUP(B70,'Detailed Update'!B:T,5,FALSE) -> 1 | H70: =G70-F70 -> 0 | I70: =VLOOKUP(B70,'Detailed Update'!B:I,6,FALSE) -> SEC | J70: =VLOOKUP(B70,'Detailed Update'!B:I,7,FALSE) -> Western | K70: =VLOOKUP(B70,'Detailed Update'!B:I,8,FALSE) -> Madinah | L70: N/A | M70: =VLOOKUP(B70,'Detailed Update'!B:T,11,FALSE) -> 45562 | N70: =VLOOKUP(B70,'Detailed Update'!B:T,12,FALSE) -> 45657 | O70: =VLOOKUP(B70,'Detailed Update'!B:T,13,FALSE) -> 45754 | P70: =VLOOKUP(B70,'Detailed Update'!B:U,20,FALSE) -> FAC received
A71: =A70+1 -> 66 | B71: PE-260 | C71: =VLOOKUP(B71,'Detailed Update'!B:C,2,FALSE) -> Sanabel con.at Jeddah | D71: Abdelazeem Morsy | E71: =VLOOKUP(B71,'Detailed Update'!B:D,3,FALSE) -> 44924 | F71: =VLOOKUP(B71,'Detailed Update'!B:T,4,FALSE) -> 1 | G71: =VLOOKUP(B71,'Detailed Update'!B:T,5,FALSE) -> 0.975 | H71: =G71-F71 -> -0.025 | I71: =VLOOKUP(B71,'Detailed Update'!B:I,6,FALSE) -> SEC | J71: =VLOOKUP(B71,'Detailed Update'!B:I,7,FALSE) -> Western | K71: =VLOOKUP(B71,'Detailed Update'!B:I,8,FALSE) -> Jeddah | L71: Approved | M71: =VLOOKUP(B71,'Detailed Update'!B:T,11,FALSE) -> 45594 | N71: =VLOOKUP(B71,'Detailed Update'!B:T,12,FALSE) -> 45687 | O71: =VLOOKUP(B71,'Detailed Update'!B:T,13,FALSE) -> 45992 | P71: =VLOOKUP(B71,'Detailed Update'!B:U,20,FALSE) -> SAS Configuration and testing pending, due to AES team mobilization pending
A72: =A71+1 -> 67 | B72: PE-262 | C72: =VLOOKUP(B72,'Detailed Update'!B:C,2,FALSE) -> Reinf. of Thuwal Town KAUST 2 | D72: Abdelazeem Morsy | E72: =VLOOKUP(B72,'Detailed Update'!B:D,3,FALSE) -> 44924 | F72: =VLOOKUP(B72,'Detailed Update'!B:T,4,FALSE) -> 1 | G72: =VLOOKUP(B72,'Detailed Update'!B:T,5,FALSE) -> 0.9696 | H72: =G72-F72 -> -0.0304 | I72: =VLOOKUP(B72,'Detailed Update'!B:I,6,FALSE) -> SEC | J72: =VLOOKUP(B72,'Detailed Update'!B:I,7,FALSE) -> Western | K72: =VLOOKUP(B72,'Detailed Update'!B:I,8,FALSE) -> Jeddah | L72: Approved | M72: =VLOOKUP(B72,'Detailed Update'!B:T,11,FALSE) -> 45533 | N72: =VLOOKUP(B72,'Detailed Update'!B:T,12,FALSE) -> 45656 | O72: =VLOOKUP(B72,'Detailed Update'!B:T,13,FALSE) -> 45992 | P72: =VLOOKUP(B72,'Detailed Update'!B:U,20,FALSE) -> SAS Configuration and testing pending
A73: =A72+1 -> 68 | B73: PE-296 | C73: =VLOOKUP(B73,'Detailed Update'!B:C,2,FALSE) -> Waly Alahad-4 110/13.8KV SS | D73: Moustafa Elkayyal | E73: =VLOOKUP(B73,'Detailed Update'!B:D,3,FALSE) -> 45218 | F73: =VLOOKUP(B73,'Detailed Update'!B:T,4,FALSE) -> 1 | G73: =VLOOKUP(B73,'Detailed Update'!B:T,5,FALSE) -> 0.9453 | H73: =G73-F73 -> -0.0547 | I73: =VLOOKUP(B73,'Detailed Update'!B:I,6,FALSE) -> SEC | J73: =VLOOKUP(B73,'Detailed Update'!B:I,7,FALSE) -> Western | K73: =VLOOKUP(B73,'Detailed Update'!B:I,8,FALSE) -> Makkah | L73: N/A | M73: =VLOOKUP(B73,'Detailed Update'!B:T,11,FALSE) -> 45707 | N73: =VLOOKUP(B73,'Detailed Update'!B:T,12,FALSE) -> 45980 | O73: =VLOOKUP(B73,'Detailed Update'!B:T,13,FALSE) -> 45980 | P73: =VLOOKUP(B73,'Detailed Update'!B:U,20,FALSE) -> 1) Line readiness pending from SEC
A74: =A73+1 -> 69 | B74: PE-281 | C74: =VLOOKUP(B74,'Detailed Update'!B:C,2,FALSE) -> 110KV SS - KAEC-3 | D74: Hossam Amin | E74: =VLOOKUP(B74,'Detailed Update'!B:D,3,FALSE) -> 45442 | F74: =VLOOKUP(B74,'Detailed Update'!B:T,4,FALSE) -> 1 | G74: =VLOOKUP(B74,'Detailed Update'!B:T,5,FALSE) -> 0.99 | H74: =G74-F74 -> -0.01 | I74: =VLOOKUP(B74,'Detailed Update'!B:I,6,FALSE) -> SEC | J74: =VLOOKUP(B74,'Detailed Update'!B:I,7,FALSE) -> Western | K74: =VLOOKUP(B74,'Detailed Update'!B:I,8,FALSE) -> Jeddah | L74: N/A | M74: =VLOOKUP(B74,'Detailed Update'!B:T,11,FALSE) -> 45991 | N74: =VLOOKUP(B74,'Detailed Update'!B:T,12,FALSE) -> 45991 | O74: =VLOOKUP(B74,'Detailed Update'!B:T,13,FALSE) -> 45991 | P74: =VLOOKUP(B74,'Detailed Update'!B:U,20,FALSE) -> TCC, PAC Received. FAC Letter Submitted to Client
A75: =A74+1 -> 70 | B75: PE-280 | C75: =VLOOKUP(B75,'Detailed Update'!B:C,2,FALSE) -> 110KV SS - KAEC-2 | D75: Hossam Amin | E75: =VLOOKUP(B75,'Detailed Update'!B:D,3,FALSE) -> 45442 | F75: =VLOOKUP(B75,'Detailed Update'!B:T,4,FALSE) -> 1 | G75: =VLOOKUP(B75,'Detailed Update'!B:T,5,FALSE) -> 1 | H75: =G75-F75 -> 0 | I75: =VLOOKUP(B75,'Detailed Update'!B:I,6,FALSE) -> SEC | J75: =VLOOKUP(B75,'Detailed Update'!B:I,7,FALSE) -> Western | K75: =VLOOKUP(B75,'Detailed Update'!B:I,8,FALSE) -> Jeddah | L75: N/A | M75: =VLOOKUP(B75,'Detailed Update'!B:T,11,FALSE) -> 45991 | N75: =VLOOKUP(B75,'Detailed Update'!B:T,12,FALSE) -> 45991 | O75: =VLOOKUP(B75,'Detailed Update'!B:T,13,FALSE) -> 45991 | P75: =VLOOKUP(B75,'Detailed Update'!B:U,20,FALSE) -> FAC received
A76: =A75+1 -> 71 | B76: PE-185 | C76: =VLOOKUP(B76,'Detailed Update'!B:C,2,FALSE) -> NG Taif | D76: Omar Samman | E76: =VLOOKUP(B76,'Detailed Update'!B:D,3,FALSE) -> 43156 | F76: =VLOOKUP(B76,'Detailed Update'!B:T,4,FALSE) -> 1 | G76: =VLOOKUP(B76,'Detailed Update'!B:T,5,FALSE) -> 0.9965 | H76: =G76-F76 -> -0.0035 | I76: =VLOOKUP(B76,'Detailed Update'!B:I,6,FALSE) -> NG | J76: =VLOOKUP(B76,'Detailed Update'!B:I,7,FALSE) -> Western | K76: =VLOOKUP(B76,'Detailed Update'!B:I,8,FALSE) -> Taif | L76: Under Approval | M76: =VLOOKUP(B76,'Detailed Update'!B:T,11,FALSE) -> NA | N76: =VLOOKUP(B76,'Detailed Update'!B:T,12,FALSE) -> NA | O76: =VLOOKUP(B76,'Detailed Update'!B:T,13,FALSE) -> NA | P76: =VLOOKUP(B76,'Detailed Update'!B:U,20,FALSE) -> EOT: Contract amendment approved,PCC on 14th Jul 25, EOT-2 submitted on 4th Nov 25, with 8 months (PCC: 14th Mar 26), Under SEC approval 1) All cable ceiling end joints works replacing works in progress, expected compeltion by 30th May 26. 2) Remote end-1 final setting done, Remote end 2 final setting completion by 10th May. 3) HV Test and end to end test pending expected completion by 15th Jun and 30th Jun
... A88: =A87+1 -> 83 | B88: PE-295 | C88: =VLOOKUP(B88,'Detailed Update'!B:C,2,FALSE) -> Interconnection of AJM-1 (New Jamoom) | D88: Abdelazeem Morsy | E88: =VLOOKUP(B88,'Detailed Update'!B:D,3,FALSE) -> 45299 | F88: =VLOOKUP(B88,'Detailed Update'!B:T,4,FALSE) -> 1 | G88: =VLOOKUP(B88,'Detailed Update'!B:T,5,FALSE) -> 0.9052 | H88: =G88-F88 -> -0.0948 | I88: =VLOOKUP(B88,'Detailed Update'!B:I,6,FALSE) -> SEC | J88: =VLOOKUP(B88,'Detailed Update'!B:I,7,FALSE) -> Western | K88: =VLOOKUP(B88,'Detailed Update'!B:I,8,FALSE) -> Makkah | L88: N/A | M88: =VLOOKUP(B88,'Detailed Update'!B:T,11,FALSE) -> 46120 | N88: =VLOOKUP(B88,'Detailed Update'!B:T,12,FALSE) -> 46120 | O88: =VLOOKUP(B88,'Detailed Update'!B:T,13,FALSE) -> 46120 | P88: =VLOOKUP(B88,'Detailed Update'!B:U,20,FALSE) -> 1) T.C.C received. 2)Shutdown required for Connecting existing GIS to new GIS bay, expected in Aug-26.
A89: =A88+1 -> 84 | B89: PE-301 | C89: =VLOOKUP(B89,'Detailed Update'!B:C,2,FALSE) -> Expansion of Mowaih PV 380kV BSP | D89: Ahmed Aboelseoud | E89: =VLOOKUP(B89,'Detailed Update'!B:D,3,FALSE) -> 45551 | F89: =VLOOKUP(B89,'Detailed Update'!B:T,4,FALSE) -> 1 | G89: 0.89 | H89: =G89-F89 -> -0.11 | I89: =VLOOKUP(B89,'Detailed Update'!B:I,6,FALSE) -> SEC | J89: =VLOOKUP(B89,'Detailed Update'!B:I,7,FALSE) -> Western | K89: =VLOOKUP(B89,'Detailed Update'!B:I,8,FALSE) -> Mowaih | L89: Under Approval | M89: =VLOOKUP(B89,'Detailed Update'!B:T,11,FALSE) -> 45946 | N89: =VLOOKUP(B89,'Detailed Update'!B:T,12,FALSE) -> 45946 | O89: =VLOOKUP(B89,'Detailed Update'!B:T,13,FALSE) -> 46264 | P89: =VLOOKUP(B89,'Detailed Update'!B:U,20,FALSE) -> 1) EOT-1 submitted on 16th Oct 25, with TCC Date on 27-5-26. Rejected by SEC on 21-Oct-25, Resubmitted, under approval with SE. 2) TCC delayed by SE, Due to SE-MOD time extension approval 2) 48 V DC system: FAT done delivery delayed expected delivery in Sep-26 3) Remote End Substations are not ready
A90: =A89+1 -> 85 | B90: PE-305 | C90: =VLOOKUP(B90,'Detailed Update'!B:C,2,FALSE) -> 110kV SS Kar-2 | D90: Bander Khalid Al Qalah | E90: =VLOOKUP(B90,'Detailed Update'!B:D,3,FALSE) -> 45532 | F90: =VLOOKUP(B90,'Detailed Update'!B:T,4,FALSE) -> 0.93 | G90: =VLOOKUP(B90,'Detailed Update'!B:T,5,FALSE) -> 0.9 | H90: =G90-F90 -> -0.03 | I90: =VLOOKUP(B90,'Detailed Update'!B:I,6,FALSE) -> Masar | J90: =VLOOKUP(B90,'Detailed Update'!B:I,7,FALSE) -> Western | K90: =VLOOKUP(B90,'Detailed Update'!B:I,8,FALSE) -> Makkah | L90: Under Approval | M90: =VLOOKUP(B90,'Detailed Update'!B:T,11,FALSE) -> 46139 | N90: =VLOOKUP(B90,'Detailed Update'!B:T,12,FALSE) -> 46323 | O90: =VLOOKUP(B90,'Detailed Update'!B:T,13,FALSE) -> 46323 | P90: =VLOOKUP(B90,'Detailed Update'!B:U,20,FALSE) -> 1) Delay in Mechanical materials i.e. HVAC system (PACU), Expected material delivery by Mid Aug-26 due to current Geo-political instability.
